Workbook

Sheet 00_Inputs
C2: MODELO NEXUM - INPUTS DEL MANDATO
C3: Moneda funcional USD. Los porcentajes de cartera serán resultados del optimizador.
C5: Estado de la hoja | D5: =IF(AND(D17>0,D18>0,D24>0,D25>=0,D26>0,COUNTBLANK(E33:E36)=0),"COMPLETA PARA 01_FLUJOS","REVISAR INPUTS")
C7: Convención: amarillo = input editable; verde = fórmula; gris = política o dato descriptivo.
C9: 1. CONFIGURACIÓN DEL MODELO
C10: Parámetro | D10: Valor | E10: Unidad | F10: Clasificación | G10: Fuente | H10: Tratamiento
C11: Moneda funcional | D11: USD | E11: Moneda | F11: Política | G11: Informe Estrategia de Inversión, Grupo 11 | H11: Todos los cálculos se expresarán en USD
C12: Fecha de corte | D12: 46245 | E12: Fecha | F12: Input | G12: Confirmado por el usuario | H12: Fecha asociada a los tipos de cambio iniciales
C13: Escenario central | D13: Base contractual | E13: Escenario | F13: Política | G13: Caso e IPS | H13: 19 aportes; objetivos en dinero de hoy
C14: Base de medición | D14: USD reales | E14: Unidad | F14: Política | G14: Informe Estrategia de Inversión, Grupo 11 | H14: Dólares de la fecha de corte
C15: 2. TIPOS DE CAMBIO
C16: Parámetro | D16: Valor | E16: Unidad | F16: Clasificación | G16: Fuente | H16: Fórmula / tratamiento
C17: USD/CLP | D17: 911.77 | E17: CLP por USD | F17: Input | G17: Valor confirmado por el usuario | H17: Celda actualizable
C18: UF/CLP | D18: 40846 | E18: CLP por UF | F18: Input | G18: Valor confirmado por el usuario | H18: Celda actualizable
C19: USD por UF | D19: =D18/D17 | E19: USD por UF | F19: Calculado | G19: Derivado de tipos de cambio | H19: UF/CLP dividido por USD/CLP
C20: USD por CLP | D20: =1/D17 | E20: USD por CLP | F20: Calculado | G20: Derivado de USD/CLP | H20: Inverso de USD/CLP
C22: 3. CAPITAL Y APORTES
C23: Parámetro | D23: Valor | E23: Unidad | F23: Clasificación | G23: Fuente | H23: Tratamiento
C24: Capital inicial | D24: 150000 | E24: USD | F24: Dato del caso | G24: IPS, sección Perfil del Cliente | H24: Entrada en el año 0
C25: Aporte anual de Tomás | D25: 10000 | E25: USD | F25: Dato del caso | G25: IPS, sección Perfil del Cliente | H25: Aporte en abril de cada año
C26: Cantidad de aportes | D26: 19 | E26: Años | F26: Dato del caso | G26: IPS, sección Perfil del Cliente | H26: Escenario central contractual
C27: Primer año de aporte | D27: 1 | E27: Año | F27: Supuesto temporal | G27: Metodología del modelo | H27: Primer aporte posterior al capital inicial
C28: Mes del aporte | D28: Abril | E28: Mes | F28: Dato del caso | G28: IPS, sección Perfil del Cliente | H28: Se detallará al usar fechas exactas
C29: Aportes futuros sin capitalizar | D29: =D25*D26 | E29: USD | F29: Calculado | G29: Capital y aportes | H29: Aporte anual por cantidad de aportes
C31: 4. OBJETIVOS FINANCIEROS
C32: Prioridad | D32: Objetivo | E32: Monto original | F32: Moneda | G32: Primer año | H32: Último año | I32: N° pagos | J32: Total en USD | K32: Pago por evento USD | L32: Fuente / tratamiento
C33: 1 | D33: Educación Vicente | E33: 65000000 | F33: CLP | G33: 14 | H33: 18 | I33: 5 | J33: =E33/$D$17 | K33: =J33/I33 | L33: IPS: CLP 65 millones en dinero de hoy
C34: 1 | D34: Educación Emilia | E34: 65000000 | F34: CLP | G34: 16 | H34: 20 | I34: 5 | J34: =E34/$D$17 | K34: =J34/I34 | L34: IPS: CLP 65 millones en dinero de hoy
C35: 2 | D35: Propiedad en Villarrica | E35: 10500 | F35: UF | G35: 25 | H35: 25 | I35: 1 | J35: =E35*$D$19 | K35: =J35/I35 | L35: Desembolso adicional; el resto se financia con venta de la casa
C36: 3 | D36: Herencia familiar | E36: 500000 | F36: USD | G36: 50 | H36: 50 | I36: 1 | J36: =E36 | K36: =J36/I36 | L36: USD 250.000 por hijo
C38: Resumen sin descuento | D38: Valor | E38: Unidad | F38: Interpretación
C39: Educación total | D39: =SUM(J33:J34) | E39: USD | F39: Dos carreras completas
C40: Objetivos totales | D40: =SUM(J33:J36) | E40: USD | F40: Suma nominal real; no incorpora tiempos
C41: Capital más aportes | D41: =D24+D29 | E41: USD | F41: Suma sin capitalización; no mide suficiencia
C43: 5. RESTRICCIONES Y POLÍTICAS DEL IPS
C44: Restricción | D44: Valor | E44: Unidad | F44: Uso futuro | G44: Fuente | H44: Observación
C45: Tracking Error máximo cartera activa | D45: 0.04 | E45: % anual | F45: Optimizer / control | G45: IPS, Métricas de riesgo | H45: Se validará empíricamente
C46: Fondo de emergencia dentro del mandato | D46: No | E46: Política | F46: Flujos | G46: IPS, Escenarios de estrés | H46: La caja interna será liquidez operativa
C47: Instrumentos compatibles con StockTrak | D47: Sí | E47: Política | F47: Universo de activos | G47: IPS, Restricciones | H47: Condición de elegibilidad
C48: Uso puramente especulativo | D48: No permitido | E48: Política | F48: Universo de activos | G48: IPS, Restricciones | H48: Aplica a cortos, margen y derivados
C49: Prioridad 1 | D49: Educación | E49: Objetivo | F49: Monte Carlo | G49: IPS | H49: Objetivo crítico
C50: Prioridad 2 | D50: Propiedad | E50: Objetivo | F50: Monte Carlo | G50: Caso y estrategia corregida | H50: Admite ajuste antes que educación
C51: Prioridad 3 | D51: Herencia | E51: Objetivo | F51: Monte Carlo | G51: Caso y estrategia corregida | H51: Objetivo flexible
C53: 6. SUPUESTOS PROVISIONALES PARA SENSIBILIDAD
C54: Supuesto | D54: Caso central | E54: Unidad | F54: Estado | G54: Uso futuro | H54: Observación
C55: Crecimiento real adicional de educación | D55: 0 | E55: % anual | F55: Provisional | G55: Flujos / sensibilidad | H55: Caso central en dinero de hoy
C56: Interrupción de aportes | D56: 0 | E56: Años omitidos | F56: Solo estrés | G56: Stress testing | H56: El caso central conserva 19 aportes
C57: Pesos de cartera | D57: No definidos | E57: Resultado | F57: Borrador disponible en 09_Optimizador_Cartera (Solver) | G57: Optimizer | H57: D57 se mantiene "No definidos": los pesos siguen siendo un output a validar, nunca un input del modelo
C59: 7. CONTROLES DE INTEGRIDAD
C60: Control | D60: Resultado | E60: Tolerancia / condición | F60: Interpretación
C61: Conversión UF a USD | D61: =IF(ABS(D19-D18/D17)<0.000001,"OK","ERROR") | E61: 0,000001 | F61: UF/CLP dividido por USD/CLP
C62: Horizonte pagos educación | D62: =IF(AND(H33-G33+1=I33,H34-G34+1=I34),"OK","ERROR") | E62: 5 pagos por hijo | F62: Primer y último año consistentes
C63: Aportes contractuales | D63: =IF(AND(D26=19,D29=D25*D26),"OK","ERROR") | E63: 19 aportes | F63: USD 10.000 anuales
C64: Propiedad sin doble conteo | D64: OK | E64: Casa fuera de los inflows | F64: Las 10.500 UF son el desembolso adicional
C65: Pesos no prefijados | D65: =IF(D57="No definidos","OK","ERROR") | E65: Sin porcentajes | F65: Se determinarán con el modelo
C68: 8. REFERENCIA PROVISIONAL PARA VALORIZAR PASIVOS
C69: Parámetro | D69: Valor | E69: Unidad | F69: Clasificación | G69: Fuente | H69: Tratamiento
C70: Treasury 10 años nominal | D70: 0.04619 | E70: % anual | F70: Input provisional | G70: Informe Estrategia de Inversión, Grupo 11 | H70: Proxy hasta construir curva LDI
C71: Inflación de largo plazo | D71: 0.02 | E71: % anual | F71: Input provisional | G71: Informe Estrategia de Inversión, Grupo 11 | H71: Supuesto de inflación
C72: Tasa real LDI de referencia | D72: =(1+D70)/(1+D71)-1 | E72: % anual real | F72: Calculado | G72: Ecuación de Fisher | H72: (1 + tasa nominal) / (1 + inflación) - 1
C73: Estado del supuesto | D73: Provisional | E73: Estado | F73: Control | G73: Metodología | H73: Se validará en 03_LDI

Sheet 01_Flujos
C2: MODELO NEXUM - CALENDARIO DE FLUJOS
C3: Convención: entradas positivas; desembolsos negativos. Flujos anuales en USD reales.
C5: Total entradas | D5: =SUM(D10:E60) | F5: Total desembolsos | G5: =-SUM(F10:I60) | I5: Flujo neto sin descuento | J5: =SUM(J10:J60)
C6: Capital + aportes | D6: ='00_Inputs'!D41 | F6: Objetivos sin descuento | G6: ='00_Inputs'!D40 | I6: Horizonte | J6: 50
C8: FLUJOS DEL ESCENARIO CENTRAL | N8: CONTROLES DE RECONCILIACIÓN
C9: Año | D9: Capital inicial | E9: Aporte anual | F9: Educación Vicente | G9: Educación Emilia | H9: Propiedad Villarrica | I9: Herencia | J9: Flujo neto | K9: Acumulado sin retorno | L9: Evento principal | N9: Control | O9: Flujos | P9: Inputs | Q9: Diferencia
C10: 0 | D10: =IF(C10=0,'00_Inputs'!$D$24,0) | E10: =IF(AND(C10>='00_Inputs'!$D$27,C10<'00_Inputs'!$D$27+'00_Inputs'!$D$26),'00_Inputs'!$D$25,0) | F10: =IF(AND(C10>='00_Inputs'!$G$33,C10<='00_Inputs'!$H$33),-'00_Inputs'!$K$33*(1+'00_Inputs'!$D$55)^C10,0) | G10: =IF(AND(C10>='00_Inputs'!$G$34,C10<='00_Inputs'!$H$34),-'00_Inputs'!$K$34*(1+'00_Inputs'!$D$55)^C10,0) | H10: =IF(C10='00_Inputs'!$G$35,-'00_Inputs'!$J$35,0) | I10: =IF(C10='00_Inputs'!$G$36,-'00_Inputs'!$J$36,0) | J10: =SUM(D10:I10) | K10: =J10 | L10: =IF(C10=0,"Capital inicial",IF(AND(F10<0,G10<0),"Educación de ambos hijos",IF(F10<0,"Educación Vicente",IF(G10<0,"Educación Emilia",IF(H10<0,"Compra Villarrica",IF(I10<0,"Pago herencia",IF(E10>0,"Aporte anual",""))))))) | N10: Capital inicial | O10: =SUM(D10:D60) | P10: ='00_Inputs'!D24 | Q10: =O10-P10
C11: 1 | D11: =IF(C11=0,'00_Inputs'!$D$24,0) | E11: =IF(AND(C11>='00_Inputs'!$D$27,C11<'00_Inputs'!$D$27+'00_Inputs'!$D$26),'00_Inputs'!$D$25,0) | F11: =IF(AND(C11>='00_Inputs'!$G$33,C11<='00_Inputs'!$H$33),-'00_Inputs'!$K$33*(1+'00_Inputs'!$D$55)^C11,0) | G11: =IF(AND(C11>='00_Inputs'!$G$34,C11<='00_Inputs'!$H$34),-'00_Inputs'!$K$34*(1+'00_Inputs'!$D$55)^C11,0) | H11: =IF(C11='00_Inputs'!$G$35,-'00_Inputs'!$J$35,0) | I11: =IF(C11='00_Inputs'!$G$36,-'00_Inputs'!$J$36,0) | J11: =SUM(D11:I11) | K11: =K10+J11 | L11: =IF(C11=0,"Capital inicial",IF(AND(F11<0,G11<0),"Educación de ambos hijos",IF(F11<0,"Educación Vicente",IF(G11<0,"Educación Emilia",IF(H11<0,"Compra Villarrica",IF(I11<0,"Pago herencia",IF(E11>0,"Aporte anual",""))))))) | N11: Aportes | O11: =SUM(E10:E60) | P11: ='00_Inputs'!D29 | Q11: =O11-P11
C12: 2 | D12: =IF(C12=0,'00_Inputs'!$D$24,0) | E12: =IF(AND(C12>='00_Inputs'!$D$27,C12<'00_Inputs'!$D$27+'00_Inputs'!$D$26),'00_Inputs'!$D$25,0) | F12: =IF(AND(C12>='00_Inputs'!$G$33,C12<='00_Inputs'!$H$33),-'00_Inputs'!$K$33*(1+'00_Inputs'!$D$55)^C12,0) | G12: =IF(AND(C12>='00_Inputs'!$G$34,C12<='00_Inputs'!$H$34),-'00_Inputs'!$K$34*(1+'00_Inputs'!$D$55)^C12,0) | H12: =IF(C12='00_Inputs'!$G$35,-'00_Inputs'!$J$35,0) | I12: =IF(C12='00_Inputs'!$G$36,-'00_Inputs'!$J$36,0) | J12: =SUM(D12:I12) | K12: =K11+J12 | L12: =IF(C12=0,"Capital inicial",IF(AND(F12<0,G12<0),"Educación de ambos hijos",IF(F12<0,"Educación Vicente",IF(G12<0,"Educación Emilia",IF(H12<0,"Compra Villarrica",IF(I12<0,"Pago herencia",IF(E12>0,"Aporte anual",""))))))) | N12: Educación | O12: =-SUM(F10:G60) | P12: ='00_Inputs'!D39 | Q12: =O12-P12
C13: 3 | D13: =IF(C13=0,'00_Inputs'!$D$24,0) | E13: =IF(AND(C13>='00_Inputs'!$D$27,C13<'00_Inputs'!$D$27+'00_Inputs'!$D$26),'00_Inputs'!$D$25,0) | F13: =IF(AND(C13>='00_Inputs'!$G$33,C13<='00_Inputs'!$H$33),-'00_Inputs'!$K$33*(1+'00_Inputs'!$D$55)^C13,0) | G13: =IF(AND(C13>='00_Inputs'!$G$34,C13<='00_Inputs'!$H$34),-'00_Inputs'!$K$34*(1+'00_Inputs'!$D$55)^C13,0) | H13: =IF(C13='00_Inputs'!$G$35,-'00_Inputs'!$J$35,0) | I13: =IF(C13='00_Inputs'!$G$36,-'00_Inputs'!$J$36,0) | J13: =SUM(D13:I13) | K13: =K12+J13 | L13: =IF(C13=0,"Capital inicial",IF(AND(F13<0,G13<0),"Educación de ambos hijos",IF(F13<0,"Educación Vicente",IF(G13<0,"Educación Emilia",IF(H13<0,"Compra Villarrica",IF(I13<0,"Pago herencia",IF(E13>0,"Aporte anual",""))))))) | N13: Propiedad | O13: =-SUM(H10:H60) | P13: ='00_Inputs'!J35 | Q13: =O13-P13
C14: 4 | D14: =IF(C14=0,'00_Inputs'!$D$24,0) | E14: =IF(AND(C14>='00_Inputs'!$D$27,C14<'00_Inputs'!$D$27+'00_Inputs'!$D$26),'00_Inputs'!$D$25,0) | F14: =IF(AND(C14>='00_Inputs'!$G$33,C14<='00_Inputs'!$H$33),-'00_Inputs'!$K$33*(1+'00_Inputs'!$D$55)^C14,0) | G14: =IF(AND(C14>='00_Inputs'!$G$34,C14<='00_Inputs'!$H$34),-'00_Inputs'!$K$34*(1+'00_Inputs'!$D$55)^C14,0) | H14: =IF(C14='00_Inputs'!$G$35,-'00_Inputs'!$J$35,0) | I14: =IF(C14='00_Inputs'!$G$36,-'00_Inputs'!$J$36,0) | J14: =SUM(D14:I14) | K14: =K13+J14 | L14: =IF(C14=0,"Capital inicial",IF(AND(F14<0,G14<0),"Educación de ambos hijos",IF(F14<0,"Educación Vicente",IF(G14<0,"Educación Emilia",IF(H14<0,"Compra Villarrica",IF(I14<0,"Pago herencia",IF(E14>0,"Aporte anual",""))))))) | N14: Herencia | O14: =-SUM(I10:I60) | P14: ='00_Inputs'!J36 | Q14: =O14-P14
C15: 5 | D15: =IF(C15=0,'00_Inputs'!$D$24,0) | E15: =IF(AND(C15>='00_Inputs'!$D$27,C15<'00_Inputs'!$D$27+'00_Inputs'!$D$26),'00_Inputs'!$D$25,0) | F15: =IF(AND(C15>='00_Inputs'!$G$33,C15<='00_Inputs'!$H$33),-'00_Inputs'!$K$33*(1+'00_Inputs'!$D$55)^C15,0) | G15: =IF(AND(C15>='00_Inputs'!$G$34,C15<='00_Inputs'!$H$34),-'00_Inputs'!$K$34*(1+'00_Inputs'!$D$55)^C15,0) | H15: =IF(C15='00_Inputs'!$G$35,-'00_Inputs'!$J$35,0) | I15: =IF(C15='00_Inputs'!$G$36,-'00_Inputs'!$J$36,0) | J15: =SUM(D15:I15) | K15: =K14+J15 | L15: =IF(C15=0,"Capital inicial",IF(AND(F15<0,G15<0),"Educación de ambos hijos",IF(F15<0,"Educación Vicente",IF(G15<0,"Educación Emilia",IF(H15<0,"Compra Villarrica",IF(I15<0,"Pago herencia",IF(E15>0,"Aporte anual",""))))))) | N15: Flujo neto | O15: =SUM(J10:J60) | P15: =SUM(D10:I60) | Q15: =O15-P15
C16: 6 | D16: =IF(C16=0,'00_Inputs'!$D$24,0) | E16: =IF(AND(C16>='00_Inputs'!$D$27,C16<'00_Inputs'!$D$27+'00_Inputs'!$D$26),'00_Inputs'!$D$25,0) | F16: =IF(AND(C16>='00_Inputs'!$G$33,C16<='00_Inputs'!$H$33),-'00_Inputs'!$K$33*(1+'00_Inputs'!$D$55)^C16,0) | G16: =IF(AND(C16>='00_Inputs'!$G$34,C16<='00_Inputs'!$H$34),-'00_Inputs'!$K$34*(1+'00_Inputs'!$D$55)^C16,0) | H16: =IF(C16='00_Inputs'!$G$35,-'00_Inputs'!$J$35,0) | I16: =IF(C16='00_Inputs'!$G$36,-'00_Inputs'!$J$36,0) | J16: =SUM(D16:I16) | K16: =K15+J16 | L16: =IF(C16=0,"Capital inicial",IF(AND(F16<0,G16<0),"Educación de ambos hijos",IF(F16<0,"Educación Vicente",IF(G16<0,"Educación Emilia",IF(H16<0,"Compra Villarrica",IF(I16<0,"Pago herencia",IF(E16>0,"Aporte anual","")))))))
C17: 7 | D17: =IF(C17=0,'00_Inputs'!$D$24,0) | E17: =IF(AND(C17>='00_Inputs'!$D$27,C17<'00_Inputs'!$D$27+'00_Inputs'!$D$26),'00_Inputs'!$D$25,0) | F17: =IF(AND(C17>='00_Inputs'!$G$33,C17<='00_Inputs'!$H$33),-'00_Inputs'!$K$33*(1+'00_Inputs'!$D$55)^C17,0) | G17: =IF(AND(C17>='00_Inputs'!$G$34,C17<='00_Inputs'!$H$34),-'00_Inputs'!$K$34*(1+'00_Inputs'!$D$55)^C17,0) | H17: =IF(C17='00_Inputs'!$G$35,-'00_Inputs'!$J$35,0) | I17: =IF(C17='00_Inputs'!$G$36,-'00_Inputs'!$J$36,0) | J17: =SUM(D17:I17) | K17: =K16+J17 | L17: =IF(C17=0,"Capital inicial",IF(AND(F17<0,G17<0),"Educación de ambos hijos",IF(F17<0,"Educación Vicente",IF(G17<0,"Educación Emilia",IF(H17<0,"Compra Villarrica",IF(I17<0,"Pago herencia",IF(E17>0,"Aporte anual","")))))))
C18: 8 | D18: =IF(C18=0,'00_Inputs'!$D$24,0) | E18: =IF(AND(C18>='00_Inputs'!$D$27,C18<'00_Inputs'!$D$27+'00_Inputs'!$D$26),'00_Inputs'!$D$25,0) | F18: =IF(AND(C18>='00_Inputs'!$G$33,C18<='00_Inputs'!$H$33),-'00_Inputs'!$K$33*(1+'00_Inputs'!$D$55)^C18,0) | G18: =IF(AND(C18>='00_Inputs'!$G$34,C18<='00_Inputs'!$H$34),-'00_Inputs'!$K$34*(1+'00_Inputs'!$D$55)^C18,0) | H18: =IF(C18='00_Inputs'!$G$35,-'00_Inputs'!$J$35,0) | I18: =IF(C18='00_Inputs'!$G$36,-'00_Inputs'!$J$36,0) | J18: =SUM(D18:I18) | K18: =K17+J18 | L18: =IF(C18=0,"Capital inicial",IF(AND(F18<0,G18<0),"Educación de ambos hijos",IF(F18<0,"Educación Vicente",IF(G18<0,"Educación Emilia",IF(H18<0,"Compra Villarrica",IF(I18<0,"Pago herencia",IF(E18>0,"Aporte anual",""))))))) | N18: SUPUESTOS DE TEMPORIZACIÓN
C19: 9 | D19: =IF(C19=0,'00_Inputs'!$D$24,0) | E19: =IF(AND(C19>='00_Inputs'!$D$27,C19<'00_Inputs'!$D$27+'00_Inputs'!$D$26),'00_Inputs'!$D$25,0) | F19: =IF(AND(C19>='00_Inputs'!$G$33,C19<='00_Inputs'!$H$33),-'00_Inputs'!$K$33*(1+'00_Inputs'!$D$55)^C19,0) | G19: =IF(AND(C19>='00_Inputs'!$G$34,C19<='00_Inputs'!$H$34),-'00_Inputs'!$K$34*(1+'00_Inputs'!$D$55)^C19,0) | H19: =IF(C19='00_Inputs'!$G$35,-'00_Inputs'!$J$35,0) | I19: =IF(C19='00_Inputs'!$G$36,-'00_Inputs'!$J$36,0) | J19: =SUM(D19:I19) | K19: =K18+J19 | L19: =IF(C19=0,"Capital inicial",IF(AND(F19<0,G19<0),"Educación de ambos hijos",IF(F19<0,"Educación Vicente",IF(G19<0,"Educación Emilia",IF(H19<0,"Compra Villarrica",IF(I19<0,"Pago herencia",IF(E19>0,"Aporte anual",""))))))) | N19: Frecuencia | O19: Anual | Q19: Misma convención que el Banco de Información
C20: 10 | D20: =IF(C20=0,'00_Inputs'!$D$24,0) | E20: =IF(AND(C20>='00_Inputs'!$D$27,C20<'00_Inputs'!$D$27+'00_Inputs'!$D$26),'00_Inputs'!$D$25,0) | F20: =IF(AND(C20>='00_Inputs'!$G$33,C20<='00_Inputs'!$H$33),-'00_Inputs'!$K$33*(1+'00_Inputs'!$D$55)^C20,0) | G20: =IF(AND(C20>='00_Inputs'!$G$34,C20<='00_Inputs'!$H$34),-'00_Inputs'!$K$34*(1+'00_Inputs'!$D$55)^C20,0) | H20: =IF(C20='00_Inputs'!$G$35,-'00_Inputs'!$J$35,0) | I20: =IF(C20='00_Inputs'!$G$36,-'00_Inputs'!$J$36,0) | J20: =SUM(D20:I20) | K20: =K19+J20 | L20: =IF(C20=0,"Capital inicial",IF(AND(F20<0,G20<0),"Educación de ambos hijos",IF(F20<0,"Educación Vicente",IF(G20<0,"Educación Emilia",IF(H20<0,"Compra Villarrica",IF(I20<0,"Pago herencia",IF(E20>0,"Aporte anual",""))))))) | N20: Momento del flujo | O20: Fin de año | Q20: Se usará IRR sobre años 0 a 50
C21: 11 | D21: =IF(C21=0,'00_Inputs'!$D$24,0) | E21: =IF(AND(C21>='00_Inputs'!$D$27,C21<'00_Inputs'!$D$27+'00_Inputs'!$D$26),'00_Inputs'!$D$25,0) | F21: =IF(AND(C21>='00_Inputs'!$G$33,C21<='00_Inputs'!$H$33),-'00_Inputs'!$K$33*(1+'00_Inputs'!$D$55)^C21,0) | G21: =IF(AND(C21>='00_Inputs'!$G$34,C21<='00_Inputs'!$H$34),-'00_Inputs'!$K$34*(1+'00_Inputs'!$D$55)^C21,0) | H21: =IF(C21='00_Inputs'!$G$35,-'00_Inputs'!$J$35,0) | I21: =IF(C21='00_Inputs'!$G$36,-'00_Inputs'!$J$36,0) | J21: =SUM(D21:I21) | K21: =K20+J21 | L21: =IF(C21=0,"Capital inicial",IF(AND(F21<0,G21<0),"Educación de ambos hijos",IF(F21<0,"Educación Vicente",IF(G21<0,"Educación Emilia",IF(H21<0,"Compra Villarrica",IF(I21<0,"Pago herencia",IF(E21>0,"Aporte anual",""))))))) | N21: Aportes | O21: Años 1 a 19 | Q21: USD 10.000 por año
C22: 12 | D22: =IF(C22=0,'00_Inputs'!$D$24,0) | E22: =IF(AND(C22>='00_Inputs'!$D$27,C22<'00_Inputs'!$D$27+'00_Inputs'!$D$26),'00_Inputs'!$D$25,0) | F22: =IF(AND(C22>='00_Inputs'!$G$33,C22<='00_Inputs'!$H$33),-'00_Inputs'!$K$33*(1+'00_Inputs'!$D$55)^C22,0) | G22: =IF(AND(C22>='00_Inputs'!$G$34,C22<='00_Inputs'!$H$34),-'00_Inputs'!$K$34*(1+'00_Inputs'!$D$55)^C22,0) | H22: =IF(C22='00_Inputs'!$G$35,-'00_Inputs'!$J$35,0) | I22: =IF(C22='00_Inputs'!$G$36,-'00_Inputs'!$J$36,0) | J22: =SUM(D22:I22) | K22: =K21+J22 | L22: =IF(C22=0,"Capital inicial",IF(AND(F22<0,G22<0),"Educación de ambos hijos",IF(F22<0,"Educación Vicente",IF(G22<0,"Educación Emilia",IF(H22<0,"Compra Villarrica",IF(I22<0,"Pago herencia",IF(E22>0,"Aporte anual",""))))))) | N22: Educación | O22: 5 pagos por hijo | Q22: Vicente 14-18; Emilia 16-20
C23: 13 | D23: =IF(C23=0,'00_Inputs'!$D$24,0) | E23: =IF(AND(C23>='00_Inputs'!$D$27,C23<'00_Inputs'!$D$27+'00_Inputs'!$D$26),'00_Inputs'!$D$25,0) | F23: =IF(AND(C23>='00_Inputs'!$G$33,C23<='00_Inputs'!$H$33),-'00_Inputs'!$K$33*(1+'00_Inputs'!$D$55)^C23,0) | G23: =IF(AND(C23>='00_Inputs'!$G$34,C23<='00_Inputs'!$H$34),-'00_Inputs'!$K$34*(1+'00_Inputs'!$D$55)^C23,0) | H23: =IF(C23='00_Inputs'!$G$35,-'00_Inputs'!$J$35,0) | I23: =IF(C23='00_Inputs'!$G$36,-'00_Inputs'!$J$36,0) | J23: =SUM(D23:I23) | K23: =K22+J23 | L23: =IF(C23=0,"Capital inicial",IF(AND(F23<0,G23<0),"Educación de ambos hijos",IF(F23<0,"Educación Vicente",IF(G23<0,"Educación Emilia",IF(H23<0,"Compra Villarrica",IF(I23<0,"Pago herencia",IF(E23>0,"Aporte anual","")))))))
C24: 14 | D24: =IF(C24=0,'00_Inputs'!$D$24,0) | E24: =IF(AND(C24>='00_Inputs'!$D$27,C24<'00_Inputs'!$D$27+'00_Inputs'!$D$26),'00_Inputs'!$D$25,0) | F24: =IF(AND(C24>='00_Inputs'!$G$33,C24<='00_Inputs'!$H$33),-'00_Inputs'!$K$33*(1+'00_Inputs'!$D$55)^C24,0) | G24: =IF(AND(C24>='00_Inputs'!$G$34,C24<='00_Inputs'!$H$34),-'00_Inputs'!$K$34*(1+'00_Inputs'!$D$55)^C24,0) | H24: =IF(C24='00_Inputs'!$G$35,-'00_Inputs'!$J$35,0) | I24: =IF(C24='00_Inputs'!$G$36,-'00_Inputs'!$J$36,0) | J24: =SUM(D24:I24) | K24: =K23+J24 | L24: =IF(C24=0,"Capital inicial",IF(AND(F24<0,G24<0),"Educación de ambos hijos",IF(F24<0,"Educación Vicente",IF(G24<0,"Educación Emilia",IF(H24<0,"Compra Villarrica",IF(I24<0,"Pago herencia",IF(E24>0,"Aporte anual","")))))))
C25: 15 | D25: =IF(C25=0,'00_Inputs'!$D$24,0) | E25: =IF(AND(C25>='00_Inputs'!$D$27,C25<'00_Inputs'!$D$27+'00_Inputs'!$D$26),'00_Inputs'!$D$25,0) | F25: =IF(AND(C25>='00_Inputs'!$G$33,C25<='00_Inputs'!$H$33),-'00_Inputs'!$K$33*(1+'00_Inputs'!$D$55)^C25,0) | G25: =IF(AND(C25>='00_Inputs'!$G$34,C25<='00_Inputs'!$H$34),-'00_Inputs'!$K$34*(1+'00_Inputs'!$D$55)^C25,0) | H25: =IF(C25='00_Inputs'!$G$35,-'00_Inputs'!$J$35,0) | I25: =IF(C25='00_Inputs'!$G$36,-'00_Inputs'!$J$36,0) | J25: =SUM(D25:I25) | K25: =K24+J25 | L25: =IF(C25=0,"Capital inicial",IF(AND(F25<0,G25<0),"Educación de ambos hijos",IF(F25<0,"Educación Vicente",IF(G25<0,"Educación Emilia",IF(H25<0,"Compra Villarrica",IF(I25<0,"Pago herencia",IF(E25>0,"Aporte anual","")))))))
C26: 16 | D26: =IF(C26=0,'00_Inputs'!$D$24,0) | E26: =IF(AND(C26>='00_Inputs'!$D$27,C26<'00_Inputs'!$D$27+'00_Inputs'!$D$26),'00_Inputs'!$D$25,0) | F26: =IF(AND(C26>='00_Inputs'!$G$33,C26<='00_Inputs'!$H$33),-'00_Inputs'!$K$33*(1+'00_Inputs'!$D$55)^C26,0) | G26: =IF(AND(C26>='00_Inputs'!$G$34,C26<='00_Inputs'!$H$34),-'00_Inputs'!$K$34*(1+'00_Inputs'!$D$55)^C26,0) | H26: =IF(C26='00_Inputs'!$G$35,-'00_Inputs'!$J$35,0) | I26: =IF(C26='00_Inputs'!$G$36,-'00_Inputs'!$J$36,0) | J26: =SUM(D26:I26) | K26: =K25+J26 | L26: =IF(C26=0,"Capital inicial",IF(AND(F26<0,G26<0),"Educación de ambos hijos",IF(F26<0,"Educación Vicente",IF(G26<0,"Educación Emilia",IF(H26<0,"Compra Villarrica",IF(I26<0,"Pago herencia",IF(E26>0,"Aporte anual","")))))))
C27: 17 | D27: =IF(C27=0,'00_Inputs'!$D$24,0) | E27: =IF(AND(C27>='00_Inputs'!$D$27,C27<'00_Inputs'!$D$27+'00_Inputs'!$D$26),'00_Inputs'!$D$25,0) | F27: =IF(AND(C27>='00_Inputs'!$G$33,C27<='00_Inputs'!$H$33),-'00_Inputs'!$K$33*(1+'00_Inputs'!$D$55)^C27,0) | G27: =IF(AND(C27>='00_Inputs'!$G$34,C27<='00_Inputs'!$H$34),-'00_Inputs'!$K$34*(1+'00_Inputs'!$D$55)^C27,0) | H27: =IF(C27='00_Inputs'!$G$35,-'00_Inputs'!$J$35,0) | I27: =IF(C27='00_Inputs'!$G$36,-'00_Inputs'!$J$36,0) | J27: =SUM(D27:I27) | K27: =K26+J27 | L27: =IF(C27=0,"Capital inicial",IF(AND(F27<0,G27<0),"Educación de ambos hijos",IF(F27<0,"Educación Vicente",IF(G27<0,"Educación Emilia",IF(H27<0,"Compra Villarrica",IF(I27<0,"Pago herencia",IF(E27>0,"Aporte anual","")))))))
C28: 18 | D28: =IF(C28=0,'00_Inputs'!$D$24,0) | E28: =IF(AND(C28>='00_Inputs'!$D$27,C28<'00_Inputs'!$D$27+'00_Inputs'!$D$26),'00_Inputs'!$D$25,0) | F28: =IF(AND(C28>='00_Inputs'!$G$33,C28<='00_Inputs'!$H$33),-'00_Inputs'!$K$33*(1+'00_Inputs'!$D$55)^C28,0) | G28: =IF(AND(C28>='00_Inputs'!$G$34,C28<='00_Inputs'!$H$34),-'00_Inputs'!$K$34*(1+'00_Inputs'!$D$55)^C28,0) | H28: =IF(C28='00_Inputs'!$G$35,-'00_Inputs'!$J$35,0) | I28: =IF(C28='00_Inputs'!$G$36,-'00_Inputs'!$J$36,0) | J28: =SUM(D28:I28) | K28: =K27+J28 | L28: =IF(C28=0,"Capital inicial",IF(AND(F28<0,G28<0),"Educación de ambos hijos",IF(F28<0,"Educación Vicente",IF(G28<0,"Educación Emilia",IF(H28<0,"Compra Villarrica",IF(I28<0,"Pago herencia",IF(E28>0,"Aporte anual","")))))))
C29: 19 | D29: =IF(C29=0,'00_Inputs'!$D$24,0) | E29: =IF(AND(C29>='00_Inputs'!$D$27,C29<'00_Inputs'!$D$27+'00_Inputs'!$D$26),'00_Inputs'!$D$25,0) | F29: =IF(AND(C29>='00_Inputs'!$G$33,C29<='00_Inputs'!$H$33),-'00_Inputs'!$K$33*(1+'00_Inputs'!$D$55)^C29,0) | G29: =IF(AND(C29>='00_Inputs'!$G$34,C29<='00_Inputs'!$H$34),-'00_Inputs'!$K$34*(1+'00_Inputs'!$D$55)^C29,0) | H29: =IF(C29='00_Inputs'!$G$35,-'00_Inputs'!$J$35,0) | I29: =IF(C29='00_Inputs'!$G$36,-'00_Inputs'!$J$36,0) | J29: =SUM(D29:I29) | K29: =K28+J29 | L29: =IF(C29=0,"Capital inicial",IF(AND(F29<0,G29<0),"Educación de ambos hijos",IF(F29<0,"Educación Vicente",IF(G29<0,"Educación Emilia",IF(H29<0,"Compra Villarrica",IF(I29<0,"Pago herencia",IF(E29>0,"Aporte anual","")))))))
C30: 20 | D30: =IF(C30=0,'00_Inputs'!$D$24,0) | E30: =IF(AND(C30>='00_Inputs'!$D$27,C30<'00_Inputs'!$D$27+'00_Inputs'!$D$26),'00_Inputs'!$D$25,0) | F30: =IF(AND(C30>='00_Inputs'!$G$33,C30<='00_Inputs'!$H$33),-'00_Inputs'!$K$33*(1+'00_Inputs'!$D$55)^C30,0) | G30: =IF(AND(C30>='00_Inputs'!$G$34,C30<='00_Inputs'!$H$34),-'00_Inputs'!$K$34*(1+'00_Inputs'!$D$55)^C30,0) | H30: =IF(C30='00_Inputs'!$G$35,-'00_Inputs'!$J$35,0) | I30: =IF(C30='00_Inputs'!$G$36,-'00_Inputs'!$J$36,0) | J30: =SUM(D30:I30) | K30: =K29+J30 | L30: =IF(C30=0,"Capital inicial",IF(AND(F30<0,G30<0),"Educación de ambos hijos",IF(F30<0,"Educación Vicente",IF(G30<0,"Educación Emilia",IF(H30<0,"Compra Villarrica",IF(I30<0,"Pago herencia",IF(E30>0,"Aporte anual","")))))))
C31: 21 | D31: =IF(C31=0,'00_Inputs'!$D$24,0) | E31: =IF(AND(C31>='00_Inputs'!$D$27,C31<'00_Inputs'!$D$27+'00_Inputs'!$D$26),'00_Inputs'!$D$25,0) | F31: =IF(AND(C31>='00_Inputs'!$G$33,C31<='00_Inputs'!$H$33),-'00_Inputs'!$K$33*(1+'00_Inputs'!$D$55)^C31,0) | G31: =IF(AND(C31>='00_Inputs'!$G$34,C31<='00_Inputs'!$H$34),-'00_Inputs'!$K$34*(1+'00_Inputs'!$D$55)^C31,0) | H31: =IF(C31='00_Inputs'!$G$35,-'00_Inputs'!$J$35,0) | I31: =IF(C31='00_Inputs'!$G$36,-'00_Inputs'!$J$36,0) | J31: =SUM(D31:I31) | K31: =K30+J31 | L31: =IF(C31=0,"Capital inicial",IF(AND(F31<0,G31<0),"Educación de ambos hijos",IF(F31<0,"Educación Vicente",IF(G31<0,"Educación Emilia",IF(H31<0,"Compra Villarrica",IF(I31<0,"Pago herencia",IF(E31>0,"Aporte anual","")))))))
C32: 22 | D32: =IF(C32=0,'00_Inputs'!$D$24,0) | E32: =IF(AND(C32>='00_Inputs'!$D$27,C32<'00_Inputs'!$D$27+'00_Inputs'!$D$26),'00_Inputs'!$D$25,0) | F32: =IF(AND(C32>='00_Inputs'!$G$33,C32<='00_Inputs'!$H$33),-'00_Inputs'!$K$33*(1+'00_Inputs'!$D$55)^C32,0) | G32: =IF(AND(C32>='00_Inputs'!$G$34,C32<='00_Inputs'!$H$34),-'00_Inputs'!$K$34*(1+'00_Inputs'!$D$55)^C32,0) | H32: =IF(C32='00_Inputs'!$G$35,-'00_Inputs'!$J$35,0) | I32: =IF(C32='00_Inputs'!$G$36,-'00_Inputs'!$J$36,0) | J32: =SUM(D32:I32) | K32: =K31+J32 | L32: =IF(C32=0,"Capital inicial",IF(AND(F32<0,G32<0),"Educación de ambos hijos",IF(F32<0,"Educación Vicente",IF(G32<0,"Educación Emilia",IF(H32<0,"Compra Villarrica",IF(I32<0,"Pago herencia",IF(E32>0,"Aporte anual","")))))))
C33: 23 | D33: =IF(C33=0,'00_Inputs'!$D$24,0) | E33: =IF(AND(C33>='00_Inputs'!$D$27,C33<'00_Inputs'!$D$27+'00_Inputs'!$D$26),'00_Inputs'!$D$25,0) | F33: =IF(AND(C33>='00_Inputs'!$G$33,C33<='00_Inputs'!$H$33),-'00_Inputs'!$K$33*(1+'00_Inputs'!$D$55)^C33,0) | G33: =IF(AND(C33>='00_Inputs'!$G$34,C33<='00_Inputs'!$H$34),-'00_Inputs'!$K$34*(1+'00_Inputs'!$D$55)^C33,0) | H33: =IF(C33='00_Inputs'!$G$35,-'00_Inputs'!$J$35,0) | I33: =IF(C33='00_Inputs'!$G$36,-'00_Inputs'!$J$36,0) | J33: =SUM(D33:I33) | K33: =K32+J33 | L33: =IF(C33=0,"Capital inicial",IF(AND(F33<0,G33<0),"Educación de ambos hijos",IF(F33<0,"Educación Vicente",IF(G33<0,"Educación Emilia",IF(H33<0,"Compra Villarrica",IF(I33<0,"Pago herencia",IF(E33>0,"Aporte anual","")))))))
C34: 24 | D34: =IF(C34=0,'00_Inputs'!$D$24,0) | E34: =IF(AND(C34>='00_Inputs'!$D$27,C34<'00_Inputs'!$D$27+'00_Inputs'!$D$26),'00_Inputs'!$D$25,0) | F34: =IF(AND(C34>='00_Inputs'!$G$33,C34<='00_Inputs'!$H$33),-'00_Inputs'!$K$33*(1+'00_Inputs'!$D$55)^C34,0) | G34: =IF(AND(C34>='00_Inputs'!$G$34,C34<='00_Inputs'!$H$34),-'00_Inputs'!$K$34*(1+'00_Inputs'!$D$55)^C34,0) | H34: =IF(C34='00_Inputs'!$G$35,-'00_Inputs'!$J$35,0) | I34: =IF(C34='00_Inputs'!$G$36,-'00_Inputs'!$J$36,0) | J34: =SUM(D34:I34) | K34: =K33+J34 | L34: =IF(C34=0,"Capital inicial",IF(AND(F34<0,G34<0),"Educación de ambos hijos",IF(F34<0,"Educación Vicente",IF(G34<0,"Educación Emilia",IF(H34<0,"Compra Villarrica",IF(I34<0,"Pago herencia",IF(E34>0,"Aporte anual","")))))))
... C60: 50 | D60: =IF(C60=0,'00_Inputs'!$D$24,0) | E60: =IF(AND(C60>='00_Inputs'!$D$27,C60<'00_Inputs'!$D$27+'00_Inputs'!$D$26),'00_Inputs'!$D$25,0) | F60: =IF(AND(C60>='00_Inputs'!$G$33,C60<='00_Inputs'!$H$33),-'00_Inputs'!$K$33*(1+'00_Inputs'!$D$55)^C60,0) | G60: =IF(AND(C60>='00_Inputs'!$G$34,C60<='00_Inputs'!$H$34),-'00_Inputs'!$K$34*(1+'00_Inputs'!$D$55)^C60,0) | H60: =IF(C60='00_Inputs'!$G$35,-'00_Inputs'!$J$35,0) | I60: =IF(C60='00_Inputs'!$G$36,-'00_Inputs'!$J$36,0) | J60: =SUM(D60:I60) | K60: =K59+J60 | L60: =IF(C60=0,"Capital inicial",IF(AND(F60<0,G60<0),"Educación de ambos hijos",IF(F60<0,"Educación Vicente",IF(G60<0,"Educación Emilia",IF(H60<0,"Compra Villarrica",IF(I60<0,"Pago herencia",IF(E60>0,"Aporte anual","")))))))

Sheet 02_TIR_Objetivos
C2: MODELO NEXUM - RETORNOS MÍNIMOS REQUERIDOS
C3: Las tasas resuelven VPN = 0. No son retornos esperados ni garantizados de la cartera.
C5: 1. TIR GLOBAL DEL MANDATO | H5: 2. FONDEO LDI DE EDUCACIÓN | N5: CONTROLES
C6: TIR real requerida | D6: =IRR('01_Flujos'!J10:J60,0.045) | E6: % anual | F6: IRR de todos los flujos | H6: Tasa real LDI de referencia | I6: ='00_Inputs'!D72 | J6: % anual | K6: Proxy provisional | L6: Fisher: Treasury e inflación | N6: Control | O6: Resultado | P6: Tolerancia | Q6: Estado
C7: VP de entradas | D7: =SUM(G23:G73) | E7: USD | F7: Descontado a la TIR global | H7: Capital requerido hoy | I7: =SUM(J23:J73) | J7: USD | K7: VP de los diez pagos | L7: Resultado del modelo | N7: VPN global | O7: =D9 | P7: 0.01 | Q7: =IF(ABS(O7)<=P7,"OK","ERROR")
C8: VP de desembolsos | D8: =SUM(H23:H73) | E8: USD | F8: Descontado a la TIR global | H8: Participación implícita inicial | I8: =I7/'00_Inputs'!D24 | J8: % capital inicial | K8: No es un peso prefijado | L8: Capital LDI / capital inicial | N8: VP entradas vs salidas | O8: =D7-D8 | P8: 0.01 | Q8: =IF(ABS(O8)<=P8,"OK","ERROR")
C9: Diferencia de VP | D9: =D7-D8 | E9: USD | F9: Debe ser 0 | H9: Capital inicial residual | I9: ='00_Inputs'!D24-I7 | J9: USD | K9: Capital para crecimiento | L9: Capital inicial menos LDI | N9: Funding educación | O9: =I10-1 | P9: 1e-06 | Q9: =IF(ABS(O9)<=P9,"OK","ERROR")
C10: Lectura | D10: =IF(ABS(D9)<0.01,"EQUILIBRIO VERIFICADO","REVISAR") | F10: Tasa de equilibrio del plan completo | H10: Funding ratio inicial | I10: =I7/I7 | J10: x | K10: Capital asignado / VP educación | L10: Debe ser 1,00x | N10: VPN crecimiento | O10: =D17 | P10: 0.01 | Q10: =IF(ABS(O10)<=P10,"OK","ERROR")
H11: Estado tasa LDI | I11: ='00_Inputs'!D73 | K11: Pendiente de validación | L11: Se revisará con curva e instrumentos | N11: Capital inicial asignado | O11: =I7+I9-'00_Inputs'!D24 | P11: 0.01 | Q11: =IF(ABS(O11)<=P11,"OK","ERROR")
C12: 3. BLOQUE DE CRECIMIENTO | N12: Tasas positivas | O12: =MIN(D6,I6,D16) | P12: 0 | Q12: =IF(O12>0,"OK","ERROR")
C13: Capital inicial residual | D13: =I9 | E13: USD | F13: Después de prefinanciar educación
C14: Aportes asignados | D14: ='00_Inputs'!D29 | E14: USD | F14: 19 aportes contractuales
C15: Objetivos financiados | D15: ='00_Inputs'!J35+'00_Inputs'!J36 | E15: USD | F15: Propiedad más herencia | N15: LECTURA METODOLÓGICA
C16: TIR real mínima del bloque | D16: =IRR(K23:K73,0.05) | E16: % anual | F16: IRR del flujo de crecimiento | N16: TIR global | O16: =D6 | Q16: Tasa de equilibrio de todos los flujos
C17: VPN del bloque a su TIR | D17: =SUM(L23:L73) | E17: USD | F17: Debe ser 0 | N17: Tasa LDI | O17: =I6 | Q17: Tasa de descuento provisional; no es output del IRR
C18: Diferencia frente a TIR global | D18: =(D16-D6)*100 | E18: p.p. | F18: Exigencia adicional del bloque | N18: Participación LDI | O18: =I8 | Q18: Resultado del VP de educación / capital inicial
N19: TIR crecimiento | O19: =D16 | Q19: Hurdle para propiedad y herencia con aportes
C21: COMPROBACIÓN DE VALOR PRESENTE POR AÑO
C22: Año | D22: Flujo global | E22: Factor descuento | F22: VP global | G22: VP entradas | H22: VP desembolsos | I22: Flujo educación | J22: VP educación | K22: Flujo crecimiento | L22: VP crecimiento
C23: ='01_Flujos'!C10 | D23: ='01_Flujos'!J10 | E23: =1/(1+$D$6)^C23 | F23: =D23*E23 | G23: =IF(F23>0,F23,0) | H23: =IF(F23<0,-F23,0) | I23: ='01_Flujos'!F10+'01_Flujos'!G10 | J23: =-I23/(1+$I$6)^C23 | K23: =$I$9 | L23: =K23/(1+$D$16)^C23
C24: ='01_Flujos'!C11 | D24: ='01_Flujos'!J11 | E24: =1/(1+$D$6)^C24 | F24: =D24*E24 | G24: =IF(F24>0,F24,0) | H24: =IF(F24<0,-F24,0) | I24: ='01_Flujos'!F11+'01_Flujos'!G11 | J24: =-I24/(1+$I$6)^C24 | K24: ='01_Flujos'!E11+'01_Flujos'!H11+'01_Flujos'!I11 | L24: =K24/(1+$D$16)^C24
C25: ='01_Flujos'!C12 | D25: ='01_Flujos'!J12 | E25: =1/(1+$D$6)^C25 | F25: =D25*E25 | G25: =IF(F25>0,F25,0) | H25: =IF(F25<0,-F25,0) | I25: ='01_Flujos'!F12+'01_Flujos'!G12 | J25: =-I25/(1+$I$6)^C25 | K25: ='01_Flujos'!E12+'01_Flujos'!H12+'01_Flujos'!I12 | L25: =K25/(1+$D$16)^C25
C26: ='01_Flujos'!C13 | D26: ='01_Flujos'!J13 | E26: =1/(1+$D$6)^C26 | F26: =D26*E26 | G26: =IF(F26>0,F26,0) | H26: =IF(F26<0,-F26,0) | I26: ='01_Flujos'!F13+'01_Flujos'!G13 | J26: =-I26/(1+$I$6)^C26 | K26: ='01_Flujos'!E13+'01_Flujos'!H13+'01_Flujos'!I13 | L26: =K26/(1+$D$16)^C26
C27: ='01_Flujos'!C14 | D27: ='01_Flujos'!J14 | E27: =1/(1+$D$6)^C27 | F27: =D27*E27 | G27: =IF(F27>0,F27,0) | H27: =IF(F27<0,-F27,0) | I27: ='01_Flujos'!F14+'01_Flujos'!G14 | J27: =-I27/(1+$I$6)^C27 | K27: ='01_Flujos'!E14+'01_Flujos'!H14+'01_Flujos'!I14 | L27: =K27/(1+$D$16)^C27
C28: ='01_Flujos'!C15 | D28: ='01_Flujos'!J15 | E28: =1/(1+$D$6)^C28 | F28: =D28*E28 | G28: =IF(F28>0,F28,0) | H28: =IF(F28<0,-F28,0) | I28: ='01_Flujos'!F15+'01_Flujos'!G15 | J28: =-I28/(1+$I$6)^C28 | K28: ='01_Flujos'!E15+'01_Flujos'!H15+'01_Flujos'!I15 | L28: =K28/(1+$D$16)^C28
C29: ='01_Flujos'!C16 | D29: ='01_Flujos'!J16 | E29: =1/(1+$D$6)^C29 | F29: =D29*E29 | G29: =IF(F29>0,F29,0) | H29: =IF(F29<0,-F29,0) | I29: ='01_Flujos'!F16+'01_Flujos'!G16 | J29: =-I29/(1+$I$6)^C29 | K29: ='01_Flujos'!E16+'01_Flujos'!H16+'01_Flujos'!I16 | L29: =K29/(1+$D$16)^C29
C30: ='01_Flujos'!C17 | D30: ='01_Flujos'!J17 | E30: =1/(1+$D$6)^C30 | F30: =D30*E30 | G30: =IF(F30>0,F30,0) | H30: =IF(F30<0,-F30,0) | I30: ='01_Flujos'!F17+'01_Flujos'!G17 | J30: =-I30/(1+$I$6)^C30 | K30: ='01_Flujos'!E17+'01_Flujos'!H17+'01_Flujos'!I17 | L30: =K30/(1+$D$16)^C30
C31: ='01_Flujos'!C18 | D31: ='01_Flujos'!J18 | E31: =1/(1+$D$6)^C31 | F31: =D31*E31 | G31: =IF(F31>0,F31,0) | H31: =IF(F31<0,-F31,0) | I31: ='01_Flujos'!F18+'01_Flujos'!G18 | J31: =-I31/(1+$I$6)^C31 | K31: ='01_Flujos'!E18+'01_Flujos'!H18+'01_Flujos'!I18 | L31: =K31/(1+$D$16)^C31
C32: ='01_Flujos'!C19 | D32: ='01_Flujos'!J19 | E32: =1/(1+$D$6)^C32 | F32: =D32*E32 | G32: =IF(F32>0,F32,0) | H32: =IF(F32<0,-F32,0) | I32: ='01_Flujos'!F19+'01_Flujos'!G19 | J32: =-I32/(1+$I$6)^C32 | K32: ='01_Flujos'!E19+'01_Flujos'!H19+'01_Flujos'!I19 | L32: =K32/(1+$D$16)^C32
C33: ='01_Flujos'!C20 | D33: ='01_Flujos'!J20 | E33: =1/(1+$D$6)^C33 | F33: =D33*E33 | G33: =IF(F33>0,F33,0) | H33: =IF(F33<0,-F33,0) | I33: ='01_Flujos'!F20+'01_Flujos'!G20 | J33: =-I33/(1+$I$6)^C33 | K33: ='01_Flujos'!E20+'01_Flujos'!H20+'01_Flujos'!I20 | L33: =K33/(1+$D$16)^C33
C34: ='01_Flujos'!C21 | D34: ='01_Flujos'!J21 | E34: =1/(1+$D$6)^C34 | F34: =D34*E34 | G34: =IF(F34>0,F34,0) | H34: =IF(F34<0,-F34,0) | I34: ='01_Flujos'!F21+'01_Flujos'!G21 | J34: =-I34/(1+$I$6)^C34 | K34: ='01_Flujos'!E21+'01_Flujos'!H21+'01_Flujos'!I21 | L34: =K34/(1+$D$16)^C34
C35: ='01_Flujos'!C22 | D35: ='01_Flujos'!J22 | E35: =1/(1+$D$6)^C35 | F35: =D35*E35 | G35: =IF(F35>0,F35,0) | H35: =IF(F35<0,-F35,0) | I35: ='01_Flujos'!F22+'01_Flujos'!G22 | J35: =-I35/(1+$I$6)^C35 | K35: ='01_Flujos'!E22+'01_Flujos'!H22+'01_Flujos'!I22 | L35: =K35/(1+$D$16)^C35
... C73: ='01_Flujos'!C60 | D73: ='01_Flujos'!J60 | E73: =1/(1+$D$6)^C73 | F73: =D73*E73 | G73: =IF(F73>0,F73,0) | H73: =IF(F73<0,-F73,0) | I73: ='01_Flujos'!F60+'01_Flujos'!G60 | J73: =-I73/(1+$I$6)^C73 | K73: ='01_Flujos'!E60+'01_Flujos'!H60+'01_Flujos'!I60 | L73: =K73/(1+$D$16)^C73

Sheet 03_LDI_Educacion
C2: MODELO NEXUM - LDI E INMUNIZACIÓN DE EDUCACIÓN
C3: Se evalúan valor presente, duración, convexidad, riesgo cambiario y factibilidad de calce.
C5: 1. PASIVO EDUCACIONAL | H5: 2. FACTIBILIDAD DEL CALCE
C6: Tasa real de descuento | D6: ='00_Inputs'!D72 | E6: % anual | F6: Proxy provisional LDI | H6: Duración modificada del pasivo | I6: =D9 | J6: Objetivo de sensibilidad a tasas
C7: Valor presente | D7: =SUM(H33:H39) | E7: USD | F7: Diez pagos educacionales | H7: Mayor duración LDI disponible | I7: =MAX(F17:F21) | J7: Máximo entre instrumentos elegibles
C8: Duración Macaulay | D8: =SUM(I33:I39)/D7 | E8: Años | F8: Promedio temporal ponderado por VP | H8: Brecha de duración | I8: =I7-I6 | J8: Activo máximo menos pasivo
C9: Duración modificada | D9: =D8/(1+D6) | E9: Años | F9: Sensibilidad aproximada a tasas | H9: Calce exacto factible | I9: =IF(I8>=0,"POSIBLE POR DURACIÓN","NO FACTIBLE CON VCLT/TLH/MM") | J9: Evaluación con instrumentos actuales
C10: Convexidad | D10: =SUM(J33:J39)/D7 | E10: Índice | F10: Curvatura del precio del pasivo | H10: Moneda de los pasivos | I10: CLP | J10: Obligación educacional local
C11: Capital asignado | D11: ='02_TIR_Objetivos'!I7 | E11: USD | F11: Capital requerido calculado | H11: Moneda de los activos LDI | I11: USD | J11: VCLT, TLH y Money Market
C12: Funding ratio | D12: =D11/D7 | E12: x | F12: Capital asignado / valor presente | H12: Riesgo cambiario | I12: ABIERTO | J12: Requiere cobertura o calce natural
C15: 3. INSTRUMENTOS CONSIDERADOS
C16: Componente | D16: Ticker | E16: Elegible LDI | F16: Duración efectiva | G16: Moneda | H16: Riesgo principal | I16: Fuente / fecha | J16: Estado | L16: Shock | M16: Tasa real | N16: VP educación | O16: Funding ratio | P16: Superávit / déficit
C17: Bonos corporativos largos | D17: VCLT | E17: Sí | F17: 13 | G17: USD | H17: Tasa + spread de crédito | I17: Estructura_Portafolio.pdf | J17: Provisional; actualizar con factsheet | L17: -0.02 | M17: =$D$6+L17 | N17: =SUMPRODUCT($F$33:$F$39/(1+M17)^$C$33:$C$39) | O17: =$D$11/N17 | P17: =$D$11-N17
C18: Treasuries 10-20 años | D18: TLH | E18: Sí | F18: 11.71 | G18: USD | H18: Tasa soberana | I18: iShares, 09-09-2026 | J18: Fuente oficial | L18: -0.01 | M18: =$D$6+L18 | N18: =SUMPRODUCT($F$33:$F$39/(1+M18)^$C$33:$C$39) | O18: =$D$11/N18 | P18: =$D$11-N18
C19: Money Market / T-Bills | D19: Por definir | E19: Sí | F19: 0.25 | G19: USD | H19: Reinversión | I19: Convención 3 meses | J19: Proxy | L19: 0 | M19: =$D$6+L19 | N19: =SUMPRODUCT($F$33:$F$39/(1+M19)^$C$33:$C$39) | O19: =$D$11/N19 | P19: =$D$11-N19
C20: Beta pasiva S&P 500 | D20: SPY o VOO | E20: No | G20: USD | H20: Renta variable | I20: Estrategia corregida | J20: Core pasivo; no inmuniza educación | L20: 0.01 | M20: =$D$6+L20 | N20: =SUMPRODUCT($F$33:$F$39/(1+M20)^$C$33:$C$39) | O20: =$D$11/N20 | P20: =$D$11-N20
C21: Treasury STRIPS largos | D21: GOVZ (proxy EDV) | E21: Sí | F21: 26.52 | G21: USD | H21: Tasa (alta sensibilidad, sin spread de crédito) | I21: Yahoo Finance (EDV), 10-sep-2026 / '04_Universo_Benchmarks'!J17 | J21: Agregado: faltaba en el listado pese a estar en 04_Universo_Benchmarks y disponible en 05_Datos_Historicos | L21: 0.02 | M21: =$D$6+L21 | N21: =SUMPRODUCT($F$33:$F$39/(1+M21)^$C$33:$C$39) | O21: =$D$11/N21 | P21: =$D$11-N21
C22: Conclusión | D22: Con GOVZ (duración 26,52 años) incorporado al conjunto de instrumentos, la duración máxima disponible (26,52) supera la duración modificada del pasivo (16,5); el calce es factible por duración.
C23: Implicancia | D23: Combinar VCLT, TLH y GOVZ (estrategia barbell) para igualar la duración del pasivo; ver pesos calculados en 09_Optimizador_Cartera.
C24: Restricción | D24: Antes de asignar capital, validar GOVZ como proxy de STRIPS (liquidez, tracking) y fijar un límite de concentración dado su alto riesgo de tasa. | L24: CONTROLES
L25: Control | M25: Resultado | N25: Referencia | O25: Diferencia | P25: Estado
L26: VP educación | M26: =D7 | N26: ='02_TIR_Objetivos'!I7 | O26: =M26-N26 | P26: =IF(ABS(O26)<0.01,"OK","ERROR")
L27: Funding ratio | M27: =D12 | N27: 1 | O27: =M27-N27 | P27: =IF(ABS(O27)<0.01,"OK","ERROR")
L28: Pagos totales | M28: =F40 | N28: ='00_Inputs'!D39 | O28: =M28-N28 | P28: =IF(ABS(O28)<0.01,"OK","ERROR")
L29: Duración positiva | M29: =D9 | N29: 0 | O29: =M29-N29 | P29: =IF(M29>0,"OK","ERROR")
L30: Factibilidad informada | M30: =IF(I9<>"",1,0) | N30: 1 | O30: =M30-N30 | P30: =IF(ABS(O30)<0.01,"OK","ERROR")
C31: CALENDARIO Y DURACIÓN DEL PASIVO
C32: Año | D32: Vicente | E32: Emilia | F32: Pago total | G32: Factor descuento | H32: Valor presente | I32: Año x VP | J32: Convexidad contrib.
C33: 14 | D33: =-'01_Flujos'!F24 | E33: =-'01_Flujos'!G24 | F33: =D33+E33 | G33: =1/(1+$D$6)^C33 | H33: =F33*G33 | I33: =C33*H33 | J33: =C33*(C33+1)*F33/(1+$D$6)^(C33+2)
C34: 15 | D34: =-'01_Flujos'!F25 | E34: =-'01_Flujos'!G25 | F34: =D34+E34 | G34: =1/(1+$D$6)^C34 | H34: =F34*G34 | I34: =C34*H34 | J34: =C34*(C34+1)*F34/(1+$D$6)^(C34+2)
C35: 16 | D35: =-'01_Flujos'!F26 | E35: =-'01_Flujos'!G26 | F35: =D35+E35 | G35: =1/(1+$D$6)^C35 | H35: =F35*G35 | I35: =C35*H35 | J35: =C35*(C35+1)*F35/(1+$D$6)^(C35+2)
C36: 17 | D36: =-'01_Flujos'!F27 | E36: =-'01_Flujos'!G27 | F36: =D36+E36 | G36: =1/(1+$D$6)^C36 | H36: =F36*G36 | I36: =C36*H36 | J36: =C36*(C36+1)*F36/(1+$D$6)^(C36+2)
C37: 18 | D37: =-'01_Flujos'!F28 | E37: =-'01_Flujos'!G28 | F37: =D37+E37 | G37: =1/(1+$D$6)^C37 | H37: =F37*G37 | I37: =C37*H37 | J37: =C37*(C37+1)*F37/(1+$D$6)^(C37+2)
C38: 19 | D38: =-'01_Flujos'!F29 | E38: =-'01_Flujos'!G29 | F38: =D38+E38 | G38: =1/(1+$D$6)^C38 | H38: =F38*G38 | I38: =C38*H38 | J38: =C38*(C38+1)*F38/(1+$D$6)^(C38+2)
C39: 20 | D39: =-'01_Flujos'!F30 | E39: =-'01_Flujos'!G30 | F39: =D39+E39 | G39: =1/(1+$D$6)^C39 | H39: =F39*G39 | I39: =C39*H39 | J39: =C39*(C39+1)*F39/(1+$D$6)^(C39+2)
C40: Total | F40: =SUM(F33:F39) | H40: =SUM(H33:H39) | I40: =SUM(I33:I39) | J40: =SUM(J33:J39)

Sheet 04_Universo_Benchmarks
C2: MODELO NEXUM - UNIVERSO ESTRATÉGICO Y BENCHMARKS
C3: Define las unidades que entrarán al optimizador y su medición. Los pesos todavía no se fijan: serán una salida de Markowitz/Solver.
C5: RESUMEN DEL UNIVERSO | H5: CRITERIO METODOLÓGICO
C6: Sleeves optimizables | D6: =COUNTIF(G15:G22,"Sí") | E6: unidades | F6: Cada fila es una serie de retorno | H6: Unidad de optimización | I6: Sleeve estratégico | K6: Evita mezclar acciones individuales con ETF
C7: Pasivos / core | D7: =COUNTIF(E15:E22,"Pasiva / core") | E7: unidades | F7: ETF o liquidez | H7: Frecuencia objetivo | I7: Mensual | K7: Retornos totales en USD
C8: Activos | D8: =COUNTIF(E15:E22,"Activa") | E8: unidades | F8: Estrategias sistemáticas | H8: ETF pasivos | I8: Total return | K8: Precio ajustado por distribuciones
C9: Elegibles LDI | D9: =COUNTIF(H15:H22,"Sí") | E9: unidades | F9: Tasa, crédito o caja | H9: Estrategias activas | I9: Backtest neto | K9: Serie construida con reglas ex ante
C10: Mayor duración disponible | D10: =MAX(J15:J22) | E10: años | F10: Incluye GOVZ candidato | H10: Pesos | I10: Borrador en 09_Optimizador_Cartera | K10: Sujeto a validar con Solver en Excel; ver limitaciones en esa hoja
C11: Brecha vs. pasivo | D11: =D10-'03_LDI_Educacion'!D9 | E11: años | F11: Máximo activo menos pasivo | H11: Benchmark de política | I11: Dinámico | K11: Suma de pesos finales × benchmarks
C13: 1. UNIVERSO PARA OPTIMIZACIÓN | O13: CONTROLES
C14: ID | D14: Sleeve estratégico | E14: Gestión | F14: Implementación base | G14: Optimizador | H14: LDI | I14: Moneda | J14: Duración | K14: Costo anual | L14: Serie requerida | M14: Estado | O14: Control | P14: Resultado | Q14: Objetivo | R14: Estado
C15: LDI_CORP | D15: Bonos corporativos largos | E15: Pasiva / core | F15: VCLT | G15: Sí | H15: Sí | I15: USD | J15: 13 | L15: TR mensual VCLT | M15: Incluido; duración + spread de crédito | O15: IDs únicos | P15: =IF(AND(COUNTIF($C$15:$C$22,C15)=1,COUNTIF($C$15:$C$22,C16)=1,COUNTIF($C$15:$C$22,C17)=1,COUNTIF($C$15:$C$22,C18)=1,COUNTIF($C$15:$C$22,C19)=1,COUNTIF($C$15:$C$22,C20)=1,COUNTIF($C$15:$C$22,C21)=1,COUNTIF($C$15:$C$22,C22)=1),0,1) | Q15: 0 | R15: =IF(P15=Q15,"OK","REVISAR")
C16: LDI_TSY | D16: Treasuries 10–20 años | E16: Pasiva / core | F16: TLH | G16: Sí | H16: Sí | I16: USD | J16: 11.71 | K16: 0.0015 | L16: TR mensual TLH | M16: Incluido; duración soberana líquida | O16: Benchmark por sleeve | P16: =COUNTBLANK(D27:D34) | Q16: 0 | R16: =IF(P16=Q16,"OK","REVISAR")
C17: LDI_STRIPS | D17: Treasury STRIPS largos | E17: Pasiva / core | F17: GOVZ | G17: Sí | H17: Sí | I17: USD | J17: 26.52 | K17: 0.001 | L17: TR mensual GOVZ | M17: Candidato; fuente oficial | O17: Pesos fijados | P17: 0 | Q17: 0 | R17: =IF(P17=Q17,"OK","REVISAR")
C18: EQ_CORE | D18: Beta pasiva S&P 500 | E18: Pasiva / core | F18: SPY (VOO admisible) | G18: Sí | H18: No | I18: USD | K18: 0.000945 | L18: TR mensual ETF | M18: Fuente oficial SPY | O18: Moneda única | P18: =COUNTIF(I15:I22,"<>USD") | Q18: 0 | R18: =IF(P18=Q18,"OK","REVISAR")
C19: CASH | D19: Liquidez / T-Bills 0–3m | E19: Pasiva / core | F19: SGOV | G19: Sí | H19: Sí | I19: USD | J19: 0.25 | K19: 0.0009 | L19: TR mensual SGOV | M19: Duración proxy | O19: Factibilidad duración | P19: =IF(D11>=0,1,0) | Q19: 1 | R19: =IF(P19=Q19,"OK","REVISAR")
C20: MOM_EQ | D20: Momentum renta variable | E20: Activa | F20: Acciones S&P 500 | G20: Sí | H20: No | I20: USD | L20: Backtest neto estrategia | M20: Reglas por parametrizar | O20: Activos con backtest | P20: =IF(L20="Backtest neto estrategia",1,0)+IF(L21="Backtest neto estrategia",1,0)+IF(L22="Backtest neto estrategia",1,0) | Q20: 3 | R20: =IF(P20=Q20,"OK","REVISAR")
C21: BAB_EQ | D21: Betting Against Beta | E21: Activa | F21: Acciones S&P 500 | G21: Sí | H21: No | I21: USD | L21: Backtest neto estrategia | M21: Beta objetivo pendiente
C22: MOM_CMD | D22: Momentum commodities | E22: Activa | F22: GLD / USO / DBA | G22: Sí | H22: No | I22: USD | L22: Backtest neto estrategia | M22: Universo por cerrar
C25: 2. MAPA DE BENCHMARKS
C26: ID | D26: Benchmark | E26: Versión | F26: Construcción / uso | G26: Rebalance | H26: Proveedor | I26: Retorno | J26: Moneda | K26: Estado | L26: Observación
C27: LDI_CORP | D27: Bloomberg U.S. 10+ Year Corporate Bond Index | E27: Total Return | F27: Referencia del ETF y spread de crédito | G27: Según índice | H27: Bloomberg | I27: Total | J27: USD | K27: Correcto | L27: Usar serie TR, no price return
C28: LDI_TSY | D28: ICE U.S. Treasury 10–20 Year Bond Index | E28: Total Return | F28: Referencia oficial de TLH | G28: Mensual / índice | H28: ICE | I28: Total | J28: USD | K28: Correcto | L28: Consistente con implementación
C29: LDI_STRIPS | D29: ICE BofA Long US Treasury Principal STRIPS Index | E29: Total Return | F29: Referencia oficial de GOVZ | G29: Mensual / índice | H29: ICE BofA | I29: Total | J29: USD | K29: Correcto | L29: Aporta duración al universo
C30: EQ_CORE | D30: S&P 500 Index | E30: Total Return | F30: Beta pasiva de gran capitalización EE.UU. | G30: Índice | H30: S&P DJI | I30: Total | J30: USD | K30: Correcto | L30: Preferir versión TR
C31: CASH | D31: ICE 0–3 Month U.S. Treasury Securities Index | E31: Total Return | F31: Referencia oficial de SGOV | G31: Mensual / índice | H31: ICE | I31: Total | J31: USD | K31: Correcto | L31: Mejor que una tasa fija manual
C32: MOM_EQ | D32: S&P 500 Momentum Index | E32: Total Return | F32: Benchmark estilístico de momentum | G32: Semestral | H32: S&P DJI | I32: Total | J32: USD | K32: Correcto | L32: Comparar además contra S&P 500 TR
C33: BAB_EQ | D33: β objetivo × S&P 500 TR + (1−β) × T-Bill TR | E33: Total Return | F33: Benchmark beta-matched; β fijada ex ante | G33: Por período | H33: Construido | I33: Total | J33: USD | K33: Corregido | L33: No usar 70/30 fijo sin estimar β
C34: MOM_CMD | D34: Bloomberg Commodity Index | E34: Total Return | F34: Solo si el universo es diversificado | G34: Índice | H34: Bloomberg | I34: Total | J34: USD | K34: Condicional | L34: Con GLD/USO/DBA crear mezcla neutral
C37: 3. IMPLEMENTACIÓN ADMISIBLE (NO SON PESOS NI SLEEVES ADICIONALES)
C38: Sleeve | D38: Instrumento | E38: Rol | F38: Tratamiento | G38: ¿Serie separada? | H38: Decisión pendiente | I38: Fuente | J38: Estado | L38: DECISIONES DE ESTA HOJA
C39: EQ_CORE | D39: SPY | E39: Implementación base | F39: ETF S&P 500 | G39: No | H39: Confirmar SPY vs VOO | I39: State Street | J39: Admisible | L39: • VCLT y TLH permanecen simultáneamente como sleeves distintos. • Ambos renuevan sus bonos y mantienen exposición de duración; su liquidez permite rebalancear, no evita una repricing inmediata. • GOVZ queda como candidato para inmunización inicial exacta, sujeto a límites. • SPY/VOO representa un solo sleeve pasivo del S&P 500. • Momentum, BAB y commodities entrarán como series de estrategias. • Los pesos siguen vacíos hasta completar datos, backtests y restricciones.
C40: EQ_CORE | D40: VOO | E40: Alternativa de menor costo | F40: Sustituto, no nueva clase | G40: No | H40: Comparar costos/liquidez | I40: Vanguard | J40: Admisible
C41: MOM_EQ | D41: Acciones S&P 500 | E41: Selección momentum | F41: Constituyentes del backtest | G41: No | H41: Ventana, ranking y número | I41: S&P 500 | J41: Pendiente
C42: BAB_EQ | D42: Acciones S&P 500 | E42: Selección baja beta | F42: Constituyentes del backtest | G42: No | H42: Beta objetivo y apalancamiento | I42: S&P 500 | J42: Pendiente
C43: MOM_CMD | D43: GLD | E43: Oro | F43: Parte del backtest | G43: No | H43: Regla de señal | I43: State Street | J43: Provisional
C44: MOM_CMD | D44: USO | E44: Petróleo | F44: Parte del backtest | G44: No | H44: Riesgo de roll yield | I44: USCF | J44: Provisional
C45: MOM_CMD | D45: DBA | E45: Agricultura | F45: Parte del backtest | G45: No | H45: Regla de señal | I45: Invesco | J45: Provisional
C48: Nota: GOVZ hace factible el objetivo por duración en términos de universo, pero su alta sensibilidad a tasas exige límites de concentración y validación mediante Solver.

Sheet 05_Datos_Historicos
C2: MODELO NEXUM - DATOS HISTÓRICOS Y RETORNOS MENSUALES
C3: Calendario común, fuentes y fórmulas que alimentarán backtests, covarianzas, Markowitz y Solver. Sin pesos de cartera.
C5: PARÁMETROS DEL HISTÓRICO | I5: REGLA DE CONSTRUCCIÓN
C6: Inicio objetivo | D6: 40574 | E6: Mes cierre | F6: Permite más de un ciclo de tasas | I6: 1 | K6: Índices | M6: Priorizar benchmark total return para historia larga
C7: Fin del análisis | D7: 46265 | E7: Mes cierre | F7: Último mes completo anterior al modelo | I7: 2 | K7: ETF | M7: Usar ETF para validar implementación, tracking y costos
C8: Frecuencia | D8: Mensual | F8: Cierre de mes | I8: 3 | K8: Activas | M8: Usar retorno neto del backtest, sin look-ahead bias
C9: Moneda funcional | D9: USD | F9: Sin convertir series USD | I9: 4 | K9: Alineación | M9: Conservar solo meses disponibles para todos los sleeves
C10: Tipo de retorno | D10: Total Return | F10: Incluye distribuciones | I10: 5 | K10: Retorno | M10: R(t)=Nivel(t)/Nivel(t−1)−1
C11: Regla de muestra | D11: Complete case | F11: Mismos meses para todas las series | I11: 6 | K11: Vacíos | M11: No reemplazar datos faltantes por cero
C12: Meses esperados | D12: =(YEAR(D7)-YEAR(D6))*12+MONTH(D7)-MONTH(D6)+1 | E12: observaciones | F12: Incluye mes inicial de niveles | I12: 7 | K12: Rebalanceo | M12: Series activas respetan la frecuencia definida ex ante
C14: 1. MAPA DE SERIES Y COBERTURA | W14: CONTROLES
C15: ID | D15: Sleeve | E15: Serie primaria | F15: Serie de validación | G15: Inicio deseado | H15: Fin deseado | I15: Frecuencia | J15: Retorno | K15: Moneda | L15: Fuente primaria | M15: Nivel cargado | N15: Retornos válidos | O15: Faltantes | P15: Cobertura | Q15: Uso | R15: Estado | S15: Observación | W15: Control | X15: Resultado | Y15: Objetivo | Z15: Estado
C16: LDI_CORP | D16: Bonos corporativos largos | E16: VCLT Adjusted Close | F16: Bloomberg US 10+ Year Corporate TR | G16: =$D$6 | H16: =$D$7 | I16: Mensual | J16: Total | K16: USD | L16: Yahoo Finance, Adj Close, 10-sep-2026 | M16: =COUNT(D$27:D$214) | N16: =MAX(0,M16-1) | O16: =$D$12-M16 | P16: =IF($D$12=0,0,M16/$D$12) | Q16: Markowitz + control | R16: =IF(P16=1,"Completa",IF(M16=0,"Pendiente","Parcial")) | S16: ETF implementable; incluye crédito y gastos | W16: Fechas esperadas | X16: =COUNT(C27:C214) | Y16: =$D$12 | Z16: =IF(X16=Y16,"OK","REVISAR")
C17: LDI_TSY | D17: Treasuries 10–20 años | E17: TLH Adjusted Close | F17: ICE US Treasury 10–20 Year TR | G17: =$D$6 | H17: =$D$7 | I17: Mensual | J17: Total | K17: USD | L17: Yahoo Finance, Adj Close, 10-sep-2026 | M17: =COUNT(E$27:E$214) | N17: =MAX(0,M17-1) | O17: =$D$12-M17 | P17: =IF($D$12=0,0,M17/$D$12) | Q17: Markowitz + control | R17: =IF(P17=1,"Completa",IF(M17=0,"Pendiente","Parcial")) | S17: ETF implementable; Treasury sin spread corporativo | W17: Fechas duplicadas | X17: 0 | Y17: 0 | Z17: =IF(X17=Y17,"OK","REVISAR")
C18: LDI_STRIPS | D18: Treasury STRIPS largos | E18: EDV Adjusted Close (proxy GOVZ) | F18: GOVZ / ICE BofA Principal STRIPS TR | G18: =$D$6 | H18: =$D$7 | I18: Mensual | J18: Total | K18: USD | L18: Yahoo Finance, Adj Close, 10-sep-2026 | M18: =COUNT(F$27:F$214) | N18: =MAX(0,M18-1) | O18: =$D$12-M18 | P18: =IF($D$12=0,0,M18/$D$12) | Q18: Markowitz + control | R18: =IF(P18=1,"Completa",IF(M18=0,"Pendiente","Parcial")) | S18: Proxy larga desde 2011; GOVZ se valida desde 2020 | W18: Series completas | X18: =COUNTIF(R16:R23,"Completa") | Y18: 8 | Z18: =IF(X18=Y18,"OK","REVISAR")
C19: EQ_CORE | D19: Beta pasiva S&P 500 | E19: SPY Adjusted Close | F19: S&P 500 Total Return | G19: =$D$6 | H19: =$D$7 | I19: Mensual | J19: Total | K19: USD | L19: Yahoo Finance, Adj Close, 10-sep-2026 | M19: =COUNT(G$27:G$214) | N19: =MAX(0,M19-1) | O19: =$D$12-M19 | P19: =IF($D$12=0,0,M19/$D$12) | Q19: Markowitz + control | R19: =IF(P19=1,"Completa",IF(M19=0,"Pendiente","Parcial")) | S19: ETF implementable del sleeve pasivo | W19: Ceros usados como faltante | X19: =COUNTIF(D27:K214,0) | Y19: 0 | Z19: =IF(X19=Y19,"OK","REVISAR")
C20: CASH | D20: Liquidez / T-Bills | E20: BIL Adjusted Close (proxy SGOV) | F20: SGOV / ICE 0–3 Month Treasury TR | G20: =$D$6 | H20: =$D$7 | I20: Mensual | J20: Total | K20: USD | L20: Yahoo Finance, Adj Close, 10-sep-2026 | M20: =COUNT(H$27:H$214) | N20: =MAX(0,M20-1) | O20: =$D$12-M20 | P20: =IF($D$12=0,0,M20/$D$12) | Q20: Markowitz + control | R20: =IF(P20=1,"Completa",IF(M20=0,"Pendiente","Parcial")) | S20: Proxy de T-Bills desde 2011; SGOV se valida desde 2020 | W20: Retornos fuera de rango ±50% | X20: =IF(X18<8,0,COUNTIF(N28:U214,">0.5")+COUNTIF(N28:U214,"<-0.5")) | Y20: 0 | Z20: =IF(X20=Y20,"OK","REVISAR")
C21: MOM_EQ | D21: Momentum renta variable | E21: SPMO Adjusted Close (proxy) | F21: S&P 500 Momentum Index TR | G21: =$D$6 | H21: =$D$7 | I21: Mensual | J21: Total | K21: USD | L21: Yahoo Finance / Invesco, 10-sep-2026 | M21: =COUNT(I$27:I$214) | N21: =MAX(0,M21-1) | O21: =$D$12-M21 | P21: =IF($D$12=0,0,M21/$D$12) | Q21: Markowitz + backtest | R21: =IF(P21=1,"Completa",IF(M21=0,"Pendiente","Parcial")) | S21: Proxy provisional; no sustituye selección individual | W21: Apto para Markowitz | X21: =IF(AND(X16=Y16,X17=Y17,X18=Y18,X19=Y19,X20=Y20),1,0) | Y21: 1 | Z21: =IF(X21=Y21,"OK","REVISAR")
C22: BAB_EQ | D22: Betting Against Beta | E22: SPLV Adjusted Close (proxy) | F22: Benchmark beta-matched | G22: =$D$6 | H22: =$D$7 | I22: Mensual | J22: Total | K22: USD | L22: Yahoo Finance / Invesco, 10-sep-2026 | M22: =COUNT(J$27:J$214) | N22: =MAX(0,M22-1) | O22: =$D$12-M22 | P22: =IF($D$12=0,0,M22/$D$12) | Q22: Markowitz + backtest | R22: =IF(P22=1,"Completa",IF(M22=0,"Pendiente","Parcial")) | S22: Baja volatilidad ≠ baja beta; validar beta realizada
C23: MOM_CMD | D23: Momentum commodities | E23: Índice neto Commodity Momentum | F23: Bloomberg Commodity TR | G23: =$D$6 | H23: =$D$7 | I23: Mensual | J23: Total | K23: USD | L23: Modelo Nexum + Yahoo Finance, 10-sep-2026 | M23: =COUNT(K$27:K$214) | N23: =MAX(0,M23-1) | O23: =$D$12-M23 | P23: =IF($D$12=0,0,M23/$D$12) | Q23: Markowitz + backtest | R23: =IF(P23=1,"Completa",IF(M23=0,"Pendiente","Parcial")) | S23: Backtest ETF GLD/USO/DBA; BIL sin señal
W24: ESTADO DE ESTA ETAPA Cargadas 5 exposiciones pasivas con 188 niveles ajustados mensuales cada una. EDV extiende la historia de GOVZ y BIL extiende la de SGOV. Estas proxies son implementables, pero no son idénticas a los ETF finales; se validarán por solapamiento desde 2020. Las tres estrategias activas permanecen pendientes hasta construir backtests sin look-ahead bias. Markowitz continúa bloqueado hasta completar las ocho series.
C25: 2. NIVELES TOTAL RETURN / ÍNDICES (INPUT) | M25: 3. RETORNOS MENSUALES (CÁLCULO)
C26: Fecha | D26: LDI_CORP | E26: LDI_TSY | F26: LDI_STRIPS | G26: EQ_CORE | H26: CASH | I26: MOM_EQ | J26: BAB_EQ | K26: MOM_CMD | M26: Fecha | N26: LDI_CORP | O26: LDI_TSY | P26: LDI_STRIPS | Q26: EQ_CORE | R26: CASH | S26: MOM_EQ | T26: BAB_EQ | U26: MOM_CMD
C27: 40574 | D27: 38.328106 | E27: 73.719078 | F27: 40.941681 | G27: 97.919441 | H27: 73.224716 | K27: ='07_Backtest_CMD'!AL40 | M27: 40574
C28: 40602 | D28: 39.000149 | E28: 74.271912 | F28: 42.048649 | G28: 101.32092 | H28: 73.224716 | K28: ='07_Backtest_CMD'!AL41 | M28: 40602 | N28: =IF(OR(D28="",D27=""),"",D28/D27-1) | O28: =IF(OR(E28="",E27=""),"",E28/E27-1) | P28: =IF(OR(F28="",F27=""),"",F28/F27-1) | Q28: =IF(OR(G28="",G27=""),"",G28/G27-1) | R28: =IF(OR(H28="",H27=""),"",H28/H27-1) | S28: =IF(OR(I28="",I27=""),"",I28/I27-1) | T28: =IF(OR(J28="",J27=""),"",J28/J27-1) | U28: =IF(OR(K28="",K27=""),"",K28/K27-1)
C29: 40633 | D29: 38.754154 | E29: 74.119438 | F29: 41.997406 | G29: 101.33308 | H29: 73.224716 | K29: ='07_Backtest_CMD'!AL42 | M29: 40633 | N29: =IF(OR(D29="",D28=""),"",D29/D28-1) | O29: =IF(OR(E29="",E28=""),"",E29/E28-1) | P29: =IF(OR(F29="",F28=""),"",F29/F28-1) | Q29: =IF(OR(G29="",G28=""),"",G29/G28-1) | R29: =IF(OR(H29="",H28=""),"",H29/H28-1) | S29: =IF(OR(I29="",I28=""),"",I29/I28-1) | T29: =IF(OR(J29="",J28=""),"",J29/J28-1) | U29: =IF(OR(K29="",K28=""),"",K29/K28-1)
C30: 40663 | D30: 39.80669 | E30: 75.548477 | F30: 43.307144 | G30: 104.26781 | H30: 73.224716 | K30: ='07_Backtest_CMD'!AL43 | M30: 40663 | N30: =IF(OR(D30="",D29=""),"",D30/D29-1) | O30: =IF(OR(E30="",E29=""),"",E30/E29-1) | P30: =IF(OR(F30="",F29=""),"",F30/F29-1) | Q30: =IF(OR(G30="",G29=""),"",G30/G29-1) | R30: =IF(OR(H30="",H29=""),"",H30/H29-1) | S30: =IF(OR(I30="",I29=""),"",I30/I29-1) | T30: =IF(OR(J30="",J29=""),"",J30/J29-1) | U30: =IF(OR(K30="",K29=""),"",K30/K29-1)
C31: 40694 | D31: 40.897831 | E31: 77.696457 | F31: 45.788231 | G31: 103.09853 | H31: 73.240692 | J31: 17.846209 | K31: ='07_Backtest_CMD'!AL44 | M31: 40694 | N31: =IF(OR(D31="",D30=""),"",D31/D30-1) | O31: =IF(OR(E31="",E30=""),"",E31/E30-1) | P31: =IF(OR(F31="",F30=""),"",F31/F30-1) | Q31: =IF(OR(G31="",G30=""),"",G31/G30-1) | R31: =IF(OR(H31="",H30=""),"",H31/H30-1) | S31: =IF(OR(I31="",I30=""),"",I31/I30-1) | T31: =IF(OR(J31="",J30=""),"",J31/J30-1) | U31: =IF(OR(K31="",K30=""),"",K31/K30-1)
C32: 40724 | D32: 40.031162 | E32: 76.629753 | F32: 43.800438 | G32: 101.3593 | H32: 73.240692 | J32: 17.638529 | K32: ='07_Backtest_CMD'!AL45 | M32: 40724 | N32: =IF(OR(D32="",D31=""),"",D32/D31-1) | O32: =IF(OR(E32="",E31=""),"",E32/E31-1) | P32: =IF(OR(F32="",F31=""),"",F32/F31-1) | Q32: =IF(OR(G32="",G31=""),"",G32/G31-1) | R32: =IF(OR(H32="",H31=""),"",H32/H31-1) | S32: =IF(OR(I32="",I31=""),"",I32/I31-1) | T32: =IF(OR(J32="",J31=""),"",J32/J31-1) | U32: =IF(OR(K32="",K31=""),"",K32/K31-1)
C33: 40755 | D33: 41.60384 | E33: 79.646957 | F33: 46.425346 | G33: 99.331627 | H33: 73.240692 | J33: 17.226107 | K33: ='07_Backtest_CMD'!AL46 | M33: 40755 | N33: =IF(OR(D33="",D32=""),"",D33/D32-1) | O33: =IF(OR(E33="",E32=""),"",E33/E32-1) | P33: =IF(OR(F33="",F32=""),"",F33/F32-1) | Q33: =IF(OR(G33="",G32=""),"",G33/G32-1) | R33: =IF(OR(H33="",H32=""),"",H33/H32-1) | S33: =IF(OR(I33="",I32=""),"",I33/I32-1) | T33: =IF(OR(J33="",J32=""),"",J33/J32-1) | U33: =IF(OR(K33="",K32=""),"",K33/K32-1)
C34: 40786 | D34: 42.118465 | E34: 84.846062 | F34: 54.025723 | G34: 93.870842 | H34: 73.240692 | J34: 17.238224 | K34: ='07_Backtest_CMD'!AL47 | M34: 40786 | N34: =IF(OR(D34="",D33=""),"",D34/D33-1) | O34: =IF(OR(E34="",E33=""),"",E34/E33-1) | P34: =IF(OR(F34="",F33=""),"",F34/F33-1) | Q34: =IF(OR(G34="",G33=""),"",G34/G33-1) | R34: =IF(OR(H34="",H33=""),"",H34/H33-1) | S34: =IF(OR(I34="",I33=""),"",I34/I33-1) | T34: =IF(OR(J34="",J33=""),"",J34/J33-1) | U34: =IF(OR(K34="",K33=""),"",K34/K33-1)
C35: 40816 | D35: 43.548748 | E35: 89.135994 | F35: 66.864548 | G35: 87.354218 | H35: 73.224716 | J35: 16.868879 | K35: ='07_Backtest_CMD'!AL48 | M35: 40816 | N35: =IF(OR(D35="",D34=""),"",D35/D34-1) | O35: =IF(OR(E35="",E34=""),"",E35/E34-1) | P35: =IF(OR(F35="",F34=""),"",F35/F34-1) | Q35: =IF(OR(G35="",G34=""),"",G35/G34-1) | R35: =IF(OR(H35="",H34=""),"",H35/H34-1) | S35: =IF(OR(I35="",I34=""),"",I35/I34-1) | T35: =IF(OR(J35="",J34=""),"",J35/J34-1) | U35: =IF(OR(K35="",K34=""),"",K35/K34-1)
C36: 40847 | D36: 45.022495 | E36: 87.311516 | F36: 62.399704 | G36: 96.888687 | H36: 73.192772 | J36: 17.872644 | K36: ='07_Backtest_CMD'!AL49 | M36: 40847 | N36: =IF(OR(D36="",D35=""),"",D36/D35-1) | O36: =IF(OR(E36="",E35=""),"",E36/E35-1) | P36: =IF(OR(F36="",F35=""),"",F36/F35-1) | Q36: =IF(OR(G36="",G35=""),"",G36/G35-1) | R36: =IF(OR(H36="",H35=""),"",H36/H35-1) | S36: =IF(OR(I36="",I35=""),"",I36/I35-1) | T36: =IF(OR(J36="",J35=""),"",J36/J35-1) | U36: =IF(OR(K36="",K35=""),"",K36/K35-1)
C37: 40877 | D37: 43.544956 | E37: 88.30101 | F37: 64.55629 | G37: 96.494957 | H37: 73.208733 | J37: 18.059425 | K37: ='07_Backtest_CMD'!AL50 | M37: 40877 | N37: =IF(OR(D37="",D36=""),"",D37/D36-1) | O37: =IF(OR(E37="",E36=""),"",E37/E36-1) | P37: =IF(OR(F37="",F36=""),"",F37/F36-1) | Q37: =IF(OR(G37="",G36=""),"",G37/G36-1) | R37: =IF(OR(H37="",H36=""),"",H37/H36-1) | S37: =IF(OR(I37="",I36=""),"",I37/I36-1) | T37: =IF(OR(J37="",J36=""),"",J37/J36-1) | U37: =IF(OR(K37="",K36=""),"",K37/K36-1)
C38: 40908 | D38: 45.425926 | E38: 90.389778 | F38: 68.059143 | G38: 97.503204 | H38: 73.195953 | J38: 18.622484 | K38: ='07_Backtest_CMD'!AL51 | M38: 40908 | N38: =IF(OR(D38="",D37=""),"",D38/D37-1) | O38: =IF(OR(E38="",E37=""),"",E38/E37-1) | P38: =IF(OR(F38="",F37=""),"",F38/F37-1) | Q38: =IF(OR(G38="",G37=""),"",G38/G37-1) | R38: =IF(OR(H38="",H37=""),"",H38/H37-1) | S38: =IF(OR(I38="",I37=""),"",I38/I37-1) | T38: =IF(OR(J38="",J37=""),"",J38/J37-1) | U38: =IF(OR(K38="",K37=""),"",K38/K37-1)
C39: 40939 | D39: 46.177795 | E39: 90.906479 | F39: 67.021019 | G39: 102.02486 | H39: 73.18 | J39: 18.51972 | K39: ='07_Backtest_CMD'!AL52 | M39: 40939 | N39: =IF(OR(D39="",D38=""),"",D39/D38-1) | O39: =IF(OR(E39="",E38=""),"",E39/E38-1) | P39: =IF(OR(F39="",F38=""),"",F39/F38-1) | Q39: =IF(OR(G39="",G38=""),"",G39/G38-1) | R39: =IF(OR(H39="",H38=""),"",H39/H38-1) | S39: =IF(OR(I39="",I38=""),"",I39/I38-1) | T39: =IF(OR(J39="",J38=""),"",J39/J38-1) | U39: =IF(OR(K39="",K38=""),"",K39/K38-1)
C40: 40968 | D40: 46.766449 | E40: 89.574997 | F40: 64.821991 | G40: 106.45325 | H40: 73.195953 | J40: 18.857145 | K40: ='07_Backtest_CMD'!AL53 | M40: 40968 | N40: =IF(OR(D40="",D39=""),"",D40/D39-1) | O40: =IF(OR(E40="",E39=""),"",E40/E39-1) | P40: =IF(OR(F40="",F39=""),"",F40/F39-1) | Q40: =IF(OR(G40="",G39=""),"",G40/G39-1) | R40: =IF(OR(H40="",H39=""),"",H40/H39-1) | S40: =IF(OR(I40="",I39=""),"",I40/I39-1) | T40: =IF(OR(J40="",J39=""),"",J40/J39-1) | U40: =IF(OR(K40="",K39=""),"",K40/K39-1)
C41: 40999 | D41: 45.020485 | E41: 87.234421 | F41: 60.525654 | G41: 109.87722 | H41: 73.18 | J41: 19.398426 | K41: ='07_Backtest_CMD'!AL54 | M41: 40999 | N41: =IF(OR(D41="",D40=""),"",D41/D40-1) | O41: =IF(OR(E41="",E40=""),"",E41/E40-1) | P41: =IF(OR(F41="",F40=""),"",F41/F40-1) | Q41: =IF(OR(G41="",G40=""),"",G41/G40-1) | R41: =IF(OR(H41="",H40=""),"",H41/H40-1) | S41: =IF(OR(I41="",I40=""),"",I41/I40-1) | T41: =IF(OR(J41="",J40=""),"",J41/J40-1) | U41: =IF(OR(K41="",K40=""),"",K41/K40-1)
C42: 41029 | D42: 46.027992 | E42: 90.346573 | F42: 64.590691 | G42: 109.14369 | H42: 73.195953 | J42: 19.605089 | K42: ='07_Backtest_CMD'!AL55 | M42: 41029 | N42: =IF(OR(D42="",D41=""),"",D42/D41-1) | O42: =IF(OR(E42="",E41=""),"",E42/E41-1) | P42: =IF(OR(F42="",F41=""),"",F42/F41-1) | Q42: =IF(OR(G42="",G41=""),"",G42/G41-1) | R42: =IF(OR(H42="",H41=""),"",H42/H41-1) | S42: =IF(OR(I42="",I41=""),"",I42/I41-1) | T42: =IF(OR(J42="",J41=""),"",J42/J41-1) | U42: =IF(OR(K42="",K41=""),"",K42/K41-1)
... C83: 42277 | D83: 53.228012 | E83: 101.03169 | F83: 78.083458 | G83: 160.59944 | H83: 72.972389 | J83: 28.553587 | K83: ='07_Backtest_CMD'!AL96 | M83: 42277 | N83: =IF(OR(D83="",D82=""),"",D83/D82-1) | O83: =IF(OR(E83="",E82=""),"",E83/E82-1) | P83: =IF(OR(F83="",F82=""),"",F83/F82-1) | Q83: =IF(OR(G83="",G82=""),"",G83/G82-1) | R83: =IF(OR(H83="",H82=""),"",H83/H82-1) | S83: =IF(OR(I83="",I82=""),"",I83/I82-1) | T83: =IF(OR(J83="",J82=""),"",J83/J82-1) | U83: =IF(OR(K83="",K82=""),"",K83/K82-1)
C84: 42308 | D84: 53.737965 | E84: 100.24723 | F84: 77.76712 | G84: 174.25998 | H84: 72.956383 | I84: 23.113064 | J84: 30.517954 | K84: ='07_Backtest_CMD'!AL97 | M84: 42308 | N84: =IF(OR(D84="",D83=""),"",D84/D83-1) | O84: =IF(OR(E84="",E83=""),"",E84/E83-1) | P84: =IF(OR(F84="",F83=""),"",F84/F83-1) | Q84: =IF(OR(G84="",G83=""),"",G84/G83-1) | R84: =IF(OR(H84="",H83=""),"",H84/H83-1) | S84: =IF(OR(I84="",I83=""),"",I84/I83-1) | T84: =IF(OR(J84="",J83=""),"",J84/J83-1) | U84: =IF(OR(K84="",K83=""),"",K84/K83-1)
C85: 42338 | D85: 53.597675 | E85: 99.84906 | F85: 76.653328 | G85: 174.89694 | H85: 72.972389 | I85: 23.351433 | J85: 30.843168 | K85: ='07_Backtest_CMD'!AL98 | M85: 42338 | N85: =IF(OR(D85="",D84=""),"",D85/D84-1) | O85: =IF(OR(E85="",E84=""),"",E85/E84-1) | P85: =IF(OR(F85="",F84=""),"",F85/F84-1) | Q85: =IF(OR(G85="",G84=""),"",G85/G84-1) | R85: =IF(OR(H85="",H84=""),"",H85/H84-1) | S85: =IF(OR(I85="",I84=""),"",I85/I84-1) | T85: =IF(OR(J85="",J84=""),"",J85/J84-1) | U85: =IF(OR(K85="",K84=""),"",K85/K84-1)
C86: 42369 | D86: 52.911129 | E86: 99.48838 | F86: 76.088898 | G86: 171.8743 | H86: 72.956383 | I86: 22.857357 | J86: 30.794647 | K86: ='07_Backtest_CMD'!AL99 | M86: 42369 | N86: =IF(OR(D86="",D85=""),"",D86/D85-1) | O86: =IF(OR(E86="",E85=""),"",E86/E85-1) | P86: =IF(OR(F86="",F85=""),"",F86/F85-1) | Q86: =IF(OR(G86="",G85=""),"",G86/G85-1) | R86: =IF(OR(H86="",H85=""),"",H86/H85-1) | S86: =IF(OR(I86="",I85=""),"",I86/I85-1) | T86: =IF(OR(J86="",J85=""),"",J86/J85-1) | U86: =IF(OR(K86="",K85=""),"",K86/K85-1)
C87: 42400 | D87: 52.697392 | E87: 103.17255 | F87: 82.501328 | G87: 163.31721 | H87: 72.972389 | I87: 21.944839 | J87: 30.253817 | K87: ='07_Backtest_CMD'!AL100 | M87: 42400 | N87: =IF(OR(D87="",D86=""),"",D87/D86-1) | O87: =IF(OR(E87="",E86=""),"",E87/E86-1) | P87: =IF(OR(F87="",F86=""),"",F87/F86-1) | Q87: =IF(OR(G87="",G86=""),"",G87/G86-1) | R87: =IF(OR(H87="",H86=""),"",H87/H86-1) | S87: =IF(OR(I87="",I86=""),"",I87/I86-1) | T87: =IF(OR(J87="",J86=""),"",J87/J86-1) | U87: =IF(OR(K87="",K86=""),"",K87/K86-1)
C88: 42429 | D88: 53.247402 | E88: 105.0889 | F88: 85.862152 | G88: 163.18233 | H88: 72.972389 | I88: 21.900539 | J88: 30.552904 | K88: ='07_Backtest_CMD'!AL101 | M88: 42429 | N88: =IF(OR(D88="",D87=""),"",D88/D87-1) | O88: =IF(OR(E88="",E87=""),"",E88/E87-1) | P88: =IF(OR(F88="",F87=""),"",F88/F87-1) | Q88: =IF(OR(G88="",G87=""),"",G88/G87-1) | R88: =IF(OR(H88="",H87=""),"",H88/H87-1) | S88: =IF(OR(I88="",I87=""),"",I88/I87-1) | T88: =IF(OR(J88="",J87=""),"",J88/J87-1) | U88: =IF(OR(K88="",K87=""),"",K88/K87-1)
C89: 42460 | D89: 56.648182 | E89: 105.2249 | F89: 85.697685 | G89: 174.15895 | H89: 72.972389 | I89: 23.078838 | J89: 32.383434 | K89: ='07_Backtest_CMD'!AL102 | M89: 42460 | N89: =IF(OR(D89="",D88=""),"",D89/D88-1) | O89: =IF(OR(E89="",E88=""),"",E89/E88-1) | P89: =IF(OR(F89="",F88=""),"",F89/F88-1) | Q89: =IF(OR(G89="",G88=""),"",G89/G88-1) | R89: =IF(OR(H89="",H88=""),"",H89/H88-1) | S89: =IF(OR(I89="",I88=""),"",I89/I88-1) | T89: =IF(OR(J89="",J88=""),"",J89/J88-1) | U89: =IF(OR(K89="",K88=""),"",K89/K88-1)
C90: 42490 | D90: 57.963646 | E90: 104.82878 | F90: 84.751427 | G90: 174.84535 | H90: 73.004288 | I90: 23.194008 | J90: 32.125381 | K90: ='07_Backtest_CMD'!AL103 | M90: 42490 | N90: =IF(OR(D90="",D89=""),"",D90/D89-1) | O90: =IF(OR(E90="",E89=""),"",E90/E89-1) | P90: =IF(OR(F90="",F89=""),"",F90/F89-1) | Q90: =IF(OR(G90="",G89=""),"",G90/G89-1) | R90: =IF(OR(H90="",H89=""),"",H90/H89-1) | S90: =IF(OR(I90="",I89=""),"",I90/I89-1) | T90: =IF(OR(J90="",J89=""),"",J90/J89-1) | U90: =IF(OR(K90="",K89=""),"",K90/K89-1)
C91: 42521 | D91: 57.772995 | E91: 105.13384 | F91: 85.6166 | G91: 177.81979 | H91: 73.004288 | I91: 23.202873 | J91: 32.664574 | K91: ='07_Backtest_CMD'!AL104 | M91: 42521 | N91: =IF(OR(D91="",D90=""),"",D91/D90-1) | O91: =IF(OR(E91="",E90=""),"",E91/E90-1) | P91: =IF(OR(F91="",F90=""),"",F91/F90-1) | Q91: =IF(OR(G91="",G90=""),"",G91/G90-1) | R91: =IF(OR(H91="",H90=""),"",H91/H90-1) | S91: =IF(OR(I91="",I90=""),"",I91/I90-1) | T91: =IF(OR(J91="",J90=""),"",J91/J90-1) | U91: =IF(OR(K91="",K90=""),"",K91/K90-1)
C92: 42551 | D92: 60.509811 | E92: 109.53237 | F92: 93.938126 | G92: 178.43781 | H92: 72.98835 | I92: 23.071985 | J92: 34.539783 | K92: ='07_Backtest_CMD'!AL105 | M92: 42551 | N92: =IF(OR(D92="",D91=""),"",D92/D91-1) | O92: =IF(OR(E92="",E91=""),"",E92/E91-1) | P92: =IF(OR(F92="",F91=""),"",F92/F91-1) | Q92: =IF(OR(G92="",G91=""),"",G92/G91-1) | R92: =IF(OR(H92="",H91=""),"",H92/H91-1) | S92: =IF(OR(I92="",I91=""),"",I92/I91-1) | T92: =IF(OR(J92="",J91=""),"",J92/J91-1) | U92: =IF(OR(K92="",K91=""),"",K92/K91-1)
C93: 42582 | D93: 62.053112 | E93: 110.25217 | F93: 97.087059 | G93: 184.94571 | H93: 73.020287 | I93: 24.190037 | J93: 34.61697 | K93: ='07_Backtest_CMD'!AL106 | M93: 42582 | N93: =IF(OR(D93="",D92=""),"",D93/D92-1) | O93: =IF(OR(E93="",E92=""),"",E93/E92-1) | P93: =IF(OR(F93="",F92=""),"",F93/F92-1) | Q93: =IF(OR(G93="",G92=""),"",G93/G92-1) | R93: =IF(OR(H93="",H92=""),"",H93/H92-1) | S93: =IF(OR(I93="",I92=""),"",I93/I92-1) | T93: =IF(OR(J93="",J92=""),"",J93/J92-1) | U93: =IF(OR(K93="",K92=""),"",K93/K92-1)
C94: 42613 | D94: 62.151684 | E94: 109.01801 | F94: 95.658829 | G94: 185.16714 | H94: 73.020287 | I94: 24.190037 | J94: 33.957237 | K94: ='07_Backtest_CMD'!AL107 | M94: 42613 | N94: =IF(OR(D94="",D93=""),"",D94/D93-1) | O94: =IF(OR(E94="",E93=""),"",E94/E93-1) | P94: =IF(OR(F94="",F93=""),"",F94/F93-1) | Q94: =IF(OR(G94="",G93=""),"",G94/G93-1) | R94: =IF(OR(H94="",H93=""),"",H94/H93-1) | S94: =IF(OR(I94="",I93=""),"",I94/I93-1) | T94: =IF(OR(J94="",J93=""),"",J94/J93-1) | U94: =IF(OR(K94="",K93=""),"",K94/K93-1)
C95: 42643 | D95: 61.873707 | E95: 108.67358 | F95: 93.427765 | G95: 185.17787 | H95: 73.036255 | I95: 24.31002 | J95: 33.654423 | K95: ='07_Backtest_CMD'!AL108 | M95: 42643 | N95: =IF(OR(D95="",D94=""),"",D95/D94-1) | O95: =IF(OR(E95="",E94=""),"",E95/E94-1) | P95: =IF(OR(F95="",F94=""),"",F95/F94-1) | Q95: =IF(OR(G95="",G94=""),"",G95/G94-1) | R95: =IF(OR(H95="",H94=""),"",H95/H94-1) | S95: =IF(OR(I95="",I94=""),"",I95/I94-1) | T95: =IF(OR(J95="",J94=""),"",J95/J94-1) | U95: =IF(OR(K95="",K94=""),"",K95/K94-1)
... C214: 46265 | D214: 71.837997 | E214: 96.628006 | F214: 60.169998 | G214: 767.04999 | H214: 91.380005 | I214: 147.09 | J214: 74.690002 | K214: ='07_Backtest_CMD'!AL227 | M214: 46265 | N214: =IF(OR(D214="",D213=""),"",D214/D213-1) | O214: =IF(OR(E214="",E213=""),"",E214/E213-1) | P214: =IF(OR(F214="",F213=""),"",F214/F213-1) | Q214: =IF(OR(G214="",G213=""),"",G214/G213-1) | R214: =IF(OR(H214="",H213=""),"",H214/H213-1) | S214: =IF(OR(I214="",I213=""),"",I214/I213-1) | T214: =IF(OR(J214="",J213=""),"",J214/J213-1) | U214: =IF(OR(K214="",K213=""),"",K214/K213-1)

Sheet 06_Parametros_Estrategias
C2: MODELO NEXUM - PARÁMETROS EX ANTE DE ESTRATEGIAS ACTIVAS
C3: Reglas cerradas antes del backtest. Estos porcentajes son filtros o ponderadores de score; no son pesos del portafolio.
C5: REGLAS COMUNES | I5: PRINCIPIOS DE VALIDACIÓN
C6: Frecuencia del backtest | D6: Mensual | F6: Coherente con datos y benchmark | I6: Point-in-time | K6: Usar constituyentes históricos del S&P 500
C7: Fecha de señal | D7: Último cierre del mes | F7: Solo información disponible en t | I7: Supervivencia | K7: Mantener deslistados hasta su fecha efectiva
C8: Inicio de posición | D8: Mes siguiente | F8: Evita look-ahead bias | I8: Eventos | K8: Precios ajustados por dividendos, splits y cambios de ticker
C9: Ponderación base | D9: Equal weight | F9: Evita optimización dentro del backtest | I9: Señales | K9: Toda ventana termina antes de la fecha de ejecución
C10: Costo por rotación one-way | D10: 0.001 | E10: % nocional transado | F10: Editable; incluye fricción estimada | I10: Vacíos | K10: No completar retornos faltantes con cero
C11: Monitoreo | D11: Semanal | F11: No implica operación semanal | I11: Costos | K11: Aplicar costo sobre turnover, no sobre patrimonio fijo
C12: Retorno de caja | D12: BIL | F12: Capital sin señal permanece en T-Bills | I12: Robustez | K12: Reportar máximo, 10 años, 5 años y subperíodos
C14: 1. EQUITY MOMENTUM | O14: CONTROLES
C15: Grupo | D15: Parámetro | E15: Valor | F15: Unidad | G15: Tipo | H15: Fuente lógica | I15: Implementación | J15: Control | K15: Estado | L15: Observación | O15: Control | P15: Resultado | Q15: Objetivo | R15: Estado
C16: Universo | D16: Constituyentes | E16: S&P 500 histórico | F16: point-in-time | G16: Restricción | H16: Informe corregido | I16: Archivo de membresía histórica | J16: Obligatorio | K16: Definido | L16: No usar constituyentes actuales | O16: Score Momentum suma | P16: =E23+E24 | Q16: 1 | R16: =IF(ABS(P16-Q16)<0.00001,"OK","REVISAR")
C17: Elegibilidad | D17: Retorno 3 meses | E17: 0 | F17: > | G17: Filtro | H17: Informe Grupo 11 | I17: Cierre t / cierre t-3 - 1 | J17: Sin look-ahead | K17: Definido | O17: Score commodities suma | P17: =E55+E56+E57 | Q17: 1 | R17: =IF(ABS(P17-Q17)<0.00001,"OK","REVISAR")
C18: Elegibilidad | D18: Retorno 6 meses | E18: 0.05 | F18: > | G18: Filtro | H18: Informe Grupo 11 | I18: Cierre t / cierre t-6 - 1 | J18: Sin look-ahead | K18: Definido | O18: Beta min < max | P18: =IF(E34<E35,1,0) | Q18: 1 | R18: =IF(ABS(P18-Q18)<0.00001,"OK","REVISAR")
C19: Elegibilidad | D19: Retorno 12 meses | E19: 0.1 | F19: > | G19: Filtro | H19: Informe Grupo 11 | I19: Cierre t / cierre t-12 - 1 | J19: Sin look-ahead | K19: Definido | O19: Beta objetivo en rango | P19: =IF(AND(E43>=E34,E43<=E35),1,0) | Q19: 1 | R19: =IF(ABS(P19-Q19)<0.00001,"OK","REVISAR")
C20: Tendencia | D20: Precio / MM200 | E20: 1 | F20: > | G20: Filtro | H20: Informe Grupo 11 | I20: Precio t > media 200 días | J20: Dato diario | K20: Definido | O20: Costo no negativo | P20: =IF(D10>=0,1,0) | Q20: 1 | R20: =IF(ABS(P20-Q20)<0.00001,"OK","REVISAR")
C21: Liquidez | D21: ADV mínimo | E21: 5000000 | F21: USD/día | G21: Filtro | H21: Informe Grupo 11 | I21: Promedio 60 días | J21: Dato diario | K21: Definido | O21: Ejecución rezagada | P21: =IF(D8="Mes siguiente",1,0) | Q21: 1 | R21: =IF(ABS(P21-Q21)<0.00001,"OK","REVISAR")
C22: Riesgo | D22: Sharpe histórico mínimo | E22: 0.5 | F22: x | G22: Filtro | H22: Informe Grupo 11 | I22: 12 meses; BIL como rf | J22: Mensual | K22: Definido | O22: Base BAB sin cortos | P22: =IF(E42=0,1,0) | Q22: 1 | R22: =IF(ABS(P22-Q22)<0.00001,"OK","REVISAR")
C23: Ranking | D23: Peso retorno 6m | E23: 0.5 | F23: score | G23: Ponderador | H23: Regla Nexum | I23: Percentil entre elegibles | J23: Suma score | K23: Definido | L23: Ranking parsimonioso | O23: Pesos portafolio definidos | P23: 0 | Q23: 0 | R23: =IF(ABS(P23-Q23)<0.00001,"OK","REVISAR")
C24: Ranking | D24: Peso retorno 12m | E24: 0.5 | F24: score | G24: Ponderador | H24: Regla Nexum | I24: Percentil entre elegibles | J24: Suma score | K24: Definido | L24: Evita sobrecargar indicadores
C25: Cartera | D25: Número objetivo | E25: 10 | F25: acciones | G25: Selección | H25: Regla Nexum | I25: Top 10 por score | J25: Diversificación | K25: Definido
C26: Cartera | D26: Máximo por sector | E26: 0.25 | F26: % estrategia | G26: Límite | H26: Control riesgo | I26: Reemplazar por siguiente ranking | J26: Ex ante | K26: Definido | O26: DECISIONES METODOLÓGICAS • Se conserva la esencia de los filtros del informe. • Momentum se rankea solo con retornos 6m y 12m; las medias móviles y Sharpe actúan como filtros para evitar doble conteo. • BAB se implementa long-only en el caso base; no replica la versión académica apalancada. • Commodities usa ETF observables. La curva de futuros queda como overlay de monitoreo, no como señal histórica inventada. • Monitorear semanalmente no significa rebalancear semanalmente. • Ningún parámetro de esta hoja fija la asignación final del portafolio.
C27: Rebalanceo | D27: Frecuencia | E27: Mensual | G27: Regla | H27: Benchmark metodología | I27: Señal t; retorno t+1 | J27: Calendario | K27: Definido | L27: Semanal solo por breach
C30: 2. BETTING AGAINST BETA - ADAPTACIÓN LONG-ONLY
C31: Grupo | D31: Parámetro | E31: Valor | F31: Unidad | G31: Tipo | H31: Fuente lógica | I31: Implementación | J31: Control | K31: Estado | L31: Observación
C32: Universo | D32: Constituyentes | E32: S&P 500 histórico | F32: point-in-time | G32: Restricción | H32: Benchmark Nexum | I32: Archivo de membresía histórica | J32: Obligatorio | K32: Definido
C33: Beta | D33: Ventana estimación | E33: 36 | F33: meses | G33: Parámetro | H33: Regla Nexum | I33: Cov(Ri,Rm)/Var(Rm) | J33: Mínimo 30 obs. | K33: Definido | L33: Mercado = SPY
C34: Beta | D34: Beta mínima | E34: 0.5 | F34: beta | G34: Filtro | H34: IPS / Informe | I34: Estimación al cierre t | J34: Ex ante | K34: Definido
C35: Beta | D35: Beta máxima | E35: 0.9 | F35: beta | G35: Filtro | H35: IPS / Informe | I35: Estimación al cierre t | J35: Ex ante | K35: Definido
C36: Liquidez | D36: ADV mínimo | E36: 5000000 | F36: USD/día | G36: Filtro | H36: Informe Grupo 11 | I36: Promedio 60 días | J36: Dato diario | K36: Definido
C37: Precio | D37: Precio mínimo | E37: 5 | F37: USD | G37: Filtro | H37: Informe Grupo 11 | I37: Precio al cierre t | J37: Dato diario | K37: Definido
C38: Historia | D38: Cotización mínima | E38: 36 | F38: meses | G38: Filtro | H38: Informe Grupo 11 | I38: Retornos mensuales válidos | J38: Sin backfill | K38: Definido
C39: Ranking | D39: Criterio primario | E39: Beta ascendente | G39: Ranking | H39: Regla Nexum | I39: Menor beta obtiene mayor score | J39: Simple | K39: Definido | O39: DATOS AÚN NECESARIOS 1. Membresía histórica point-in-time del S&P 500. 2. Precios ajustados diarios de las acciones elegibles. 3. Volumen y capitalización en cada fecha. 4. Precios ajustados de GLD, USO y DBA. Sin los puntos 1–3 no se presentará un backtest accionario como libre de sesgo de supervivencia.
C40: Cartera | D40: Número objetivo | E40: 10 | F40: acciones | G40: Selección | H40: Regla Nexum | I40: Top 10 elegibles | J40: Diversificación | K40: Definido
C41: Cartera | D41: Máximo por sector | E41: 0.25 | F41: % estrategia | G41: Límite | H41: Control riesgo | I41: Reemplazar por siguiente ranking | J41: Ex ante | K41: Definido
C42: Implementación | D42: Posición corta | E42: 0 | F42: % | G42: Base case | H42: Benchmark Nexum | I42: Long-only sin apalancamiento | J42: Mandato | K42: Definido | L42: Cortos solo escenario separado
C43: Benchmark | D43: Beta objetivo | E43: 0.7 | F43: beta | G43: Referencia | H43: Benchmark Nexum | I43: β×SPY+(1−β)×BIL | J43: Fija por período | K43: Provisional | L43: Validar beta realizada
C44: Rebalanceo | D44: Frecuencia | E44: Mensual | G44: Regla | H44: Benchmark metodología | I44: Señal t; retorno t+1 | J44: Calendario | K44: Definido | L44: Semanal solo por breach
C47: 3. COMMODITY MOMENTUM - IMPLEMENTACIÓN ETF
C48: Grupo | D48: Parámetro | E48: Valor | F48: Unidad | G48: Tipo | H48: Fuente lógica | I48: Implementación | J48: Control | K48: Estado | L48: Observación
C49: Universo | D49: Instrumentos | E49: GLD / USO / DBA | G49: Restricción | H49: Estructura acordada | I49: Oro / petróleo / agricultura | J49: StockTrak | K49: Provisional | L49: Ampliable si la plataforma lo permite
C50: Elegibilidad | D50: Retorno 3 meses | E50: 0.05 | F50: > | G50: Filtro | H50: Informe Grupo 11 | I50: Cierre t / cierre t-3 - 1 | J50: Sin look-ahead | K50: Definido
C51: Elegibilidad | D51: Retorno 6 meses | E51: 0.08 | F51: > | G51: Filtro | H51: Informe Grupo 11 | I51: Cierre t / cierre t-6 - 1 | J51: Sin look-ahead | K51: Definido
C52: Elegibilidad | D52: Retorno 12 meses | E52: 0.1 | F52: > | G52: Filtro | H52: Informe Grupo 11 | I52: Cierre t / cierre t-12 - 1 | J52: Sin look-ahead | K52: Definido
C53: Tendencia | D53: Precio / MM200 | E53: 1 | F53: > | G53: Filtro | H53: Informe Grupo 11 | I53: Precio t > media 200 días | J53: Dato diario | K53: Definido
C54: Riesgo | D54: Volatilidad máxima | E54: 0.5 | F54: anual | G54: Filtro | H54: Informe Grupo 11 | I54: SD 12m × raíz(12) | J54: Mensual | K54: Definido
C55: Ranking | D55: Peso retorno 3m | E55: 0.333333 | F55: score | G55: Ponderador | H55: Regla Nexum | I55: Percentil entre elegibles | J55: Suma score | K55: Definido
C56: Ranking | D56: Peso retorno 6m | E56: 0.333333 | F56: score | G56: Ponderador | H56: Regla Nexum | I56: Percentil entre elegibles | J56: Suma score | K56: Definido
C57: Ranking | D57: Peso retorno 12m | E57: 0.333334 | F57: score | G57: Ponderador | H57: Regla Nexum | I57: Percentil entre elegibles | J57: Suma score | K57: Definido
C58: Cartera | D58: Número máximo | E58: 3 | F58: ETF | G58: Selección | H58: Universo disponible | I58: Todos los elegibles | J58: Diversificación | K58: Definido
C59: Cartera | D59: Sin señal | E59: 100% BIL | G59: Regla defensiva | H59: Regla Nexum | I59: Saldo no invertido va a caja | J59: Siempre invertido | K59: Definido
C60: Curva futuros | D60: Backwardation / contango | E60: Overlay en vivo | G60: Monitoreo | H60: Informe Grupo 11 | I60: No se usa en backtest ETF base | J60: Trazabilidad | K60: Definido | L60: Evita usar datos no disponibles
C61: Rebalanceo | D61: Frecuencia | E61: Mensual | G61: Regla | H61: Benchmark metodología | I61: Señal t; retorno t+1 | J61: Calendario | K61: Definido | L61: Semanal solo por breach

Sheet 07_Backtest_CMD
C2: MODELO NEXUM - BACKTEST COMMODITY MOMENTUM
C3: GLD, USO y DBA · señales al cierre t · retorno desde t+1 · BIL cuando no hay señal · costos sobre turnover
C5: RESULTADOS DEL BACKTEST | I5: OPERACIÓN Y COSTOS | O5: REGLAS ACTIVAS (VINCULADAS) | X5: VALIDACIÓN
C6: Inicio efectivo | D6: 40574 | F6: Índice base = 100 | I6: Turnover medio | J6: =AVERAGE(AH41:AH227) | L6: 0,5 × suma cambios absolutos | O6: Retorno 3m | P6: ='06_Parametros_Estrategias'!E50 | Q6: > | S6: 06_Parametros_Estrategias | X6: Look-ahead | Z6: Señal t aplicada en t+1
C7: Fin | D7: 46265 | F7: Último mes completo | I7: Costo acumulado (suma) | J7: =SUM(AJ41:AJ227) | L7: Turnover × costo one-way | O7: Retorno 6m | P7: ='06_Parametros_Estrategias'!E51 | Q7: > | S7: 06_Parametros_Estrategias | X7: Supervivencia | Z7: ETF disponibles durante toda la muestra
C8: Meses de retorno | D8: 187 | F8: Feb-2011 a Ago-2026 | I8: Meses con GLD | J8: =COUNTIF(L40:L227,">0") | L8: Peso positivo | O8: Retorno 12m | P8: ='06_Parametros_Estrategias'!E52 | Q8: > | S8: 06_Parametros_Estrategias | X8: Dividendos/splits | Z8: Adjusted Close
C9: CAGR neto | D9: =(AL227/AL40)^(12/187)-1 | F9: Crecimiento anual compuesto | I9: Meses con USO | J9: =COUNTIF(U40:U227,">0") | L9: Peso positivo | O9: Precio / MM200 | P9: ='06_Parametros_Estrategias'!E53 | Q9: > | S9: 06_Parametros_Estrategias | X9: USO | Z9: Adjusted Close captura reverse split; no elimina roll yield
C10: Volatilidad anual | D10: =STDEV.S(AK41:AK227)*SQRT(12) | F10: SD mensual × raíz(12) | I10: Meses con DBA | J10: =COUNTIF(AD40:AD227,">0") | L10: Peso positivo | O10: Volatilidad máxima | P10: ='06_Parametros_Estrategias'!E54 | Q10: < | S10: 06_Parametros_Estrategias | X10: Curva futuros | Z10: No usada por falta de serie histórica homogénea
C11: Sharpe vs BIL | D11: =AVERAGE(AO41:AO227)*12/(STDEV.S(AO41:AO227)*SQRT(12)) | F11: Exceso mensual anualizado | I11: Meses 100% BIL | J11: =COUNTIF(AE40:AE227,1) | L11: Ningún ETF elegible | O11: Costo one-way | P11: ='06_Parametros_Estrategias'!D10 | S11: 06_Parametros_Estrategias | X11: Costos | Z11: Aplicados al cambio de pesos objetivo
C12: Máximo drawdown | D12: =MIN(AN40:AN227) | F12: Peor caída desde máximo | I12: Observaciones diarias | J12: 4465 | L12: Dic-2008 a Ago-2026 | O12: Sin señal | P12: BIL | S12: 100% BIL | X12: Estado | Z12: Backtest implementable; proxy imperfecta de futuros directos
C14: BACKTEST MENSUAL Y TRAZABILIDAD DE SEÑALES
C15: Fecha | D15: GLD Px | E15: GLD MM200 | F15: GLD R1 | G15: GLD R3 | H15: GLD R6 | I15: GLD R12 | J15: GLD Vol | K15: GLD Sig | L15: GLD Peso | M15: USO Px | N15: USO MM200 | O15: USO R1 | P15: USO R3 | Q15: USO R6 | R15: USO R12 | S15: USO Vol | T15: USO Sig | U15: USO Peso | V15: DBA Px | W15: DBA MM200 | X15: DBA R1 | Y15: DBA R3 | Z15: DBA R6 | AA15: DBA R12 | AB15: DBA Vol | AC15: DBA Sig | AD15: DBA Peso | AE15: BIL Peso | AF15: BIL Px | AG15: BIL R1 | AH15: Turnover | AI15: Ret. bruto | AJ15: Costo | AK15: Ret. neto | AL15: Índice | AM15: Máximo | AN15: Drawdown | AO15: Exceso vs BIL
C16: 39844 | D16: =D272 | E16: =H272 | M16: =E272 | N16: =I272 | V16: =F272 | W16: =J272 | AF16: =G272
C17: 39872 | D17: =D291 | E17: =H291 | F17: =D17/D16-1 | M17: =E291 | N17: =I291 | O17: =M17/M16-1 | V17: =F291 | W17: =J291 | X17: =V17/V16-1 | AF17: =G291 | AG17: =AF17/AF16-1
C18: 39903 | D18: =D313 | E18: =H313 | F18: =D18/D17-1 | M18: =E313 | N18: =I313 | O18: =M18/M17-1 | V18: =F313 | W18: =J313 | X18: =V18/V17-1 | AF18: =G313 | AG18: =AF18/AF17-1
C19: 39933 | D19: =D334 | E19: =H334 | F19: =D19/D18-1 | G19: =D19/D16-1 | M19: =E334 | N19: =I334 | O19: =M19/M18-1 | P19: =M19/M16-1 | V19: =F334 | W19: =J334 | X19: =V19/V18-1 | Y19: =V19/V16-1 | AF19: =G334 | AG19: =AF19/AF18-1
C20: 39964 | D20: =D354 | E20: =H354 | F20: =D20/D19-1 | G20: =D20/D17-1 | M20: =E354 | N20: =I354 | O20: =M20/M19-1 | P20: =M20/M17-1 | V20: =F354 | W20: =J354 | X20: =V20/V19-1 | Y20: =V20/V17-1 | AF20: =G354 | AG20: =AF20/AF19-1
C21: 39994 | D21: =D376 | E21: =H376 | F21: =D21/D20-1 | G21: =D21/D18-1 | M21: =E376 | N21: =I376 | O21: =M21/M20-1 | P21: =M21/M18-1 | V21: =F376 | W21: =J376 | X21: =V21/V20-1 | Y21: =V21/V18-1 | AF21: =G376 | AG21: =AF21/AF20-1
C22: 40025 | D22: =D398 | E22: =H398 | F22: =D22/D21-1 | G22: =D22/D19-1 | H22: =D22/D16-1 | M22: =E398 | N22: =I398 | O22: =M22/M21-1 | P22: =M22/M19-1 | Q22: =M22/M16-1 | V22: =F398 | W22: =J398 | X22: =V22/V21-1 | Y22: =V22/V19-1 | Z22: =V22/V16-1 | AF22: =G398 | AG22: =AF22/AF21-1
C23: 40056 | D23: =D419 | E23: =H419 | F23: =D23/D22-1 | G23: =D23/D20-1 | H23: =D23/D17-1 | M23: =E419 | N23: =I419 | O23: =M23/M22-1 | P23: =M23/M20-1 | Q23: =M23/M17-1 | V23: =F419 | W23: =J419 | X23: =V23/V22-1 | Y23: =V23/V20-1 | Z23: =V23/V17-1 | AF23: =G419 | AG23: =AF23/AF22-1
C24: 40086 | D24: =D440 | E24: =H440 | F24: =D24/D23-1 | G24: =D24/D21-1 | H24: =D24/D18-1 | M24: =E440 | N24: =I440 | O24: =M24/M23-1 | P24: =M24/M21-1 | Q24: =M24/M18-1 | V24: =F440 | W24: =J440 | X24: =V24/V23-1 | Y24: =V24/V21-1 | Z24: =V24/V18-1 | AF24: =G440 | AG24: =AF24/AF23-1
C25: 40117 | D25: =D462 | E25: =H462 | F25: =D25/D24-1 | G25: =D25/D22-1 | H25: =D25/D19-1 | M25: =E462 | N25: =I462 | O25: =M25/M24-1 | P25: =M25/M22-1 | Q25: =M25/M19-1 | V25: =F462 | W25: =J462 | X25: =V25/V24-1 | Y25: =V25/V22-1 | Z25: =V25/V19-1 | AF25: =G462 | AG25: =AF25/AF24-1
C26: 40147 | D26: =D482 | E26: =H482 | F26: =D26/D25-1 | G26: =D26/D23-1 | H26: =D26/D20-1 | M26: =E482 | N26: =I482 | O26: =M26/M25-1 | P26: =M26/M23-1 | Q26: =M26/M20-1 | V26: =F482 | W26: =J482 | X26: =V26/V25-1 | Y26: =V26/V23-1 | Z26: =V26/V20-1 | AF26: =G482 | AG26: =AF26/AF25-1
C27: 40178 | D27: =D504 | E27: =H504 | F27: =D27/D26-1 | G27: =D27/D24-1 | H27: =D27/D21-1 | M27: =E504 | N27: =I504 | O27: =M27/M26-1 | P27: =M27/M24-1 | Q27: =M27/M21-1 | V27: =F504 | W27: =J504 | X27: =V27/V26-1 | Y27: =V27/V24-1 | Z27: =V27/V21-1 | AF27: =G504 | AG27: =AF27/AF26-1
C28: 40209 | D28: =D523 | E28: =H523 | F28: =D28/D27-1 | G28: =D28/D25-1 | H28: =D28/D22-1 | I28: =D28/D16-1 | J28: =STDEV.S(F17:F28)*SQRT(12) | K28: =IF(AND(G28>$P$6,H28>$P$7,I28>$P$8,D28>E28,J28<$P$10),1,0) | L28: =IF(SUM(K28,T28,AC28)=0,0,K28/SUM(K28,T28,AC28)) | M28: =E523 | N28: =I523 | O28: =M28/M27-1 | P28: =M28/M25-1 | Q28: =M28/M22-1 | R28: =M28/M16-1 | S28: =STDEV.S(O17:O28)*SQRT(12) | T28: =IF(AND(P28>$P$6,Q28>$P$7,R28>$P$8,M28>N28,S28<$P$10),1,0) | U28: =IF(SUM(K28,T28,AC28)=0,0,T28/SUM(K28,T28,AC28)) | V28: =F523 | W28: =J523 | X28: =V28/V27-1 | Y28: =V28/V25-1 | Z28: =V28/V22-1 | AA28: =V28/V16-1 | AB28: =STDEV.S(X17:X28)*SQRT(12) | AC28: =IF(AND(Y28>$P$6,Z28>$P$7,AA28>$P$8,V28>W28,AB28<$P$10),1,0) | AD28: =IF(SUM(K28,T28,AC28)=0,0,AC28/SUM(K28,T28,AC28)) | AE28: =IF(SUM(K28,T28,AC28)=0,1,0) | AF28: =G523 | AG28: =AF28/AF27-1
C29: 40237 | D29: =D542 | E29: =H542 | F29: =D29/D28-1 | G29: =D29/D26-1 | H29: =D29/D23-1 | I29: =D29/D17-1 | J29: =STDEV.S(F18:F29)*SQRT(12) | K29: =IF(AND(G29>$P$6,H29>$P$7,I29>$P$8,D29>E29,J29<$P$10),1,0) | L29: =IF(SUM(K29,T29,AC29)=0,0,K29/SUM(K29,T29,AC29)) | M29: =E542 | N29: =I542 | O29: =M29/M28-1 | P29: =M29/M26-1 | Q29: =M29/M23-1 | R29: =M29/M17-1 | S29: =STDEV.S(O18:O29)*SQRT(12) | T29: =IF(AND(P29>$P$6,Q29>$P$7,R29>$P$8,M29>N29,S29<$P$10),1,0) | U29: =IF(SUM(K29,T29,AC29)=0,0,T29/SUM(K29,T29,AC29)) | V29: =F542 | W29: =J542 | X29: =V29/V28-1 | Y29: =V29/V26-1 | Z29: =V29/V23-1 | AA29: =V29/V17-1 | AB29: =STDEV.S(X18:X29)*SQRT(12) | AC29: =IF(AND(Y29>$P$6,Z29>$P$7,AA29>$P$8,V29>W29,AB29<$P$10),1,0) | AD29: =IF(SUM(K29,T29,AC29)=0,0,AC29/SUM(K29,T29,AC29)) | AE29: =IF(SUM(K29,T29,AC29)=0,1,0) | AF29: =G542 | AG29: =AF29/AF28-1
C30: 40268 | D30: =D565 | E30: =H565 | F30: =D30/D29-1 | G30: =D30/D27-1 | H30: =D30/D24-1 | I30: =D30/D18-1 | J30: =STDEV.S(F19:F30)*SQRT(12) | K30: =IF(AND(G30>$P$6,H30>$P$7,I30>$P$8,D30>E30,J30<$P$10),1,0) | L30: =IF(SUM(K30,T30,AC30)=0,0,K30/SUM(K30,T30,AC30)) | M30: =E565 | N30: =I565 | O30: =M30/M29-1 | P30: =M30/M27-1 | Q30: =M30/M24-1 | R30: =M30/M18-1 | S30: =STDEV.S(O19:O30)*SQRT(12) | T30: =IF(AND(P30>$P$6,Q30>$P$7,R30>$P$8,M30>N30,S30<$P$10),1,0) | U30: =IF(SUM(K30,T30,AC30)=0,0,T30/SUM(K30,T30,AC30)) | V30: =F565 | W30: =J565 | X30: =V30/V29-1 | Y30: =V30/V27-1 | Z30: =V30/V24-1 | AA30: =V30/V18-1 | AB30: =STDEV.S(X19:X30)*SQRT(12) | AC30: =IF(AND(Y30>$P$6,Z30>$P$7,AA30>$P$8,V30>W30,AB30<$P$10),1,0) | AD30: =IF(SUM(K30,T30,AC30)=0,0,AC30/SUM(K30,T30,AC30)) | AE30: =IF(SUM(K30,T30,AC30)=0,1,0) | AF30: =G565 | AG30: =AF30/AF29-1
C31: 40298 | D31: =D586 | E31: =H586 | F31: =D31/D30-1 | G31: =D31/D28-1 | H31: =D31/D25-1 | I31: =D31/D19-1 | J31: =STDEV.S(F20:F31)*SQRT(12) | K31: =IF(AND(G31>$P$6,H31>$P$7,I31>$P$8,D31>E31,J31<$P$10),1,0) | L31: =IF(SUM(K31,T31,AC31)=0,0,K31/SUM(K31,T31,AC31)) | M31: =E586 | N31: =I586 | O31: =M31/M30-1 | P31: =M31/M28-1 | Q31: =M31/M25-1 | R31: =M31/M19-1 | S31: =STDEV.S(O20:O31)*SQRT(12) | T31: =IF(AND(P31>$P$6,Q31>$P$7,R31>$P$8,M31>N31,S31<$P$10),1,0) | U31: =IF(SUM(K31,T31,AC31)=0,0,T31/SUM(K31,T31,AC31)) | V31: =F586 | W31: =J586 | X31: =V31/V30-1 | Y31: =V31/V28-1 | Z31: =V31/V25-1 | AA31: =V31/V19-1 | AB31: =STDEV.S(X20:X31)*SQRT(12) | AC31: =IF(AND(Y31>$P$6,Z31>$P$7,AA31>$P$8,V31>W31,AB31<$P$10),1,0) | AD31: =IF(SUM(K31,T31,AC31)=0,0,AC31/SUM(K31,T31,AC31)) | AE31: =IF(SUM(K31,T31,AC31)=0,1,0) | AF31: =G586 | AG31: =AF31/AF30-1
C32: 40329 | D32: =D606 | E32: =H606 | F32: =D32/D31-1 | G32: =D32/D29-1 | H32: =D32/D26-1 | I32: =D32/D20-1 | J32: =STDEV.S(F21:F32)*SQRT(12) | K32: =IF(AND(G32>$P$6,H32>$P$7,I32>$P$8,D32>E32,J32<$P$10),1,0) | L32: =IF(SUM(K32,T32,AC32)=0,0,K32/SUM(K32,T32,AC32)) | M32: =E606 | N32: =I606 | O32: =M32/M31-1 | P32: =M32/M29-1 | Q32: =M32/M26-1 | R32: =M32/M20-1 | S32: =STDEV.S(O21:O32)*SQRT(12) | T32: =IF(AND(P32>$P$6,Q32>$P$7,R32>$P$8,M32>N32,S32<$P$10),1,0) | U32: =IF(SUM(K32,T32,AC32)=0,0,T32/SUM(K32,T32,AC32)) | V32: =F606 | W32: =J606 | X32: =V32/V31-1 | Y32: =V32/V29-1 | Z32: =V32/V26-1 | AA32: =V32/V20-1 | AB32: =STDEV.S(X21:X32)*SQRT(12) | AC32: =IF(AND(Y32>$P$6,Z32>$P$7,AA32>$P$8,V32>W32,AB32<$P$10),1,0) | AD32: =IF(SUM(K32,T32,AC32)=0,0,AC32/SUM(K32,T32,AC32)) | AE32: =IF(SUM(K32,T32,AC32)=0,1,0) | AF32: =G606 | AG32: =AF32/AF31-1
C33: 40359 | D33: =D628 | E33: =H628 | F33: =D33/D32-1 | G33: =D33/D30-1 | H33: =D33/D27-1 | I33: =D33/D21-1 | J33: =STDEV.S(F22:F33)*SQRT(12) | K33: =IF(AND(G33>$P$6,H33>$P$7,I33>$P$8,D33>E33,J33<$P$10),1,0) | L33: =IF(SUM(K33,T33,AC33)=0,0,K33/SUM(K33,T33,AC33)) | M33: =E628 | N33: =I628 | O33: =M33/M32-1 | P33: =M33/M30-1 | Q33: =M33/M27-1 | R33: =M33/M21-1 | S33: =STDEV.S(O22:O33)*SQRT(12) | T33: =IF(AND(P33>$P$6,Q33>$P$7,R33>$P$8,M33>N33,S33<$P$10),1,0) | U33: =IF(SUM(K33,T33,AC33)=0,0,T33/SUM(K33,T33,AC33)) | V33: =F628 | W33: =J628 | X33: =V33/V32-1 | Y33: =V33/V30-1 | Z33: =V33/V27-1 | AA33: =V33/V21-1 | AB33: =STDEV.S(X22:X33)*SQRT(12) | AC33: =IF(AND(Y33>$P$6,Z33>$P$7,AA33>$P$8,V33>W33,AB33<$P$10),1,0) | AD33: =IF(SUM(K33,T33,AC33)=0,0,AC33/SUM(K33,T33,AC33)) | AE33: =IF(SUM(K33,T33,AC33)=0,1,0) | AF33: =G628 | AG33: =AF33/AF32-1
C34: 40390 | D34: =D649 | E34: =H649 | F34: =D34/D33-1 | G34: =D34/D31-1 | H34: =D34/D28-1 | I34: =D34/D22-1 | J34: =STDEV.S(F23:F34)*SQRT(12) | K34: =IF(AND(G34>$P$6,H34>$P$7,I34>$P$8,D34>E34,J34<$P$10),1,0) | L34: =IF(SUM(K34,T34,AC34)=0,0,K34/SUM(K34,T34,AC34)) | M34: =E649 | N34: =I649 | O34: =M34/M33-1 | P34: =M34/M31-1 | Q34: =M34/M28-1 | R34: =M34/M22-1 | S34: =STDEV.S(O23:O34)*SQRT(12) | T34: =IF(AND(P34>$P$6,Q34>$P$7,R34>$P$8,M34>N34,S34<$P$10),1,0) | U34: =IF(SUM(K34,T34,AC34)=0,0,T34/SUM(K34,T34,AC34)) | V34: =F649 | W34: =J649 | X34: =V34/V33-1 | Y34: =V34/V31-1 | Z34: =V34/V28-1 | AA34: =V34/V22-1 | AB34: =STDEV.S(X23:X34)*SQRT(12) | AC34: =IF(AND(Y34>$P$6,Z34>$P$7,AA34>$P$8,V34>W34,AB34<$P$10),1,0) | AD34: =IF(SUM(K34,T34,AC34)=0,0,AC34/SUM(K34,T34,AC34)) | AE34: =IF(SUM(K34,T34,AC34)=0,1,0) | AF34: =G649 | AG34: =AF34/AF33-1
C35: 40421 | D35: =D671 | E35: =H671 | F35: =D35/D34-1 | G35: =D35/D32-1 | H35: =D35/D29-1 | I35: =D35/D23-1 | J35: =STDEV.S(F24:F35)*SQRT(12) | K35: =IF(AND(G35>$P$6,H35>$P$7,I35>$P$8,D35>E35,J35<$P$10),1,0) | L35: =IF(SUM(K35,T35,AC35)=0,0,K35/SUM(K35,T35,AC35)) | M35: =E671 | N35: =I671 | O35: =M35/M34-1 | P35: =M35/M32-1 | Q35: =M35/M29-1 | R35: =M35/M23-1 | S35: =STDEV.S(O24:O35)*SQRT(12) | T35: =IF(AND(P35>$P$6,Q35>$P$7,R35>$P$8,M35>N35,S35<$P$10),1,0) | U35: =IF(SUM(K35,T35,AC35)=0,0,T35/SUM(K35,T35,AC35)) | V35: =F671 | W35: =J671 | X35: =V35/V34-1 | Y35: =V35/V32-1 | Z35: =V35/V29-1 | AA35: =V35/V23-1 | AB35: =STDEV.S(X24:X35)*SQRT(12) | AC35: =IF(AND(Y35>$P$6,Z35>$P$7,AA35>$P$8,V35>W35,AB35<$P$10),1,0) | AD35: =IF(SUM(K35,T35,AC35)=0,0,AC35/SUM(K35,T35,AC35)) | AE35: =IF(SUM(K35,T35,AC35)=0,1,0) | AF35: =G671 | AG35: =AF35/AF34-1
C36: 40451 | D36: =D692 | E36: =H692 | F36: =D36/D35-1 | G36: =D36/D33-1 | H36: =D36/D30-1 | I36: =D36/D24-1 | J36: =STDEV.S(F25:F36)*SQRT(12) | K36: =IF(AND(G36>$P$6,H36>$P$7,I36>$P$8,D36>E36,J36<$P$10),1,0) | L36: =IF(SUM(K36,T36,AC36)=0,0,K36/SUM(K36,T36,AC36)) | M36: =E692 | N36: =I692 | O36: =M36/M35-1 | P36: =M36/M33-1 | Q36: =M36/M30-1 | R36: =M36/M24-1 | S36: =STDEV.S(O25:O36)*SQRT(12) | T36: =IF(AND(P36>$P$6,Q36>$P$7,R36>$P$8,M36>N36,S36<$P$10),1,0) | U36: =IF(SUM(K36,T36,AC36)=0,0,T36/SUM(K36,T36,AC36)) | V36: =F692 | W36: =J692 | X36: =V36/V35-1 | Y36: =V36/V33-1 | Z36: =V36/V30-1 | AA36: =V36/V24-1 | AB36: =STDEV.S(X25:X36)*SQRT(12) | AC36: =IF(AND(Y36>$P$6,Z36>$P$7,AA36>$P$8,V36>W36,AB36<$P$10),1,0) | AD36: =IF(SUM(K36,T36,AC36)=0,0,AC36/SUM(K36,T36,AC36)) | AE36: =IF(SUM(K36,T36,AC36)=0,1,0) | AF36: =G692 | AG36: =AF36/AF35-1
C37: 40482 | D37: =D713 | E37: =H713 | F37: =D37/D36-1 | G37: =D37/D34-1 | H37: =D37/D31-1 | I37: =D37/D25-1 | J37: =STDEV.S(F26:F37)*SQRT(12) | K37: =IF(AND(G37>$P$6,H37>$P$7,I37>$P$8,D37>E37,J37<$P$10),1,0) | L37: =IF(SUM(K37,T37,AC37)=0,0,K37/SUM(K37,T37,AC37)) | M37: =E713 | N37: =I713 | O37: =M37/M36-1 | P37: =M37/M34-1 | Q37: =M37/M31-1 | R37: =M37/M25-1 | S37: =STDEV.S(O26:O37)*SQRT(12) | T37: =IF(AND(P37>$P$6,Q37>$P$7,R37>$P$8,M37>N37,S37<$P$10),1,0) | U37: =IF(SUM(K37,T37,AC37)=0,0,T37/SUM(K37,T37,AC37)) | V37: =F713 | W37: =J713 | X37: =V37/V36-1 | Y37: =V37/V34-1 | Z37: =V37/V31-1 | AA37: =V37/V25-1 | AB37: =STDEV.S(X26:X37)*SQRT(12) | AC37: =IF(AND(Y37>$P$6,Z37>$P$7,AA37>$P$8,V37>W37,AB37<$P$10),1,0) | AD37: =IF(SUM(K37,T37,AC37)=0,0,AC37/SUM(K37,T37,AC37)) | AE37: =IF(SUM(K37,T37,AC37)=0,1,0) | AF37: =G713 | AG37: =AF37/AF36-1
C38: 40512 | D38: =D734 | E38: =H734 | F38: =D38/D37-1 | G38: =D38/D35-1 | H38: =D38/D32-1 | I38: =D38/D26-1 | J38: =STDEV.S(F27:F38)*SQRT(12) | K38: =IF(AND(G38>$P$6,H38>$P$7,I38>$P$8,D38>E38,J38<$P$10),1,0) | L38: =IF(SUM(K38,T38,AC38)=0,0,K38/SUM(K38,T38,AC38)) | M38: =E734 | N38: =I734 | O38: =M38/M37-1 | P38: =M38/M35-1 | Q38: =M38/M32-1 | R38: =M38/M26-1 | S38: =STDEV.S(O27:O38)*SQRT(12) | T38: =IF(AND(P38>$P$6,Q38>$P$7,R38>$P$8,M38>N38,S38<$P$10),1,0) | U38: =IF(SUM(K38,T38,AC38)=0,0,T38/SUM(K38,T38,AC38)) | V38: =F734 | W38: =J734 | X38: =V38/V37-1 | Y38: =V38/V35-1 | Z38: =V38/V32-1 | AA38: =V38/V26-1 | AB38: =STDEV.S(X27:X38)*SQRT(12) | AC38: =IF(AND(Y38>$P$6,Z38>$P$7,AA38>$P$8,V38>W38,AB38<$P$10),1,0) | AD38: =IF(SUM(K38,T38,AC38)=0,0,AC38/SUM(K38,T38,AC38)) | AE38: =IF(SUM(K38,T38,AC38)=0,1,0) | AF38: =G734 | AG38: =AF38/AF37-1
C39: 40543 | D39: =D756 | E39: =H756 | F39: =D39/D38-1 | G39: =D39/D36-1 | H39: =D39/D33-1 | I39: =D39/D27-1 | J39: =STDEV.S(F28:F39)*SQRT(12) | K39: =IF(AND(G39>$P$6,H39>$P$7,I39>$P$8,D39>E39,J39<$P$10),1,0) | L39: =IF(SUM(K39,T39,AC39)=0,0,K39/SUM(K39,T39,AC39)) | M39: =E756 | N39: =I756 | O39: =M39/M38-1 | P39: =M39/M36-1 | Q39: =M39/M33-1 | R39: =M39/M27-1 | S39: =STDEV.S(O28:O39)*SQRT(12) | T39: =IF(AND(P39>$P$6,Q39>$P$7,R39>$P$8,M39>N39,S39<$P$10),1,0) | U39: =IF(SUM(K39,T39,AC39)=0,0,T39/SUM(K39,T39,AC39)) | V39: =F756 | W39: =J756 | X39: =V39/V38-1 | Y39: =V39/V36-1 | Z39: =V39/V33-1 | AA39: =V39/V27-1 | AB39: =STDEV.S(X28:X39)*SQRT(12) | AC39: =IF(AND(Y39>$P$6,Z39>$P$7,AA39>$P$8,V39>W39,AB39<$P$10),1,0) | AD39: =IF(SUM(K39,T39,AC39)=0,0,AC39/SUM(K39,T39,AC39)) | AE39: =IF(SUM(K39,T39,AC39)=0,1,0) | AF39: =G756 | AG39: =AF39/AF38-1
C40: 40574 | D40: =D776 | E40: =H776 | F40: =D40/D39-1 | G40: =D40/D37-1 | H40: =D40/D34-1 | I40: =D40/D28-1 | J40: =STDEV.S(F29:F40)*SQRT(12) | K40: =IF(AND(G40>$P$6,H40>$P$7,I40>$P$8,D40>E40,J40<$P$10),1,0) | L40: =IF(SUM(K40,T40,AC40)=0,0,K40/SUM(K40,T40,AC40)) | M40: =E776 | N40: =I776 | O40: =M40/M39-1 | P40: =M40/M37-1 | Q40: =M40/M34-1 | R40: =M40/M28-1 | S40: =STDEV.S(O29:O40)*SQRT(12) | T40: =IF(AND(P40>$P$6,Q40>$P$7,R40>$P$8,M40>N40,S40<$P$10),1,0) | U40: =IF(SUM(K40,T40,AC40)=0,0,T40/SUM(K40,T40,AC40)) | V40: =F776 | W40: =J776 | X40: =V40/V39-1 | Y40: =V40/V37-1 | Z40: =V40/V34-1 | AA40: =V40/V28-1 | AB40: =STDEV.S(X29:X40)*SQRT(12) | AC40: =IF(AND(Y40>$P$6,Z40>$P$7,AA40>$P$8,V40>W40,AB40<$P$10),1,0) | AD40: =IF(SUM(K40,T40,AC40)=0,0,AC40/SUM(K40,T40,AC40)) | AE40: =IF(SUM(K40,T40,AC40)=0,1,0) | AF40: =G776 | AG40: =AF40/AF39-1 | AL40: 100 | AM40: 100 | AN40: 0
C41: 40602 | D41: =D795 | E41: =H795 | F41: =D41/D40-1 | G41: =D41/D38-1 | H41: =D41/D35-1 | I41: =D41/D29-1 | J41: =STDEV.S(F30:F41)*SQRT(12) | K41: =IF(AND(G41>$P$6,H41>$P$7,I41>$P$8,D41>E41,J41<$P$10),1,0) | L41: =IF(SUM(K41,T41,AC41)=0,0,K41/SUM(K41,T41,AC41)) | M41: =E795 | N41: =I795 | O41: =M41/M40-1 | P41: =M41/M38-1 | Q41: =M41/M35-1 | R41: =M41/M29-1 | S41: =STDEV.S(O30:O41)*SQRT(12) | T41: =IF(AND(P41>$P$6,Q41>$P$7,R41>$P$8,M41>N41,S41<$P$10),1,0) | U41: =IF(SUM(K41,T41,AC41)=0,0,T41/SUM(K41,T41,AC41)) | V41: =F795 | W41: =J795 | X41: =V41/V40-1 | Y41: =V41/V38-1 | Z41: =V41/V35-1 | AA41: =V41/V29-1 | AB41: =STDEV.S(X30:X41)*SQRT(12) | AC41: =IF(AND(Y41>$P$6,Z41>$P$7,AA41>$P$8,V41>W41,AB41<$P$10),1,0) | AD41: =IF(SUM(K41,T41,AC41)=0,0,AC41/SUM(K41,T41,AC41)) | AE41: =IF(SUM(K41,T41,AC41)=0,1,0) | AF41: =G795 | AG41: =AF41/AF40-1 | AH41: =0.5*(ABS(L40-L39)+ABS(U40-U39)+ABS(AD40-AD39)+ABS(AE40-AE39)) | AI41: =L40*F41+U40*O41+AD40*X41+AE40*AG41 | AJ41: =AH41*$P$11 | AK41: =AI41-AJ41 | AL41: =AL40*(1+AK41) | AM41: =MAX($AL$40:AL41) | AN41: =AL41/AM41-1 | AO41: =AK41-AG41
C42: 40633 | D42: =D818 | E42: =H818 | F42: =D42/D41-1 | G42: =D42/D39-1 | H42: =D42/D36-1 | I42: =D42/D30-1 | J42: =STDEV.S(F31:F42)*SQRT(12) | K42: =IF(AND(G42>$P$6,H42>$P$7,I42>$P$8,D42>E42,J42<$P$10),1,0) | L42: =IF(SUM(K42,T42,AC42)=0,0,K42/SUM(K42,T42,AC42)) | M42: =E818 | N42: =I818 | O42: =M42/M41-1 | P42: =M42/M39-1 | Q42: =M42/M36-1 | R42: =M42/M30-1 | S42: =STDEV.S(O31:O42)*SQRT(12) | T42: =IF(AND(P42>$P$6,Q42>$P$7,R42>$P$8,M42>N42,S42<$P$10),1,0) | U42: =IF(SUM(K42,T42,AC42)=0,0,T42/SUM(K42,T42,AC42)) | V42: =F818 | W42: =J818 | X42: =V42/V41-1 | Y42: =V42/V39-1 | Z42: =V42/V36-1 | AA42: =V42/V30-1 | AB42: =STDEV.S(X31:X42)*SQRT(12) | AC42: =IF(AND(Y42>$P$6,Z42>$P$7,AA42>$P$8,V42>W42,AB42<$P$10),1,0) | AD42: =IF(SUM(K42,T42,AC42)=0,0,AC42/SUM(K42,T42,AC42)) | AE42: =IF(SUM(K42,T42,AC42)=0,1,0) | AF42: =G818 | AG42: =AF42/AF41-1 | AH42: =0.5*(ABS(L41-L40)+ABS(U41-U40)+ABS(AD41-AD40)+ABS(AE41-AE40)) | AI42: =L41*F42+U41*O42+AD41*X42+AE41*AG42 | AJ42: =AH42*$P$11 | AK42: =AI42-AJ42 | AL42: =AL41*(1+AK42) | AM42: =MAX($AL$40:AL42) | AN42: =AL42/AM42-1 | AO42: =AK42-AG42
C43: 40663 | D43: =D838 | E43: =H838 | F43: =D43/D42-1 | G43: =D43/D40-1 | H43: =D43/D37-1 | I43: =D43/D31-1 | J43: =STDEV.S(F32:F43)*SQRT(12) | K43: =IF(AND(G43>$P$6,H43>$P$7,I43>$P$8,D43>E43,J43<$P$10),1,0) | L43: =IF(SUM(K43,T43,AC43)=0,0,K43/SUM(K43,T43,AC43)) | M43: =E838 | N43: =I838 | O43: =M43/M42-1 | P43: =M43/M40-1 | Q43: =M43/M37-1 | R43: =M43/M31-1 | S43: =STDEV.S(O32:O43)*SQRT(12) | T43: =IF(AND(P43>$P$6,Q43>$P$7,R43>$P$8,M43>N43,S43<$P$10),1,0) | U43: =IF(SUM(K43,T43,AC43)=0,0,T43/SUM(K43,T43,AC43)) | V43: =F838 | W43: =J838 | X43: =V43/V42-1 | Y43: =V43/V40-1 | Z43: =V43/V37-1 | AA43: =V43/V31-1 | AB43: =STDEV.S(X32:X43)*SQRT(12) | AC43: =IF(AND(Y43>$P$6,Z43>$P$7,AA43>$P$8,V43>W43,AB43<$P$10),1,0) | AD43: =IF(SUM(K43,T43,AC43)=0,0,AC43/SUM(K43,T43,AC43)) | AE43: =IF(SUM(K43,T43,AC43)=0,1,0) | AF43: =G838 | AG43: =AF43/AF42-1 | AH43: =0.5*(ABS(L42-L41)+ABS(U42-U41)+ABS(AD42-AD41)+ABS(AE42-AE41)) | AI43: =L42*F43+U42*O43+AD42*X43+AE42*AG43 | AJ43: =AH43*$P$11 | AK43: =AI43-AJ43 | AL43: =AL42*(1+AK43) | AM43: =MAX($AL$40:AL43) | AN43: =AL43/AM43-1 | AO43: =AK43-AG43
C44: 40694 | D44: =D859 | E44: =H859 | F44: =D44/D43-1 | G44: =D44/D41-1 | H44: =D44/D38-1 | I44: =D44/D32-1 | J44: =STDEV.S(F33:F44)*SQRT(12) | K44: =IF(AND(G44>$P$6,H44>$P$7,I44>$P$8,D44>E44,J44<$P$10),1,0) | L44: =IF(SUM(K44,T44,AC44)=0,0,K44/SUM(K44,T44,AC44)) | M44: =E859 | N44: =I859 | O44: =M44/M43-1 | P44: =M44/M41-1 | Q44: =M44/M38-1 | R44: =M44/M32-1 | S44: =STDEV.S(O33:O44)*SQRT(12) | T44: =IF(AND(P44>$P$6,Q44>$P$7,R44>$P$8,M44>N44,S44<$P$10),1,0) | U44: =IF(SUM(K44,T44,AC44)=0,0,T44/SUM(K44,T44,AC44)) | V44: =F859 | W44: =J859 | X44: =V44/V43-1 | Y44: =V44/V41-1 | Z44: =V44/V38-1 | AA44: =V44/V32-1 | AB44: =STDEV.S(X33:X44)*SQRT(12) | AC44: =IF(AND(Y44>$P$6,Z44>$P$7,AA44>$P$8,V44>W44,AB44<$P$10),1,0) | AD44: =IF(SUM(K44,T44,AC44)=0,0,AC44/SUM(K44,T44,AC44)) | AE44: =IF(SUM(K44,T44,AC44)=0,1,0) | AF44: =G859 | AG44: =AF44/AF43-1 | AH44: =0.5*(ABS(L43-L42)+ABS(U43-U42)+ABS(AD43-AD42)+ABS(AE43-AE42)) | AI44: =L43*F44+U43*O44+AD43*X44+AE43*AG44 | AJ44: =AH44*$P$11 | AK44: =AI44-AJ44 | AL44: =AL43*(1+AK44) | AM44: =MAX($AL$40:AL44) | AN44: =AL44/AM44-1 | AO44: =AK44-AG44
C45: 40724 | D45: =D881 | E45: =H881 | F45: =D45/D44-1 | G45: =D45/D42-1 | H45: =D45/D39-1 | I45: =D45/D33-1 | J45: =STDEV.S(F34:F45)*SQRT(12) | K45: =IF(AND(G45>$P$6,H45>$P$7,I45>$P$8,D45>E45,J45<$P$10),1,0) | L45: =IF(SUM(K45,T45,AC45)=0,0,K45/SUM(K45,T45,AC45)) | M45: =E881 | N45: =I881 | O45: =M45/M44-1 | P45: =M45/M42-1 | Q45: =M45/M39-1 | R45: =M45/M33-1 | S45: =STDEV.S(O34:O45)*SQRT(12) | T45: =IF(AND(P45>$P$6,Q45>$P$7,R45>$P$8,M45>N45,S45<$P$10),1,0) | U45: =IF(SUM(K45,T45,AC45)=0,0,T45/SUM(K45,T45,AC45)) | V45: =F881 | W45: =J881 | X45: =V45/V44-1 | Y45: =V45/V42-1 | Z45: =V45/V39-1 | AA45: =V45/V33-1 | AB45: =STDEV.S(X34:X45)*SQRT(12) | AC45: =IF(AND(Y45>$P$6,Z45>$P$7,AA45>$P$8,V45>W45,AB45<$P$10),1,0) | AD45: =IF(SUM(K45,T45,AC45)=0,0,AC45/SUM(K45,T45,AC45)) | AE45: =IF(SUM(K45,T45,AC45)=0,1,0) | AF45: =G881 | AG45: =AF45/AF44-1 | AH45: =0.5*(ABS(L44-L43)+ABS(U44-U43)+ABS(AD44-AD43)+ABS(AE44-AE43)) | AI45: =L44*F45+U44*O45+AD44*X45+AE44*AG45 | AJ45: =AH45*$P$11 | AK45: =AI45-AJ45 | AL45: =AL44*(1+AK45) | AM45: =MAX($AL$40:AL45) | AN45: =AL45/AM45-1 | AO45: =AK45-AG45
C46: 40755 | D46: =D901 | E46: =H901 | F46: =D46/D45-1 | G46: =D46/D43-1 | H46: =D46/D40-1 | I46: =D46/D34-1 | J46: =STDEV.S(F35:F46)*SQRT(12) | K46: =IF(AND(G46>$P$6,H46>$P$7,I46>$P$8,D46>E46,J46<$P$10),1,0) | L46: =IF(SUM(K46,T46,AC46)=0,0,K46/SUM(K46,T46,AC46)) | M46: =E901 | N46: =I901 | O46: =M46/M45-1 | P46: =M46/M43-1 | Q46: =M46/M40-1 | R46: =M46/M34-1 | S46: =STDEV.S(O35:O46)*SQRT(12) | T46: =IF(AND(P46>$P$6,Q46>$P$7,R46>$P$8,M46>N46,S46<$P$10),1,0) | U46: =IF(SUM(K46,T46,AC46)=0,0,T46/SUM(K46,T46,AC46)) | V46: =F901 | W46: =J901 | X46: =V46/V45-1 | Y46: =V46/V43-1 | Z46: =V46/V40-1 | AA46: =V46/V34-1 | AB46: =STDEV.S(X35:X46)*SQRT(12) | AC46: =IF(AND(Y46>$P$6,Z46>$P$7,AA46>$P$8,V46>W46,AB46<$P$10),1,0) | AD46: =IF(SUM(K46,T46,AC46)=0,0,AC46/SUM(K46,T46,AC46)) | AE46: =IF(SUM(K46,T46,AC46)=0,1,0) | AF46: =G901 | AG46: =AF46/AF45-1 | AH46: =0.5*(ABS(L45-L44)+ABS(U45-U44)+ABS(AD45-AD44)+ABS(AE45-AE44)) | AI46: =L45*F46+U45*O46+AD45*X46+AE45*AG46 | AJ46: =AH46*$P$11 | AK46: =AI46-AJ46 | AL46: =AL45*(1+AK46) | AM46: =MAX($AL$40:AL46) | AN46: =AL46/AM46-1 | AO46: =AK46-AG46
C47: 40786 | D47: =D924 | E47: =H924 | F47: =D47/D46-1 | G47: =D47/D44-1 | H47: =D47/D41-1 | I47: =D47/D35-1 | J47: =STDEV.S(F36:F47)*SQRT(12) | K47: =IF(AND(G47>$P$6,H47>$P$7,I47>$P$8,D47>E47,J47<$P$10),1,0) | L47: =IF(SUM(K47,T47,AC47)=0,0,K47/SUM(K47,T47,AC47)) | M47: =E924 | N47: =I924 | O47: =M47/M46-1 | P47: =M47/M44-1 | Q47: =M47/M41-1 | R47: =M47/M35-1 | S47: =STDEV.S(O36:O47)*SQRT(12) | T47: =IF(AND(P47>$P$6,Q47>$P$7,R47>$P$8,M47>N47,S47<$P$10),1,0) | U47: =IF(SUM(K47,T47,AC47)=0,0,T47/SUM(K47,T47,AC47)) | V47: =F924 | W47: =J924 | X47: =V47/V46-1 | Y47: =V47/V44-1 | Z47: =V47/V41-1 | AA47: =V47/V35-1 | AB47: =STDEV.S(X36:X47)*SQRT(12) | AC47: =IF(AND(Y47>$P$6,Z47>$P$7,AA47>$P$8,V47>W47,AB47<$P$10),1,0) | AD47: =IF(SUM(K47,T47,AC47)=0,0,AC47/SUM(K47,T47,AC47)) | AE47: =IF(SUM(K47,T47,AC47)=0,1,0) | AF47: =G924 | AG47: =AF47/AF46-1 | AH47: =0.5*(ABS(L46-L45)+ABS(U46-U45)+ABS(AD46-AD45)+ABS(AE46-AE45)) | AI47: =L46*F47+U46*O47+AD46*X47+AE46*AG47 | AJ47: =AH47*$P$11 | AK47: =AI47-AJ47 | AL47: =AL46*(1+AK47) | AM47: =MAX($AL$40:AL47) | AN47: =AL47/AM47-1 | AO47: =AK47-AG47
C48: 40816 | D48: =D945 | E48: =H945 | F48: =D48/D47-1 | G48: =D48/D45-1 | H48: =D48/D42-1 | I48: =D48/D36-1 | J48: =STDEV.S(F37:F48)*SQRT(12) | K48: =IF(AND(G48>$P$6,H48>$P$7,I48>$P$8,D48>E48,J48<$P$10),1,0) | L48: =IF(SUM(K48,T48,AC48)=0,0,K48/SUM(K48,T48,AC48)) | M48: =E945 | N48: =I945 | O48: =M48/M47-1 | P48: =M48/M45-1 | Q48: =M48/M42-1 | R48: =M48/M36-1 | S48: =STDEV.S(O37:O48)*SQRT(12) | T48: =IF(AND(P48>$P$6,Q48>$P$7,R48>$P$8,M48>N48,S48<$P$10),1,0) | U48: =IF(SUM(K48,T48,AC48)=0,0,T48/SUM(K48,T48,AC48)) | V48: =F945 | W48: =J945 | X48: =V48/V47-1 | Y48: =V48/V45-1 | Z48: =V48/V42-1 | AA48: =V48/V36-1 | AB48: =STDEV.S(X37:X48)*SQRT(12) | AC48: =IF(AND(Y48>$P$6,Z48>$P$7,AA48>$P$8,V48>W48,AB48<$P$10),1,0) | AD48: =IF(SUM(K48,T48,AC48)=0,0,AC48/SUM(K48,T48,AC48)) | AE48: =IF(SUM(K48,T48,AC48)=0,1,0) | AF48: =G945 | AG48: =AF48/AF47-1 | AH48: =0.5*(ABS(L47-L46)+ABS(U47-U46)+ABS(AD47-AD46)+ABS(AE47-AE46)) | AI48: =L47*F48+U47*O48+AD47*X48+AE47*AG48 | AJ48: =AH48*$P$11 | AK48: =AI48-AJ48 | AL48: =AL47*(1+AK48) | AM48: =MAX($AL$40:AL48) | AN48: =AL48/AM48-1 | AO48: =AK48-AG48
C49: 40847 | D49: =D966 | E49: =H966 | F49: =D49/D48-1 | G49: =D49/D46-1 | H49: =D49/D43-1 | I49: =D49/D37-1 | J49: =STDEV.S(F38:F49)*SQRT(12) | K49: =IF(AND(G49>$P$6,H49>$P$7,I49>$P$8,D49>E49,J49<$P$10),1,0) | L49: =IF(SUM(K49,T49,AC49)=0,0,K49/SUM(K49,T49,AC49)) | M49: =E966 | N49: =I966 | O49: =M49/M48-1 | P49: =M49/M46-1 | Q49: =M49/M43-1 | R49: =M49/M37-1 | S49: =STDEV.S(O38:O49)*SQRT(12) | T49: =IF(AND(P49>$P$6,Q49>$P$7,R49>$P$8,M49>N49,S49<$P$10),1,0) | U49: =IF(SUM(K49,T49,AC49)=0,0,T49/SUM(K49,T49,AC49)) | V49: =F966 | W49: =J966 | X49: =V49/V48-1 | Y49: =V49/V46-1 | Z49: =V49/V43-1 | AA49: =V49/V37-1 | AB49: =STDEV.S(X38:X49)*SQRT(12) | AC49: =IF(AND(Y49>$P$6,Z49>$P$7,AA49>$P$8,V49>W49,AB49<$P$10),1,0) | AD49: =IF(SUM(K49,T49,AC49)=0,0,AC49/SUM(K49,T49,AC49)) | AE49: =IF(SUM(K49,T49,AC49)=0,1,0) | AF49: =G966 | AG49: =AF49/AF48-1 | AH49: =0.5*(ABS(L48-L47)+ABS(U48-U47)+ABS(AD48-AD47)+ABS(AE48-AE47)) | AI49: =L48*F49+U48*O49+AD48*X49+AE48*AG49 | AJ49: =AH49*$P$11 | AK49: =AI49-AJ49 | AL49: =AL48*(1+AK49) | AM49: =MAX($AL$40:AL49) | AN49: =AL49/AM49-1 | AO49: =AK49-AG49
C50: 40877 | D50: =D987 | E50: =H987 | F50: =D50/D49-1 | G50: =D50/D47-1 | H50: =D50/D44-1 | I50: =D50/D38-1 | J50: =STDEV.S(F39:F50)*SQRT(12) | K50: =IF(AND(G50>$P$6,H50>$P$7,I50>$P$8,D50>E50,J50<$P$10),1,0) | L50: =IF(SUM(K50,T50,AC50)=0,0,K50/SUM(K50,T50,AC50)) | M50: =E987 | N50: =I987 | O50: =M50/M49-1 | P50: =M50/M47-1 | Q50: =M50/M44-1 | R50: =M50/M38-1 | S50: =STDEV.S(O39:O50)*SQRT(12) | T50: =IF(AND(P50>$P$6,Q50>$P$7,R50>$P$8,M50>N50,S50<$P$10),1,0) | U50: =IF(SUM(K50,T50,AC50)=0,0,T50/SUM(K50,T50,AC50)) | V50: =F987 | W50: =J987 | X50: =V50/V49-1 | Y50: =V50/V47-1 | Z50: =V50/V44-1 | AA50: =V50/V38-1 | AB50: =STDEV.S(X39:X50)*SQRT(12) | AC50: =IF(AND(Y50>$P$6,Z50>$P$7,AA50>$P$8,V50>W50,AB50<$P$10),1,0) | AD50: =IF(SUM(K50,T50,AC50)=0,0,AC50/SUM(K50,T50,AC50)) | AE50: =IF(SUM(K50,T50,AC50)=0,1,0) | AF50: =G987 | AG50: =AF50/AF49-1 | AH50: =0.5*(ABS(L49-L48)+ABS(U49-U48)+ABS(AD49-AD48)+ABS(AE49-AE48)) | AI50: =L49*F50+U49*O50+AD49*X50+AE49*AG50 | AJ50: =AH50*$P$11 | AK50: =AI50-AJ50 | AL50: =AL49*(1+AK50) | AM50: =MAX($AL$40:AL50) | AN50: =AL50/AM50-1 | AO50: =AK50-AG50
C51: 40908 | D51: =D1008 | E51: =H1008 | F51: =D51/D50-1 | G51: =D51/D48-1 | H51: =D51/D45-1 | I51: =D51/D39-1 | J51: =STDEV.S(F40:F51)*SQRT(12) | K51: =IF(AND(G51>$P$6,H51>$P$7,I51>$P$8,D51>E51,J51<$P$10),1,0) | L51: =IF(SUM(K51,T51,AC51)=0,0,K51/SUM(K51,T51,AC51)) | M51: =E1008 | N51: =I1008 | O51: =M51/M50-1 | P51: =M51/M48-1 | Q51: =M51/M45-1 | R51: =M51/M39-1 | S51: =STDEV.S(O40:O51)*SQRT(12) | T51: =IF(AND(P51>$P$6,Q51>$P$7,R51>$P$8,M51>N51,S51<$P$10),1,0) | U51: =IF(SUM(K51,T51,AC51)=0,0,T51/SUM(K51,T51,AC51)) | V51: =F1008 | W51: =J1008 | X51: =V51/V50-1 | Y51: =V51/V48-1 | Z51: =V51/V45-1 | AA51: =V51/V39-1 | AB51: =STDEV.S(X40:X51)*SQRT(12) | AC51: =IF(AND(Y51>$P$6,Z51>$P$7,AA51>$P$8,V51>W51,AB51<$P$10),1,0) | AD51: =IF(SUM(K51,T51,AC51)=0,0,AC51/SUM(K51,T51,AC51)) | AE51: =IF(SUM(K51,T51,AC51)=0,1,0) | AF51: =G1008 | AG51: =AF51/AF50-1 | AH51: =0.5*(ABS(L50-L49)+ABS(U50-U49)+ABS(AD50-AD49)+ABS(AE50-AE49)) | AI51: =L50*F51+U50*O51+AD50*X51+AE50*AG51 | AJ51: =AH51*$P$11 | AK51: =AI51-AJ51 | AL51: =AL50*(1+AK51) | AM51: =MAX($AL$40:AL51) | AN51: =AL51/AM51-1 | AO51: =AK51-AG51
C52: 40939 | D52: =D1028 | E52: =H1028 | F52: =D52/D51-1 | G52: =D52/D49-1 | H52: =D52/D46-1 | I52: =D52/D40-1 | J52: =STDEV.S(F41:F52)*SQRT(12) | K52: =IF(AND(G52>$P$6,H52>$P$7,I52>$P$8,D52>E52,J52<$P$10),1,0) | L52: =IF(SUM(K52,T52,AC52)=0,0,K52/SUM(K52,T52,AC52)) | M52: =E1028 | N52: =I1028 | O52: =M52/M51-1 | P52: =M52/M49-1 | Q52: =M52/M46-1 | R52: =M52/M40-1 | S52: =STDEV.S(O41:O52)*SQRT(12) | T52: =IF(AND(P52>$P$6,Q52>$P$7,R52>$P$8,M52>N52,S52<$P$10),1,0) | U52: =IF(SUM(K52,T52,AC52)=0,0,T52/SUM(K52,T52,AC52)) | V52: =F1028 | W52: =J1028 | X52: =V52/V51-1 | Y52: =V52/V49-1 | Z52: =V52/V46-1 | AA52: =V52/V40-1 | AB52: =STDEV.S(X41:X52)*SQRT(12) | AC52: =IF(AND(Y52>$P$6,Z52>$P$7,AA52>$P$8,V52>W52,AB52<$P$10),1,0) | AD52: =IF(SUM(K52,T52,AC52)=0,0,AC52/SUM(K52,T52,AC52)) | AE52: =IF(SUM(K52,T52,AC52)=0,1,0) | AF52: =G1028 | AG52: =AF52/AF51-1 | AH52: =0.5*(ABS(L51-L50)+ABS(U51-U50)+ABS(AD51-AD50)+ABS(AE51-AE50)) | AI52: =L51*F52+U51*O52+AD51*X52+AE51*AG52 | AJ52: =AH52*$P$11 | AK52: =AI52-AJ52 | AL52: =AL51*(1+AK52) | AM52: =MAX($AL$40:AL52) | AN52: =AL52/AM52-1 | AO52: =AK52-AG52
C53: 40968 | D53: =D1048 | E53: =H1048 | F53: =D53/D52-1 | G53: =D53/D50-1 | H53: =D53/D47-1 | I53: =D53/D41-1 | J53: =STDEV.S(F42:F53)*SQRT(12) | K53: =IF(AND(G53>$P$6,H53>$P$7,I53>$P$8,D53>E53,J53<$P$10),1,0) | L53: =IF(SUM(K53,T53,AC53)=0,0,K53/SUM(K53,T53,AC53)) | M53: =E1048 | N53: =I1048 | O53: =M53/M52-1 | P53: =M53/M50-1 | Q53: =M53/M47-1 | R53: =M53/M41-1 | S53: =STDEV.S(O42:O53)*SQRT(12) | T53: =IF(AND(P53>$P$6,Q53>$P$7,R53>$P$8,M53>N53,S53<$P$10),1,0) | U53: =IF(SUM(K53,T53,AC53)=0,0,T53/SUM(K53,T53,AC53)) | V53: =F1048 | W53: =J1048 | X53: =V53/V52-1 | Y53: =V53/V50-1 | Z53: =V53/V47-1 | AA53: =V53/V41-1 | AB53: =STDEV.S(X42:X53)*SQRT(12) | AC53: =IF(AND(Y53>$P$6,Z53>$P$7,AA53>$P$8,V53>W53,AB53<$P$10),1,0) | AD53: =IF(SUM(K53,T53,AC53)=0,0,AC53/SUM(K53,T53,AC53)) | AE53: =IF(SUM(K53,T53,AC53)=0,1,0) | AF53: =G1048 | AG53: =AF53/AF52-1 | AH53: =0.5*(ABS(L52-L51)+ABS(U52-U51)+ABS(AD52-AD51)+ABS(AE52-AE51)) | AI53: =L52*F53+U52*O53+AD52*X53+AE52*AG53 | AJ53: =AH53*$P$11 | AK53: =AI53-AJ53 | AL53: =AL52*(1+AK53) | AM53: =MAX($AL$40:AL53) | AN53: =AL53/AM53-1 | AO53: =AK53-AG53
C54: 40999 | D54: =D1070 | E54: =H1070 | F54: =D54/D53-1 | G54: =D54/D51-1 | H54: =D54/D48-1 | I54: =D54/D42-1 | J54: =STDEV.S(F43:F54)*SQRT(12) | K54: =IF(AND(G54>$P$6,H54>$P$7,I54>$P$8,D54>E54,J54<$P$10),1,0) | L54: =IF(SUM(K54,T54,AC54)=0,0,K54/SUM(K54,T54,AC54)) | M54: =E1070 | N54: =I1070 | O54: =M54/M53-1 | P54: =M54/M51-1 | Q54: =M54/M48-1 | R54: =M54/M42-1 | S54: =STDEV.S(O43:O54)*SQRT(12) | T54: =IF(AND(P54>$P$6,Q54>$P$7,R54>$P$8,M54>N54,S54<$P$10),1,0) | U54: =IF(SUM(K54,T54,AC54)=0,0,T54/SUM(K54,T54,AC54)) | V54: =F1070 | W54: =J1070 | X54: =V54/V53-1 | Y54: =V54/V51-1 | Z54: =V54/V48-1 | AA54: =V54/V42-1 | AB54: =STDEV.S(X43:X54)*SQRT(12) | AC54: =IF(AND(Y54>$P$6,Z54>$P$7,AA54>$P$8,V54>W54,AB54<$P$10),1,0) | AD54: =IF(SUM(K54,T54,AC54)=0,0,AC54/SUM(K54,T54,AC54)) | AE54: =IF(SUM(K54,T54,AC54)=0,1,0) | AF54: =G1070 | AG54: =AF54/AF53-1 | AH54: =0.5*(ABS(L53-L52)+ABS(U53-U52)+ABS(AD53-AD52)+ABS(AE53-AE52)) | AI54: =L53*F54+U53*O54+AD53*X54+AE53*AG54 | AJ54: =AH54*$P$11 | AK54: =AI54-AJ54 | AL54: =AL53*(1+AK54) | AM54: =MAX($AL$40:AL54) | AN54: =AL54/AM54-1 | AO54: =AK54-AG54
C55: 41029 | D55: =D1090 | E55: =H1090 | F55: =D55/D54-1 | G55: =D55/D52-1 | H55: =D55/D49-1 | I55: =D55/D43-1 | J55: =STDEV.S(F44:F55)*SQRT(12) | K55: =IF(AND(G55>$P$6,H55>$P$7,I55>$P$8,D55>E55,J55<$P$10),1,0) | L55: =IF(SUM(K55,T55,AC55)=0,0,K55/SUM(K55,T55,AC55)) | M55: =E1090 | N55: =I1090 | O55: =M55/M54-1 | P55: =M55/M52-1 | Q55: =M55/M49-1 | R55: =M55/M43-1 | S55: =STDEV.S(O44:O55)*SQRT(12) | T55: =IF(AND(P55>$P$6,Q55>$P$7,R55>$P$8,M55>N55,S55<$P$10),1,0) | U55: =IF(SUM(K55,T55,AC55)=0,0,T55/SUM(K55,T55,AC55)) | V55: =F1090 | W55: =J1090 | X55: =V55/V54-1 | Y55: =V55/V52-1 | Z55: =V55/V49-1 | AA55: =V55/V43-1 | AB55: =STDEV.S(X44:X55)*SQRT(12) | AC55: =IF(AND(Y55>$P$6,Z55>$P$7,AA55>$P$8,V55>W55,AB55<$P$10),1,0) | AD55: =IF(SUM(K55,T55,AC55)=0,0,AC55/SUM(K55,T55,AC55)) | AE55: =IF(SUM(K55,T55,AC55)=0,1,0) | AF55: =G1090 | AG55: =AF55/AF54-1 | AH55: =0.5*(ABS(L54-L53)+ABS(U54-U53)+ABS(AD54-AD53)+ABS(AE54-AE53)) | AI55: =L54*F55+U54*O55+AD54*X55+AE54*AG55 | AJ55: =AH55*$P$11 | AK55: =AI55-AJ55 | AL55: =AL54*(1+AK55) | AM55: =MAX($AL$40:AL55) | AN55: =AL55/AM55-1 | AO55: =AK55-AG55
C56: 41060 | D56: =D1112 | E56: =H1112 | F56: =D56/D55-1 | G56: =D56/D53-1 | H56: =D56/D50-1 | I56: =D56/D44-1 | J56: =STDEV.S(F45:F56)*SQRT(12) | K56: =IF(AND(G56>$P$6,H56>$P$7,I56>$P$8,D56>E56,J56<$P$10),1,0) | L56: =IF(SUM(K56,T56,AC56)=0,0,K56/SUM(K56,T56,AC56)) | M56: =E1112 | N56: =I1112 | O56: =M56/M55-1 | P56: =M56/M53-1 | Q56: =M56/M50-1 | R56: =M56/M44-1 | S56: =STDEV.S(O45:O56)*SQRT(12) | T56: =IF(AND(P56>$P$6,Q56>$P$7,R56>$P$8,M56>N56,S56<$P$10),1,0) | U56: =IF(SUM(K56,T56,AC56)=0,0,T56/SUM(K56,T56,AC56)) | V56: =F1112 | W56: =J1112 | X56: =V56/V55-1 | Y56: =V56/V53-1 | Z56: =V56/V50-1 | AA56: =V56/V44-1 | AB56: =STDEV.S(X45:X56)*SQRT(12) | AC56: =IF(AND(Y56>$P$6,Z56>$P$7,AA56>$P$8,V56>W56,AB56<$P$10),1,0) | AD56: =IF(SUM(K56,T56,AC56)=0,0,AC56/SUM(K56,T56,AC56)) | AE56: =IF(SUM(K56,T56,AC56)=0,1,0) | AF56: =G1112 | AG56: =AF56/AF55-1 | AH56: =0.5*(ABS(L55-L54)+ABS(U55-U54)+ABS(AD55-AD54)+ABS(AE55-AE54)) | AI56: =L55*F56+U55*O56+AD55*X56+AE55*AG56 | AJ56: =AH56*$P$11 | AK56: =AI56-AJ56 | AL56: =AL55*(1+AK56) | AM56: =MAX($AL$40:AL56) | AN56: =AL56/AM56-1 | AO56: =AK56-AG56
C57: 41090 | D57: =D1133 | E57: =H1133 | F57: =D57/D56-1 | G57: =D57/D54-1 | H57: =D57/D51-1 | I57: =D57/D45-1 | J57: =STDEV.S(F46:F57)*SQRT(12) | K57: =IF(AND(G57>$P$6,H57>$P$7,I57>$P$8,D57>E57,J57<$P$10),1,0) | L57: =IF(SUM(K57,T57,AC57)=0,0,K57/SUM(K57,T57,AC57)) | M57: =E1133 | N57: =I1133 | O57: =M57/M56-1 | P57: =M57/M54-1 | Q57: =M57/M51-1 | R57: =M57/M45-1 | S57: =STDEV.S(O46:O57)*SQRT(12) | T57: =IF(AND(P57>$P$6,Q57>$P$7,R57>$P$8,M57>N57,S57<$P$10),1,0) | U57: =IF(SUM(K57,T57,AC57)=0,0,T57/SUM(K57,T57,AC57)) | V57: =F1133 | W57: =J1133 | X57: =V57/V56-1 | Y57: =V57/V54-1 | Z57: =V57/V51-1 | AA57: =V57/V45-1 | AB57: =STDEV.S(X46:X57)*SQRT(12) | AC57: =IF(AND(Y57>$P$6,Z57>$P$7,AA57>$P$8,V57>W57,AB57<$P$10),1,0) | AD57: =IF(SUM(K57,T57,AC57)=0,0,AC57/SUM(K57,T57,AC57)) | AE57: =IF(SUM(K57,T57,AC57)=0,1,0) | AF57: =G1133 | AG57: =AF57/AF56-1 | AH57: =0.5*(ABS(L56-L55)+ABS(U56-U55)+ABS(AD56-AD55)+ABS(AE56-AE55)) | AI57: =L56*F57+U56*O57+AD56*X57+AE56*AG57 | AJ57: =AH57*$P$11 | AK57: =AI57-AJ57 | AL57: =AL56*(1+AK57) | AM57: =MAX($AL$40:AL57) | AN57: =AL57/AM57-1 | AO57: =AK57-AG57
C58: 41121 | D58: =D1154 | E58: =H1154 | F58: =D58/D57-1 | G58: =D58/D55-1 | H58: =D58/D52-1 | I58: =D58/D46-1 | J58: =STDEV.S(F47:F58)*SQRT(12) | K58: =IF(AND(G58>$P$6,H58>$P$7,I58>$P$8,D58>E58,J58<$P$10),1,0) | L58: =IF(SUM(K58,T58,AC58)=0,0,K58/SUM(K58,T58,AC58)) | M58: =E1154 | N58: =I1154 | O58: =M58/M57-1 | P58: =M58/M55-1 | Q58: =M58/M52-1 | R58: =M58/M46-1 | S58: =STDEV.S(O47:O58)*SQRT(12) | T58: =IF(AND(P58>$P$6,Q58>$P$7,R58>$P$8,M58>N58,S58<$P$10),1,0) | U58: =IF(SUM(K58,T58,AC58)=0,0,T58/SUM(K58,T58,AC58)) | V58: =F1154 | W58: =J1154 | X58: =V58/V57-1 | Y58: =V58/V55-1 | Z58: =V58/V52-1 | AA58: =V58/V46-1 | AB58: =STDEV.S(X47:X58)*SQRT(12) | AC58: =IF(AND(Y58>$P$6,Z58>$P$7,AA58>$P$8,V58>W58,AB58<$P$10),1,0) | AD58: =IF(SUM(K58,T58,AC58)=0,0,AC58/SUM(K58,T58,AC58)) | AE58: =IF(SUM(K58,T58,AC58)=0,1,0) | AF58: =G1154 | AG58: =AF58/AF57-1 | AH58: =0.5*(ABS(L57-L56)+ABS(U57-U56)+ABS(AD57-AD56)+ABS(AE57-AE56)) | AI58: =L57*F58+U57*O58+AD57*X58+AE57*AG58 | AJ58: =AH58*$P$11 | AK58: =AI58-AJ58 | AL58: =AL57*(1+AK58) | AM58: =MAX($AL$40:AL58) | AN58: =AL58/AM58-1 | AO58: =AK58-AG58
C59: 41152 | D59: =D1177 | E59: =H1177 | F59: =D59/D58-1 | G59: =D59/D56-1 | H59: =D59/D53-1 | I59: =D59/D47-1 | J59: =STDEV.S(F48:F59)*SQRT(12) | K59: =IF(AND(G59>$P$6,H59>$P$7,I59>$P$8,D59>E59,J59<$P$10),1,0) | L59: =IF(SUM(K59,T59,AC59)=0,0,K59/SUM(K59,T59,AC59)) | M59: =E1177 | N59: =I1177 | O59: =M59/M58-1 | P59: =M59/M56-1 | Q59: =M59/M53-1 | R59: =M59/M47-1 | S59: =STDEV.S(O48:O59)*SQRT(12) | T59: =IF(AND(P59>$P$6,Q59>$P$7,R59>$P$8,M59>N59,S59<$P$10),1,0) | U59: =IF(SUM(K59,T59,AC59)=0,0,T59/SUM(K59,T59,AC59)) | V59: =F1177 | W59: =J1177 | X59: =V59/V58-1 | Y59: =V59/V56-1 | Z59: =V59/V53-1 | AA59: =V59/V47-1 | AB59: =STDEV.S(X48:X59)*SQRT(12) | AC59: =IF(AND(Y59>$P$6,Z59>$P$7,AA59>$P$8,V59>W59,AB59<$P$10),1,0) | AD59: =IF(SUM(K59,T59,AC59)=0,0,AC59/SUM(K59,T59,AC59)) | AE59: =IF(SUM(K59,T59,AC59)=0,1,0) | AF59: =G1177 | AG59: =AF59/AF58-1 | AH59: =0.5*(ABS(L58-L57)+ABS(U58-U57)+ABS(AD58-AD57)+ABS(AE58-AE57)) | AI59: =L58*F59+U58*O59+AD58*X59+AE58*AG59 | AJ59: =AH59*$P$11 | AK59: =AI59-AJ59 | AL59: =AL58*(1+AK59) | AM59: =MAX($AL$40:AL59) | AN59: =AL59/AM59-1 | AO59: =AK59-AG59
C60: 41182 | D60: =D1196 | E60: =H1196 | F60: =D60/D59-1 | G60: =D60/D57-1 | H60: =D60/D54-1 | I60: =D60/D48-1 | J60: =STDEV.S(F49:F60)*SQRT(12) | K60: =IF(AND(G60>$P$6,H60>$P$7,I60>$P$8,D60>E60,J60<$P$10),1,0) | L60: =IF(SUM(K60,T60,AC60)=0,0,K60/SUM(K60,T60,AC60)) | M60: =E1196 | N60: =I1196 | O60: =M60/M59-1 | P60: =M60/M57-1 | Q60: =M60/M54-1 | R60: =M60/M48-1 | S60: =STDEV.S(O49:O60)*SQRT(12) | T60: =IF(AND(P60>$P$6,Q60>$P$7,R60>$P$8,M60>N60,S60<$P$10),1,0) | U60: =IF(SUM(K60,T60,AC60)=0,0,T60/SUM(K60,T60,AC60)) | V60: =F1196 | W60: =J1196 | X60: =V60/V59-1 | Y60: =V60/V57-1 | Z60: =V60/V54-1 | AA60: =V60/V48-1 | AB60: =STDEV.S(X49:X60)*SQRT(12) | AC60: =IF(AND(Y60>$P$6,Z60>$P$7,AA60>$P$8,V60>W60,AB60<$P$10),1,0) | AD60: =IF(SUM(K60,T60,AC60)=0,0,AC60/SUM(K60,T60,AC60)) | AE60: =IF(SUM(K60,T60,AC60)=0,1,0) | AF60: =G1196 | AG60: =AF60/AF59-1 | AH60: =0.5*(ABS(L59-L58)+ABS(U59-U58)+ABS(AD59-AD58)+ABS(AE59-AE58)) | AI60: =L59*F60+U59*O60+AD59*X60+AE59*AG60 | AJ60: =AH60*$P$11 | AK60: =AI60-AJ60 | AL60: =AL59*(1+AK60) | AM60: =MAX($AL$40:AL60) | AN60: =AL60/AM60-1 | AO60: =AK60-AG60
C61: 41213 | D61: =D1217 | E61: =H1217 | F61: =D61/D60-1 | G61: =D61/D58-1 | H61: =D61/D55-1 | I61: =D61/D49-1 | J61: =STDEV.S(F50:F61)*SQRT(12) | K61: =IF(AND(G61>$P$6,H61>$P$7,I61>$P$8,D61>E61,J61<$P$10),1,0) | L61: =IF(SUM(K61,T61,AC61)=0,0,K61/SUM(K61,T61,AC61)) | M61: =E1217 | N61: =I1217 | O61: =M61/M60-1 | P61: =M61/M58-1 | Q61: =M61/M55-1 | R61: =M61/M49-1 | S61: =STDEV.S(O50:O61)*SQRT(12) | T61: =IF(AND(P61>$P$6,Q61>$P$7,R61>$P$8,M61>N61,S61<$P$10),1,0) | U61: =IF(SUM(K61,T61,AC61)=0,0,T61/SUM(K61,T61,AC61)) | V61: =F1217 | W61: =J1217 | X61: =V61/V60-1 | Y61: =V61/V58-1 | Z61: =V61/V55-1 | AA61: =V61/V49-1 | AB61: =STDEV.S(X50:X61)*SQRT(12) | AC61: =IF(AND(Y61>$P$6,Z61>$P$7,AA61>$P$8,V61>W61,AB61<$P$10),1,0) | AD61: =IF(SUM(K61,T61,AC61)=0,0,AC61/SUM(K61,T61,AC61)) | AE61: =IF(SUM(K61,T61,AC61)=0,1,0) | AF61: =G1217 | AG61: =AF61/AF60-1 | AH61: =0.5*(ABS(L60-L59)+ABS(U60-U59)+ABS(AD60-AD59)+ABS(AE60-AE59)) | AI61: =L60*F61+U60*O61+AD60*X61+AE60*AG61 | AJ61: =AH61*$P$11 | AK61: =AI61-AJ61 | AL61: =AL60*(1+AK61) | AM61: =MAX($AL$40:AL61) | AN61: =AL61/AM61-1 | AO61: =AK61-AG61
C62: 41243 | D62: =D1238 | E62: =H1238 | F62: =D62/D61-1 | G62: =D62/D59-1 | H62: =D62/D56-1 | I62: =D62/D50-1 | J62: =STDEV.S(F51:F62)*SQRT(12) | K62: =IF(AND(G62>$P$6,H62>$P$7,I62>$P$8,D62>E62,J62<$P$10),1,0) | L62: =IF(SUM(K62,T62,AC62)=0,0,K62/SUM(K62,T62,AC62)) | M62: =E1238 | N62: =I1238 | O62: =M62/M61-1 | P62: =M62/M59-1 | Q62: =M62/M56-1 | R62: =M62/M50-1 | S62: =STDEV.S(O51:O62)*SQRT(12) | T62: =IF(AND(P62>$P$6,Q62>$P$7,R62>$P$8,M62>N62,S62<$P$10),1,0) | U62: =IF(SUM(K62,T62,AC62)=0,0,T62/SUM(K62,T62,AC62)) | V62: =F1238 | W62: =J1238 | X62: =V62/V61-1 | Y62: =V62/V59-1 | Z62: =V62/V56-1 | AA62: =V62/V50-1 | AB62: =STDEV.S(X51:X62)*SQRT(12) | AC62: =IF(AND(Y62>$P$6,Z62>$P$7,AA62>$P$8,V62>W62,AB62<$P$10),1,0) | AD62: =IF(SUM(K62,T62,AC62)=0,0,AC62/SUM(K62,T62,AC62)) | AE62: =IF(SUM(K62,T62,AC62)=0,1,0) | AF62: =G1238 | AG62: =AF62/AF61-1 | AH62: =0.5*(ABS(L61-L60)+ABS(U61-U60)+ABS(AD61-AD60)+ABS(AE61-AE60)) | AI62: =L61*F62+U61*O62+AD61*X62+AE61*AG62 | AJ62: =AH62*$P$11 | AK62: =AI62-AJ62 | AL62: =AL61*(1+AK62) | AM62: =MAX($AL$40:AL62) | AN62: =AL62/AM62-1 | AO62: =AK62-AG62
C63: 41274 | D63: =D1258 | E63: =H1258 | F63: =D63/D62-1 | G63: =D63/D60-1 | H63: =D63/D57-1 | I63: =D63/D51-1 | J63: =STDEV.S(F52:F63)*SQRT(12) | K63: =IF(AND(G63>$P$6,H63>$P$7,I63>$P$8,D63>E63,J63<$P$10),1,0) | L63: =IF(SUM(K63,T63,AC63)=0,0,K63/SUM(K63,T63,AC63)) | M63: =E1258 | N63: =I1258 | O63: =M63/M62-1 | P63: =M63/M60-1 | Q63: =M63/M57-1 | R63: =M63/M51-1 | S63: =STDEV.S(O52:O63)*SQRT(12) | T63: =IF(AND(P63>$P$6,Q63>$P$7,R63>$P$8,M63>N63,S63<$P$10),1,0) | U63: =IF(SUM(K63,T63,AC63)=0,0,T63/SUM(K63,T63,AC63)) | V63: =F1258 | W63: =J1258 | X63: =V63/V62-1 | Y63: =V63/V60-1 | Z63: =V63/V57-1 | AA63: =V63/V51-1 | AB63: =STDEV.S(X52:X63)*SQRT(12) | AC63: =IF(AND(Y63>$P$6,Z63>$P$7,AA63>$P$8,V63>W63,AB63<$P$10),1,0) | AD63: =IF(SUM(K63,T63,AC63)=0,0,AC63/SUM(K63,T63,AC63)) | AE63: =IF(SUM(K63,T63,AC63)=0,1,0) | AF63: =G1258 | AG63: =AF63/AF62-1 | AH63: =0.5*(ABS(L62-L61)+ABS(U62-U61)+ABS(AD62-AD61)+ABS(AE62-AE61)) | AI63: =L62*F63+U62*O63+AD62*X63+AE62*AG63 | AJ63: =AH63*$P$11 | AK63: =AI63-AJ63 | AL63: =AL62*(1+AK63) | AM63: =MAX($AL$40:AL63) | AN63: =AL63/AM63-1 | AO63: =AK63-AG63
C64: 41305 | D64: =D1279 | E64: =H1279 | F64: =D64/D63-1 | G64: =D64/D61-1 | H64: =D64/D58-1 | I64: =D64/D52-1 | J64: =STDEV.S(F53:F64)*SQRT(12) | K64: =IF(AND(G64>$P$6,H64>$P$7,I64>$P$8,D64>E64,J64<$P$10),1,0) | L64: =IF(SUM(K64,T64,AC64)=0,0,K64/SUM(K64,T64,AC64)) | M64: =E1279 | N64: =I1279 | O64: =M64/M63-1 | P64: =M64/M61-1 | Q64: =M64/M58-1 | R64: =M64/M52-1 | S64: =STDEV.S(O53:O64)*SQRT(12) | T64: =IF(AND(P64>$P$6,Q64>$P$7,R64>$P$8,M64>N64,S64<$P$10),1,0) | U64: =IF(SUM(K64,T64,AC64)=0,0,T64/SUM(K64,T64,AC64)) | V64: =F1279 | W64: =J1279 | X64: =V64/V63-1 | Y64: =V64/V61-1 | Z64: =V64/V58-1 | AA64: =V64/V52-1 | AB64: =STDEV.S(X53:X64)*SQRT(12) | AC64: =IF(AND(Y64>$P$6,Z64>$P$7,AA64>$P$8,V64>W64,AB64<$P$10),1,0) | AD64: =IF(SUM(K64,T64,AC64)=0,0,AC64/SUM(K64,T64,AC64)) | AE64: =IF(SUM(K64,T64,AC64)=0,1,0) | AF64: =G1279 | AG64: =AF64/AF63-1 | AH64: =0.5*(ABS(L63-L62)+ABS(U63-U62)+ABS(AD63-AD62)+ABS(AE63-AE62)) | AI64: =L63*F64+U63*O64+AD63*X64+AE63*AG64 | AJ64: =AH64*$P$11 | AK64: =AI64-AJ64 | AL64: =AL63*(1+AK64) | AM64: =MAX($AL$40:AL64) | AN64: =AL64/AM64-1 | AO64: =AK64-AG64
C65: 41333 | D65: =D1298 | E65: =H1298 | F65: =D65/D64-1 | G65: =D65/D62-1 | H65: =D65/D59-1 | I65: =D65/D53-1 | J65: =STDEV.S(F54:F65)*SQRT(12) | K65: =IF(AND(G65>$P$6,H65>$P$7,I65>$P$8,D65>E65,J65<$P$10),1,0) | L65: =IF(SUM(K65,T65,AC65)=0,0,K65/SUM(K65,T65,AC65)) | M65: =E1298 | N65: =I1298 | O65: =M65/M64-1 | P65: =M65/M62-1 | Q65: =M65/M59-1 | R65: =M65/M53-1 | S65: =STDEV.S(O54:O65)*SQRT(12) | T65: =IF(AND(P65>$P$6,Q65>$P$7,R65>$P$8,M65>N65,S65<$P$10),1,0) | U65: =IF(SUM(K65,T65,AC65)=0,0,T65/SUM(K65,T65,AC65)) | V65: =F1298 | W65: =J1298 | X65: =V65/V64-1 | Y65: =V65/V62-1 | Z65: =V65/V59-1 | AA65: =V65/V53-1 | AB65: =STDEV.S(X54:X65)*SQRT(12) | AC65: =IF(AND(Y65>$P$6,Z65>$P$7,AA65>$P$8,V65>W65,AB65<$P$10),1,0) | AD65: =IF(SUM(K65,T65,AC65)=0,0,AC65/SUM(K65,T65,AC65)) | AE65: =IF(SUM(K65,T65,AC65)=0,1,0) | AF65: =G1298 | AG65: =AF65/AF64-1 | AH65: =0.5*(ABS(L64-L63)+ABS(U64-U63)+ABS(AD64-AD63)+ABS(AE64-AE63)) | AI65: =L64*F65+U64*O65+AD64*X65+AE64*AG65 | AJ65: =AH65*$P$11 | AK65: =AI65-AJ65 | AL65: =AL64*(1+AK65) | AM65: =MAX($AL$40:AL65) | AN65: =AL65/AM65-1 | AO65: =AK65-AG65
C66: 41364 | D66: =D1318 | E66: =H1318 | F66: =D66/D65-1 | G66: =D66/D63-1 | H66: =D66/D60-1 | I66: =D66/D54-1 | J66: =STDEV.S(F55:F66)*SQRT(12) | K66: =IF(AND(G66>$P$6,H66>$P$7,I66>$P$8,D66>E66,J66<$P$10),1,0) | L66: =IF(SUM(K66,T66,AC66)=0,0,K66/SUM(K66,T66,AC66)) | M66: =E1318 | N66: =I1318 | O66: =M66/M65-1 | P66: =M66/M63-1 | Q66: =M66/M60-1 | R66: =M66/M54-1 | S66: =STDEV.S(O55:O66)*SQRT(12) | T66: =IF(AND(P66>$P$6,Q66>$P$7,R66>$P$8,M66>N66,S66<$P$10),1,0) | U66: =IF(SUM(K66,T66,AC66)=0,0,T66/SUM(K66,T66,AC66)) | V66: =F1318 | W66: =J1318 | X66: =V66/V65-1 | Y66: =V66/V63-1 | Z66: =V66/V60-1 | AA66: =V66/V54-1 | AB66: =STDEV.S(X55:X66)*SQRT(12) | AC66: =IF(AND(Y66>$P$6,Z66>$P$7,AA66>$P$8,V66>W66,AB66<$P$10),1,0) | AD66: =IF(SUM(K66,T66,AC66)=0,0,AC66/SUM(K66,T66,AC66)) | AE66: =IF(SUM(K66,T66,AC66)=0,1,0) | AF66: =G1318 | AG66: =AF66/AF65-1 | AH66: =0.5*(ABS(L65-L64)+ABS(U65-U64)+ABS(AD65-AD64)+ABS(AE65-AE64)) | AI66: =L65*F66+U65*O66+AD65*X66+AE65*AG66 | AJ66: =AH66*$P$11 | AK66: =AI66-AJ66 | AL66: =AL65*(1+AK66) | AM66: =MAX($AL$40:AL66) | AN66: =AL66/AM66-1 | AO66: =AK66-AG66
C67: 41394 | D67: =D1340 | E67: =H1340 | F67: =D67/D66-1 | G67: =D67/D64-1 | H67: =D67/D61-1 | I67: =D67/D55-1 | J67: =STDEV.S(F56:F67)*SQRT(12) | K67: =IF(AND(G67>$P$6,H67>$P$7,I67>$P$8,D67>E67,J67<$P$10),1,0) | L67: =IF(SUM(K67,T67,AC67)=0,0,K67/SUM(K67,T67,AC67)) | M67: =E1340 | N67: =I1340 | O67: =M67/M66-1 | P67: =M67/M64-1 | Q67: =M67/M61-1 | R67: =M67/M55-1 | S67: =STDEV.S(O56:O67)*SQRT(12) | T67: =IF(AND(P67>$P$6,Q67>$P$7,R67>$P$8,M67>N67,S67<$P$10),1,0) | U67: =IF(SUM(K67,T67,AC67)=0,0,T67/SUM(K67,T67,AC67)) | V67: =F1340 | W67: =J1340 | X67: =V67/V66-1 | Y67: =V67/V64-1 | Z67: =V67/V61-1 | AA67: =V67/V55-1 | AB67: =STDEV.S(X56:X67)*SQRT(12) | AC67: =IF(AND(Y67>$P$6,Z67>$P$7,AA67>$P$8,V67>W67,AB67<$P$10),1,0) | AD67: =IF(SUM(K67,T67,AC67)=0,0,AC67/SUM(K67,T67,AC67)) | AE67: =IF(SUM(K67,T67,AC67)=0,1,0) | AF67: =G1340 | AG67: =AF67/AF66-1 | AH67: =0.5*(ABS(L66-L65)+ABS(U66-U65)+ABS(AD66-AD65)+ABS(AE66-AE65)) | AI67: =L66*F67+U66*O67+AD66*X67+AE66*AG67 | AJ67: =AH67*$P$11 | AK67: =AI67-AJ67 | AL67: =AL66*(1+AK67) | AM67: =MAX($AL$40:AL67) | AN67: =AL67/AM67-1 | AO67: =AK67-AG67
C68: 41425 | D68: =D1362 | E68: =H1362 | F68: =D68/D67-1 | G68: =D68/D65-1 | H68: =D68/D62-1 | I68: =D68/D56-1 | J68: =STDEV.S(F57:F68)*SQRT(12) | K68: =IF(AND(G68>$P$6,H68>$P$7,I68>$P$8,D68>E68,J68<$P$10),1,0) | L68: =IF(SUM(K68,T68,AC68)=0,0,K68/SUM(K68,T68,AC68)) | M68: =E1362 | N68: =I1362 | O68: =M68/M67-1 | P68: =M68/M65-1 | Q68: =M68/M62-1 | R68: =M68/M56-1 | S68: =STDEV.S(O57:O68)*SQRT(12) | T68: =IF(AND(P68>$P$6,Q68>$P$7,R68>$P$8,M68>N68,S68<$P$10),1,0) | U68: =IF(SUM(K68,T68,AC68)=0,0,T68/SUM(K68,T68,AC68)) | V68: =F1362 | W68: =J1362 | X68: =V68/V67-1 | Y68: =V68/V65-1 | Z68: =V68/V62-1 | AA68: =V68/V56-1 | AB68: =STDEV.S(X57:X68)*SQRT(12) | AC68: =IF(AND(Y68>$P$6,Z68>$P$7,AA68>$P$8,V68>W68,AB68<$P$10),1,0) | AD68: =IF(SUM(K68,T68,AC68)=0,0,AC68/SUM(K68,T68,AC68)) | AE68: =IF(SUM(K68,T68,AC68)=0,1,0) | AF68: =G1362 | AG68: =AF68/AF67-1 | AH68: =0.5*(ABS(L67-L66)+ABS(U67-U66)+ABS(AD67-AD66)+ABS(AE67-AE66)) | AI68: =L67*F68+U67*O68+AD67*X68+AE67*AG68 | AJ68: =AH68*$P$11 | AK68: =AI68-AJ68 | AL68: =AL67*(1+AK68) | AM68: =MAX($AL$40:AL68) | AN68: =AL68/AM68-1 | AO68: =AK68-AG68
C69: 41455 | D69: =D1382 | E69: =H1382 | F69: =D69/D68-1 | G69: =D69/D66-1 | H69: =D69/D63-1 | I69: =D69/D57-1 | J69: =STDEV.S(F58:F69)*SQRT(12) | K69: =IF(AND(G69>$P$6,H69>$P$7,I69>$P$8,D69>E69,J69<$P$10),1,0) | L69: =IF(SUM(K69,T69,AC69)=0,0,K69/SUM(K69,T69,AC69)) | M69: =E1382 | N69: =I1382 | O69: =M69/M68-1 | P69: =M69/M66-1 | Q69: =M69/M63-1 | R69: =M69/M57-1 | S69: =STDEV.S(O58:O69)*SQRT(12) | T69: =IF(AND(P69>$P$6,Q69>$P$7,R69>$P$8,M69>N69,S69<$P$10),1,0) | U69: =IF(SUM(K69,T69,AC69)=0,0,T69/SUM(K69,T69,AC69)) | V69: =F1382 | W69: =J1382 | X69: =V69/V68-1 | Y69: =V69/V66-1 | Z69: =V69/V63-1 | AA69: =V69/V57-1 | AB69: =STDEV.S(X58:X69)*SQRT(12) | AC69: =IF(AND(Y69>$P$6,Z69>$P$7,AA69>$P$8,V69>W69,AB69<$P$10),1,0) | AD69: =IF(SUM(K69,T69,AC69)=0,0,AC69/SUM(K69,T69,AC69)) | AE69: =IF(SUM(K69,T69,AC69)=0,1,0) | AF69: =G1382 | AG69: =AF69/AF68-1 | AH69: =0.5*(ABS(L68-L67)+ABS(U68-U67)+ABS(AD68-AD67)+ABS(AE68-AE67)) | AI69: =L68*F69+U68*O69+AD68*X69+AE68*AG69 | AJ69: =AH69*$P$11 | AK69: =AI69-AJ69 | AL69: =AL68*(1+AK69) | AM69: =MAX($AL$40:AL69) | AN69: =AL69/AM69-1 | AO69: =AK69-AG69
C70: 41486 | D70: =D1404 | E70: =H1404 | F70: =D70/D69-1 | G70: =D70/D67-1 | H70: =D70/D64-1 | I70: =D70/D58-1 | J70: =STDEV.S(F59:F70)*SQRT(12) | K70: =IF(AND(G70>$P$6,H70>$P$7,I70>$P$8,D70>E70,J70<$P$10),1,0) | L70: =IF(SUM(K70,T70,AC70)=0,0,K70/SUM(K70,T70,AC70)) | M70: =E1404 | N70: =I1404 | O70: =M70/M69-1 | P70: =M70/M67-1 | Q70: =M70/M64-1 | R70: =M70/M58-1 | S70: =STDEV.S(O59:O70)*SQRT(12) | T70: =IF(AND(P70>$P$6,Q70>$P$7,R70>$P$8,M70>N70,S70<$P$10),1,0) | U70: =IF(SUM(K70,T70,AC70)=0,0,T70/SUM(K70,T70,AC70)) | V70: =F1404 | W70: =J1404 | X70: =V70/V69-1 | Y70: =V70/V67-1 | Z70: =V70/V64-1 | AA70: =V70/V58-1 | AB70: =STDEV.S(X59:X70)*SQRT(12) | AC70: =IF(AND(Y70>$P$6,Z70>$P$7,AA70>$P$8,V70>W70,AB70<$P$10),1,0) | AD70: =IF(SUM(K70,T70,AC70)=0,0,AC70/SUM(K70,T70,AC70)) | AE70: =IF(SUM(K70,T70,AC70)=0,1,0) | AF70: =G1404 | AG70: =AF70/AF69-1 | AH70: =0.5*(ABS(L69-L68)+ABS(U69-U68)+ABS(AD69-AD68)+ABS(AE69-AE68)) | AI70: =L69*F70+U69*O70+AD69*X70+AE69*AG70 | AJ70: =AH70*$P$11 | AK70: =AI70-AJ70 | AL70: =AL69*(1+AK70) | AM70: =MAX($AL$40:AL70) | AN70: =AL70/AM70-1 | AO70: =AK70-AG70
C71: 41517 | D71: =D1426 | E71: =H1426 | F71: =D71/D70-1 | G71: =D71/D68-1 | H71: =D71/D65-1 | I71: =D71/D59-1 | J71: =STDEV.S(F60:F71)*SQRT(12) | K71: =IF(AND(G71>$P$6,H71>$P$7,I71>$P$8,D71>E71,J71<$P$10),1,0) | L71: =IF(SUM(K71,T71,AC71)=0,0,K71/SUM(K71,T71,AC71)) | M71: =E1426 | N71: =I1426 | O71: =M71/M70-1 | P71: =M71/M68-1 | Q71: =M71/M65-1 | R71: =M71/M59-1 | S71: =STDEV.S(O60:O71)*SQRT(12) | T71: =IF(AND(P71>$P$6,Q71>$P$7,R71>$P$8,M71>N71,S71<$P$10),1,0) | U71: =IF(SUM(K71,T71,AC71)=0,0,T71/SUM(K71,T71,AC71)) | V71: =F1426 | W71: =J1426 | X71: =V71/V70-1 | Y71: =V71/V68-1 | Z71: =V71/V65-1 | AA71: =V71/V59-1 | AB71: =STDEV.S(X60:X71)*SQRT(12) | AC71: =IF(AND(Y71>$P$6,Z71>$P$7,AA71>$P$8,V71>W71,AB71<$P$10),1,0) | AD71: =IF(SUM(K71,T71,AC71)=0,0,AC71/SUM(K71,T71,AC71)) | AE71: =IF(SUM(K71,T71,AC71)=0,1,0) | AF71: =G1426 | AG71: =AF71/AF70-1 | AH71: =0.5*(ABS(L70-L69)+ABS(U70-U69)+ABS(AD70-AD69)+ABS(AE70-AE69)) | AI71: =L70*F71+U70*O71+AD70*X71+AE70*AG71 | AJ71: =AH71*$P$11 | AK71: =AI71-AJ71 | AL71: =AL70*(1+AK71) | AM71: =MAX($AL$40:AL71) | AN71: =AL71/AM71-1 | AO71: =AK71-AG71
C72: 41547 | D72: =D1446 | E72: =H1446 | F72: =D72/D71-1 | G72: =D72/D69-1 | H72: =D72/D66-1 | I72: =D72/D60-1 | J72: =STDEV.S(F61:F72)*SQRT(12) | K72: =IF(AND(G72>$P$6,H72>$P$7,I72>$P$8,D72>E72,J72<$P$10),1,0) | L72: =IF(SUM(K72,T72,AC72)=0,0,K72/SUM(K72,T72,AC72)) | M72: =E1446 | N72: =I1446 | O72: =M72/M71-1 | P72: =M72/M69-1 | Q72: =M72/M66-1 | R72: =M72/M60-1 | S72: =STDEV.S(O61:O72)*SQRT(12) | T72: =IF(AND(P72>$P$6,Q72>$P$7,R72>$P$8,M72>N72,S72<$P$10),1,0) | U72: =IF(SUM(K72,T72,AC72)=0,0,T72/SUM(K72,T72,AC72)) | V72: =F1446 | W72: =J1446 | X72: =V72/V71-1 | Y72: =V72/V69-1 | Z72: =V72/V66-1 | AA72: =V72/V60-1 | AB72: =STDEV.S(X61:X72)*SQRT(12) | AC72: =IF(AND(Y72>$P$6,Z72>$P$7,AA72>$P$8,V72>W72,AB72<$P$10),1,0) | AD72: =IF(SUM(K72,T72,AC72)=0,0,AC72/SUM(K72,T72,AC72)) | AE72: =IF(SUM(K72,T72,AC72)=0,1,0) | AF72: =G1446 | AG72: =AF72/AF71-1 | AH72: =0.5*(ABS(L71-L70)+ABS(U71-U70)+ABS(AD71-AD70)+ABS(AE71-AE70)) | AI72: =L71*F72+U71*O72+AD71*X72+AE71*AG72 | AJ72: =AH72*$P$11 | AK72: =AI72-AJ72 | AL72: =AL71*(1+AK72) | AM72: =MAX($AL$40:AL72) | AN72: =AL72/AM72-1 | AO72: =AK72-AG72
C73: 41578 | D73: =D1469 | E73: =H1469 | F73: =D73/D72-1 | G73: =D73/D70-1 | H73: =D73/D67-1 | I73: =D73/D61-1 | J73: =STDEV.S(F62:F73)*SQRT(12) | K73: =IF(AND(G73>$P$6,H73>$P$7,I73>$P$8,D73>E73,J73<$P$10),1,0) | L73: =IF(SUM(K73,T73,AC73)=0,0,K73/SUM(K73,T73,AC73)) | M73: =E1469 | N73: =I1469 | O73: =M73/M72-1 | P73: =M73/M70-1 | Q73: =M73/M67-1 | R73: =M73/M61-1 | S73: =STDEV.S(O62:O73)*SQRT(12) | T73: =IF(AND(P73>$P$6,Q73>$P$7,R73>$P$8,M73>N73,S73<$P$10),1,0) | U73: =IF(SUM(K73,T73,AC73)=0,0,T73/SUM(K73,T73,AC73)) | V73: =F1469 | W73: =J1469 | X73: =V73/V72-1 | Y73: =V73/V70-1 | Z73: =V73/V67-1 | AA73: =V73/V61-1 | AB73: =STDEV.S(X62:X73)*SQRT(12) | AC73: =IF(AND(Y73>$P$6,Z73>$P$7,AA73>$P$8,V73>W73,AB73<$P$10),1,0) | AD73: =IF(SUM(K73,T73,AC73)=0,0,AC73/SUM(K73,T73,AC73)) | AE73: =IF(SUM(K73,T73,AC73)=0,1,0) | AF73: =G1469 | AG73: =AF73/AF72-1 | AH73: =0.5*(ABS(L72-L71)+ABS(U72-U71)+ABS(AD72-AD71)+ABS(AE72-AE71)) | AI73: =L72*F73+U72*O73+AD72*X73+AE72*AG73 | AJ73: =AH73*$P$11 | AK73: =AI73-AJ73 | AL73: =AL72*(1+AK73) | AM73: =MAX($AL$40:AL73) | AN73: =AL73/AM73-1 | AO73: =AK73-AG73
C74: 41608 | D74: =D1489 | E74: =H1489 | F74: =D74/D73-1 | G74: =D74/D71-1 | H74: =D74/D68-1 | I74: =D74/D62-1 | J74: =STDEV.S(F63:F74)*SQRT(12) | K74: =IF(AND(G74>$P$6,H74>$P$7,I74>$P$8,D74>E74,J74<$P$10),1,0) | L74: =IF(SUM(K74,T74,AC74)=0,0,K74/SUM(K74,T74,AC74)) | M74: =E1489 | N74: =I1489 | O74: =M74/M73-1 | P74: =M74/M71-1 | Q74: =M74/M68-1 | R74: =M74/M62-1 | S74: =STDEV.S(O63:O74)*SQRT(12) | T74: =IF(AND(P74>$P$6,Q74>$P$7,R74>$P$8,M74>N74,S74<$P$10),1,0) | U74: =IF(SUM(K74,T74,AC74)=0,0,T74/SUM(K74,T74,AC74)) | V74: =F1489 | W74: =J1489 | X74: =V74/V73-1 | Y74: =V74/V71-1 | Z74: =V74/V68-1 | AA74: =V74/V62-1 | AB74: =STDEV.S(X63:X74)*SQRT(12) | AC74: =IF(AND(Y74>$P$6,Z74>$P$7,AA74>$P$8,V74>W74,AB74<$P$10),1,0) | AD74: =IF(SUM(K74,T74,AC74)=0,0,AC74/SUM(K74,T74,AC74)) | AE74: =IF(SUM(K74,T74,AC74)=0,1,0) | AF74: =G1489 | AG74: =AF74/AF73-1 | AH74: =0.5*(ABS(L73-L72)+ABS(U73-U72)+ABS(AD73-AD72)+ABS(AE73-AE72)) | AI74: =L73*F74+U73*O74+AD73*X74+AE73*AG74 | AJ74: =AH74*$P$11 | AK74: =AI74-AJ74 | AL74: =AL73*(1+AK74) | AM74: =MAX($AL$40:AL74) | AN74: =AL74/AM74-1 | AO74: =AK74-AG74
C75: 41639 | D75: =D1510 | E75: =H1510 | F75: =D75/D74-1 | G75: =D75/D72-1 | H75: =D75/D69-1 | I75: =D75/D63-1 | J75: =STDEV.S(F64:F75)*SQRT(12) | K75: =IF(AND(G75>$P$6,H75>$P$7,I75>$P$8,D75>E75,J75<$P$10),1,0) | L75: =IF(SUM(K75,T75,AC75)=0,0,K75/SUM(K75,T75,AC75)) | M75: =E1510 | N75: =I1510 | O75: =M75/M74-1 | P75: =M75/M72-1 | Q75: =M75/M69-1 | R75: =M75/M63-1 | S75: =STDEV.S(O64:O75)*SQRT(12) | T75: =IF(AND(P75>$P$6,Q75>$P$7,R75>$P$8,M75>N75,S75<$P$10),1,0) | U75: =IF(SUM(K75,T75,AC75)=0,0,T75/SUM(K75,T75,AC75)) | V75: =F1510 | W75: =J1510 | X75: =V75/V74-1 | Y75: =V75/V72-1 | Z75: =V75/V69-1 | AA75: =V75/V63-1 | AB75: =STDEV.S(X64:X75)*SQRT(12) | AC75: =IF(AND(Y75>$P$6,Z75>$P$7,AA75>$P$8,V75>W75,AB75<$P$10),1,0) | AD75: =IF(SUM(K75,T75,AC75)=0,0,AC75/SUM(K75,T75,AC75)) | AE75: =IF(SUM(K75,T75,AC75)=0,1,0) | AF75: =G1510 | AG75: =AF75/AF74-1 | AH75: =0.5*(ABS(L74-L73)+ABS(U74-U73)+ABS(AD74-AD73)+ABS(AE74-AE73)) | AI75: =L74*F75+U74*O75+AD74*X75+AE74*AG75 | AJ75: =AH75*$P$11 | AK75: =AI75-AJ75 | AL75: =AL74*(1+AK75) | AM75: =MAX($AL$40:AL75) | AN75: =AL75/AM75-1 | AO75: =AK75-AG75
C76: 41670 | D76: =D1531 | E76: =H1531 | F76: =D76/D75-1 | G76: =D76/D73-1 | H76: =D76/D70-1 | I76: =D76/D64-1 | J76: =STDEV.S(F65:F76)*SQRT(12) | K76: =IF(AND(G76>$P$6,H76>$P$7,I76>$P$8,D76>E76,J76<$P$10),1,0) | L76: =IF(SUM(K76,T76,AC76)=0,0,K76/SUM(K76,T76,AC76)) | M76: =E1531 | N76: =I1531 | O76: =M76/M75-1 | P76: =M76/M73-1 | Q76: =M76/M70-1 | R76: =M76/M64-1 | S76: =STDEV.S(O65:O76)*SQRT(12) | T76: =IF(AND(P76>$P$6,Q76>$P$7,R76>$P$8,M76>N76,S76<$P$10),1,0) | U76: =IF(SUM(K76,T76,AC76)=0,0,T76/SUM(K76,T76,AC76)) | V76: =F1531 | W76: =J1531 | X76: =V76/V75-1 | Y76: =V76/V73-1 | Z76: =V76/V70-1 | AA76: =V76/V64-1 | AB76: =STDEV.S(X65:X76)*SQRT(12) | AC76: =IF(AND(Y76>$P$6,Z76>$P$7,AA76>$P$8,V76>W76,AB76<$P$10),1,0) | AD76: =IF(SUM(K76,T76,AC76)=0,0,AC76/SUM(K76,T76,AC76)) | AE76: =IF(SUM(K76,T76,AC76)=0,1,0) | AF76: =G1531 | AG76: =AF76/AF75-1 | AH76: =0.5*(ABS(L75-L74)+ABS(U75-U74)+ABS(AD75-AD74)+ABS(AE75-AE74)) | AI76: =L75*F76+U75*O76+AD75*X76+AE75*AG76 | AJ76: =AH76*$P$11 | AK76: =AI76-AJ76 | AL76: =AL75*(1+AK76) | AM76: =MAX($AL$40:AL76) | AN76: =AL76/AM76-1 | AO76: =AK76-AG76
C77: 41698 | D77: =D1550 | E77: =H1550 | F77: =D77/D76-1 | G77: =D77/D74-1 | H77: =D77/D71-1 | I77: =D77/D65-1 | J77: =STDEV.S(F66:F77)*SQRT(12) | K77: =IF(AND(G77>$P$6,H77>$P$7,I77>$P$8,D77>E77,J77<$P$10),1,0) | L77: =IF(SUM(K77,T77,AC77)=0,0,K77/SUM(K77,T77,AC77)) | M77: =E1550 | N77: =I1550 | O77: =M77/M76-1 | P77: =M77/M74-1 | Q77: =M77/M71-1 | R77: =M77/M65-1 | S77: =STDEV.S(O66:O77)*SQRT(12) | T77: =IF(AND(P77>$P$6,Q77>$P$7,R77>$P$8,M77>N77,S77<$P$10),1,0) | U77: =IF(SUM(K77,T77,AC77)=0,0,T77/SUM(K77,T77,AC77)) | V77: =F1550 | W77: =J1550 | X77: =V77/V76-1 | Y77: =V77/V74-1 | Z77: =V77/V71-1 | AA77: =V77/V65-1 | AB77: =STDEV.S(X66:X77)*SQRT(12) | AC77: =IF(AND(Y77>$P$6,Z77>$P$7,AA77>$P$8,V77>W77,AB77<$P$10),1,0) | AD77: =IF(SUM(K77,T77,AC77)=0,0,AC77/SUM(K77,T77,AC77)) | AE77: =IF(SUM(K77,T77,AC77)=0,1,0) | AF77: =G1550 | AG77: =AF77/AF76-1 | AH77: =0.5*(ABS(L76-L75)+ABS(U76-U75)+ABS(AD76-AD75)+ABS(AE76-AE75)) | AI77: =L76*F77+U76*O77+AD76*X77+AE76*AG77 | AJ77: =AH77*$P$11 | AK77: =AI77-AJ77 | AL77: =AL76*(1+AK77) | AM77: =MAX($AL$40:AL77) | AN77: =AL77/AM77-1 | AO77: =AK77-AG77
C78: 41729 | D78: =D1571 | E78: =H1571 | F78: =D78/D77-1 | G78: =D78/D75-1 | H78: =D78/D72-1 | I78: =D78/D66-1 | J78: =STDEV.S(F67:F78)*SQRT(12) | K78: =IF(AND(G78>$P$6,H78>$P$7,I78>$P$8,D78>E78,J78<$P$10),1,0) | L78: =IF(SUM(K78,T78,AC78)=0,0,K78/SUM(K78,T78,AC78)) | M78: =E1571 | N78: =I1571 | O78: =M78/M77-1 | P78: =M78/M75-1 | Q78: =M78/M72-1 | R78: =M78/M66-1 | S78: =STDEV.S(O67:O78)*SQRT(12) | T78: =IF(AND(P78>$P$6,Q78>$P$7,R78>$P$8,M78>N78,S78<$P$10),1,0) | U78: =IF(SUM(K78,T78,AC78)=0,0,T78/SUM(K78,T78,AC78)) | V78: =F1571 | W78: =J1571 | X78: =V78/V77-1 | Y78: =V78/V75-1 | Z78: =V78/V72-1 | AA78: =V78/V66-1 | AB78: =STDEV.S(X67:X78)*SQRT(12) | AC78: =IF(AND(Y78>$P$6,Z78>$P$7,AA78>$P$8,V78>W78,AB78<$P$10),1,0) | AD78: =IF(SUM(K78,T78,AC78)=0,0,AC78/SUM(K78,T78,AC78)) | AE78: =IF(SUM(K78,T78,AC78)=0,1,0) | AF78: =G1571 | AG78: =AF78/AF77-1 | AH78: =0.5*(ABS(L77-L76)+ABS(U77-U76)+ABS(AD77-AD76)+ABS(AE77-AE76)) | AI78: =L77*F78+U77*O78+AD77*X78+AE77*AG78 | AJ78: =AH78*$P$11 | AK78: =AI78-AJ78 | AL78: =AL77*(1+AK78) | AM78: =MAX($AL$40:AL78) | AN78: =AL78/AM78-1 | AO78: =AK78-AG78
C79: 41759 | D79: =D1592 | E79: =H1592 | F79: =D79/D78-1 | G79: =D79/D76-1 | H79: =D79/D73-1 | I79: =D79/D67-1 | J79: =STDEV.S(F68:F79)*SQRT(12) | K79: =IF(AND(G79>$P$6,H79>$P$7,I79>$P$8,D79>E79,J79<$P$10),1,0) | L79: =IF(SUM(K79,T79,AC79)=0,0,K79/SUM(K79,T79,AC79)) | M79: =E1592 | N79: =I1592 | O79: =M79/M78-1 | P79: =M79/M76-1 | Q79: =M79/M73-1 | R79: =M79/M67-1 | S79: =STDEV.S(O68:O79)*SQRT(12) | T79: =IF(AND(P79>$P$6,Q79>$P$7,R79>$P$8,M79>N79,S79<$P$10),1,0) | U79: =IF(SUM(K79,T79,AC79)=0,0,T79/SUM(K79,T79,AC79)) | V79: =F1592 | W79: =J1592 | X79: =V79/V78-1 | Y79: =V79/V76-1 | Z79: =V79/V73-1 | AA79: =V79/V67-1 | AB79: =STDEV.S(X68:X79)*SQRT(12) | AC79: =IF(AND(Y79>$P$6,Z79>$P$7,AA79>$P$8,V79>W79,AB79<$P$10),1,0) | AD79: =IF(SUM(K79,T79,AC79)=0,0,AC79/SUM(K79,T79,AC79)) | AE79: =IF(SUM(K79,T79,AC79)=0,1,0) | AF79: =G1592 | AG79: =AF79/AF78-1 | AH79: =0.5*(ABS(L78-L77)+ABS(U78-U77)+ABS(AD78-AD77)+ABS(AE78-AE77)) | AI79: =L78*F79+U78*O79+AD78*X79+AE78*AG79 | AJ79: =AH79*$P$11 | AK79: =AI79-AJ79 | AL79: =AL78*(1+AK79) | AM79: =MAX($AL$40:AL79) | AN79: =AL79/AM79-1 | AO79: =AK79-AG79
C80: 41790 | D80: =D1613 | E80: =H1613 | F80: =D80/D79-1 | G80: =D80/D77-1 | H80: =D80/D74-1 | I80: =D80/D68-1 | J80: =STDEV.S(F69:F80)*SQRT(12) | K80: =IF(AND(G80>$P$6,H80>$P$7,I80>$P$8,D80>E80,J80<$P$10),1,0) | L80: =IF(SUM(K80,T80,AC80)=0,0,K80/SUM(K80,T80,AC80)) | M80: =E1613 | N80: =I1613 | O80: =M80/M79-1 | P80: =M80/M77-1 | Q80: =M80/M74-1 | R80: =M80/M68-1 | S80: =STDEV.S(O69:O80)*SQRT(12) | T80: =IF(AND(P80>$P$6,Q80>$P$7,R80>$P$8,M80>N80,S80<$P$10),1,0) | U80: =IF(SUM(K80,T80,AC80)=0,0,T80/SUM(K80,T80,AC80)) | V80: =F1613 | W80: =J1613 | X80: =V80/V79-1 | Y80: =V80/V77-1 | Z80: =V80/V74-1 | AA80: =V80/V68-1 | AB80: =STDEV.S(X69:X80)*SQRT(12) | AC80: =IF(AND(Y80>$P$6,Z80>$P$7,AA80>$P$8,V80>W80,AB80<$P$10),1,0) | AD80: =IF(SUM(K80,T80,AC80)=0,0,AC80/SUM(K80,T80,AC80)) | AE80: =IF(SUM(K80,T80,AC80)=0,1,0) | AF80: =G1613 | AG80: =AF80/AF79-1 | AH80: =0.5*(ABS(L79-L78)+ABS(U79-U78)+ABS(AD79-AD78)+ABS(AE79-AE78)) | AI80: =L79*F80+U79*O80+AD79*X80+AE79*AG80 | AJ80: =AH80*$P$11 | AK80: =AI80-AJ80 | AL80: =AL79*(1+AK80) | AM80: =MAX($AL$40:AL80) | AN80: =AL80/AM80-1 | AO80: =AK80-AG80
C81: 41820 | D81: =D1634 | E81: =H1634 | F81: =D81/D80-1 | G81: =D81/D78-1 | H81: =D81/D75-1 | I81: =D81/D69-1 | J81: =STDEV.S(F70:F81)*SQRT(12) | K81: =IF(AND(G81>$P$6,H81>$P$7,I81>$P$8,D81>E81,J81<$P$10),1,0) | L81: =IF(SUM(K81,T81,AC81)=0,0,K81/SUM(K81,T81,AC81)) | M81: =E1634 | N81: =I1634 | O81: =M81/M80-1 | P81: =M81/M78-1 | Q81: =M81/M75-1 | R81: =M81/M69-1 | S81: =STDEV.S(O70:O81)*SQRT(12) | T81: =IF(AND(P81>$P$6,Q81>$P$7,R81>$P$8,M81>N81,S81<$P$10),1,0) | U81: =IF(SUM(K81,T81,AC81)=0,0,T81/SUM(K81,T81,AC81)) | V81: =F1634 | W81: =J1634 | X81: =V81/V80-1 | Y81: =V81/V78-1 | Z81: =V81/V75-1 | AA81: =V81/V69-1 | AB81: =STDEV.S(X70:X81)*SQRT(12) | AC81: =IF(AND(Y81>$P$6,Z81>$P$7,AA81>$P$8,V81>W81,AB81<$P$10),1,0) | AD81: =IF(SUM(K81,T81,AC81)=0,0,AC81/SUM(K81,T81,AC81)) | AE81: =IF(SUM(K81,T81,AC81)=0,1,0) | AF81: =G1634 | AG81: =AF81/AF80-1 | AH81: =0.5*(ABS(L80-L79)+ABS(U80-U79)+ABS(AD80-AD79)+ABS(AE80-AE79)) | AI81: =L80*F81+U80*O81+AD80*X81+AE80*AG81 | AJ81: =AH81*$P$11 | AK81: =AI81-AJ81 | AL81: =AL80*(1+AK81) | AM81: =MAX($AL$40:AL81) | AN81: =AL81/AM81-1 | AO81: =AK81-AG81
C82: 41851 | D82: =D1656 | E82: =H1656 | F82: =D82/D81-1 | G82: =D82/D79-1 | H82: =D82/D76-1 | I82: =D82/D70-1 | J82: =STDEV.S(F71:F82)*SQRT(12) | K82: =IF(AND(G82>$P$6,H82>$P$7,I82>$P$8,D82>E82,J82<$P$10),1,0) | L82: =IF(SUM(K82,T82,AC82)=0,0,K82/SUM(K82,T82,AC82)) | M82: =E1656 | N82: =I1656 | O82: =M82/M81-1 | P82: =M82/M79-1 | Q82: =M82/M76-1 | R82: =M82/M70-1 | S82: =STDEV.S(O71:O82)*SQRT(12) | T82: =IF(AND(P82>$P$6,Q82>$P$7,R82>$P$8,M82>N82,S82<$P$10),1,0) | U82: =IF(SUM(K82,T82,AC82)=0,0,T82/SUM(K82,T82,AC82)) | V82: =F1656 | W82: =J1656 | X82: =V82/V81-1 | Y82: =V82/V79-1 | Z82: =V82/V76-1 | AA82: =V82/V70-1 | AB82: =STDEV.S(X71:X82)*SQRT(12) | AC82: =IF(AND(Y82>$P$6,Z82>$P$7,AA82>$P$8,V82>W82,AB82<$P$10),1,0) | AD82: =IF(SUM(K82,T82,AC82)=0,0,AC82/SUM(K82,T82,AC82)) | AE82: =IF(SUM(K82,T82,AC82)=0,1,0) | AF82: =G1656 | AG82: =AF82/AF81-1 | AH82: =0.5*(ABS(L81-L80)+ABS(U81-U80)+ABS(AD81-AD80)+ABS(AE81-AE80)) | AI82: =L81*F82+U81*O82+AD81*X82+AE81*AG82 | AJ82: =AH82*$P$11 | AK82: =AI82-AJ82 | AL82: =AL81*(1+AK82) | AM82: =MAX($AL$40:AL82) | AN82: =AL82/AM82-1 | AO82: =AK82-AG82
C83: 41882 | D83: =D1677 | E83: =H1677 | F83: =D83/D82-1 | G83: =D83/D80-1 | H83: =D83/D77-1 | I83: =D83/D71-1 | J83: =STDEV.S(F72:F83)*SQRT(12) | K83: =IF(AND(G83>$P$6,H83>$P$7,I83>$P$8,D83>E83,J83<$P$10),1,0) | L83: =IF(SUM(K83,T83,AC83)=0,0,K83/SUM(K83,T83,AC83)) | M83: =E1677 | N83: =I1677 | O83: =M83/M82-1 | P83: =M83/M80-1 | Q83: =M83/M77-1 | R83: =M83/M71-1 | S83: =STDEV.S(O72:O83)*SQRT(12) | T83: =IF(AND(P83>$P$6,Q83>$P$7,R83>$P$8,M83>N83,S83<$P$10),1,0) | U83: =IF(SUM(K83,T83,AC83)=0,0,T83/SUM(K83,T83,AC83)) | V83: =F1677 | W83: =J1677 | X83: =V83/V82-1 | Y83: =V83/V80-1 | Z83: =V83/V77-1 | AA83: =V83/V71-1 | AB83: =STDEV.S(X72:X83)*SQRT(12) | AC83: =IF(AND(Y83>$P$6,Z83>$P$7,AA83>$P$8,V83>W83,AB83<$P$10),1,0) | AD83: =IF(SUM(K83,T83,AC83)=0,0,AC83/SUM(K83,T83,AC83)) | AE83: =IF(SUM(K83,T83,AC83)=0,1,0) | AF83: =G1677 | AG83: =AF83/AF82-1 | AH83: =0.5*(ABS(L82-L81)+ABS(U82-U81)+ABS(AD82-AD81)+ABS(AE82-AE81)) | AI83: =L82*F83+U82*O83+AD82*X83+AE82*AG83 | AJ83: =AH83*$P$11 | AK83: =AI83-AJ83 | AL83: =AL82*(1+AK83) | AM83: =MAX($AL$40:AL83) | AN83: =AL83/AM83-1 | AO83: =AK83-AG83
C84: 41912 | D84: =D1698 | E84: =H1698 | F84: =D84/D83-1 | G84: =D84/D81-1 | H84: =D84/D78-1 | I84: =D84/D72-1 | J84: =STDEV.S(F73:F84)*SQRT(12) | K84: =IF(AND(G84>$P$6,H84>$P$7,I84>$P$8,D84>E84,J84<$P$10),1,0) | L84: =IF(SUM(K84,T84,AC84)=0,0,K84/SUM(K84,T84,AC84)) | M84: =E1698 | N84: =I1698 | O84: =M84/M83-1 | P84: =M84/M81-1 | Q84: =M84/M78-1 | R84: =M84/M72-1 | S84: =STDEV.S(O73:O84)*SQRT(12) | T84: =IF(AND(P84>$P$6,Q84>$P$7,R84>$P$8,M84>N84,S84<$P$10),1,0) | U84: =IF(SUM(K84,T84,AC84)=0,0,T84/SUM(K84,T84,AC84)) | V84: =F1698 | W84: =J1698 | X84: =V84/V83-1 | Y84: =V84/V81-1 | Z84: =V84/V78-1 | AA84: =V84/V72-1 | AB84: =STDEV.S(X73:X84)*SQRT(12) | AC84: =IF(AND(Y84>$P$6,Z84>$P$7,AA84>$P$8,V84>W84,AB84<$P$10),1,0) | AD84: =IF(SUM(K84,T84,AC84)=0,0,AC84/SUM(K84,T84,AC84)) | AE84: =IF(SUM(K84,T84,AC84)=0,1,0) | AF84: =G1698 | AG84: =AF84/AF83-1 | AH84: =0.5*(ABS(L83-L82)+ABS(U83-U82)+ABS(AD83-AD82)+ABS(AE83-AE82)) | AI84: =L83*F84+U83*O84+AD83*X84+AE83*AG84 | AJ84: =AH84*$P$11 | AK84: =AI84-AJ84 | AL84: =AL83*(1+AK84) | AM84: =MAX($AL$40:AL84) | AN84: =AL84/AM84-1 | AO84: =AK84-AG84
C85: 41943 | D85: =D1721 | E85: =H1721 | F85: =D85/D84-1 | G85: =D85/D82-1 | H85: =D85/D79-1 | I85: =D85/D73-1 | J85: =STDEV.S(F74:F85)*SQRT(12) | K85: =IF(AND(G85>$P$6,H85>$P$7,I85>$P$8,D85>E85,J85<$P$10),1,0) | L85: =IF(SUM(K85,T85,AC85)=0,0,K85/SUM(K85,T85,AC85)) | M85: =E1721 | N85: =I1721 | O85: =M85/M84-1 | P85: =M85/M82-1 | Q85: =M85/M79-1 | R85: =M85/M73-1 | S85: =STDEV.S(O74:O85)*SQRT(12) | T85: =IF(AND(P85>$P$6,Q85>$P$7,R85>$P$8,M85>N85,S85<$P$10),1,0) | U85: =IF(SUM(K85,T85,AC85)=0,0,T85/SUM(K85,T85,AC85)) | V85: =F1721 | W85: =J1721 | X85: =V85/V84-1 | Y85: =V85/V82-1 | Z85: =V85/V79-1 | AA85: =V85/V73-1 | AB85: =STDEV.S(X74:X85)*SQRT(12) | AC85: =IF(AND(Y85>$P$6,Z85>$P$7,AA85>$P$8,V85>W85,AB85<$P$10),1,0) | AD85: =IF(SUM(K85,T85,AC85)=0,0,AC85/SUM(K85,T85,AC85)) | AE85: =IF(SUM(K85,T85,AC85)=0,1,0) | AF85: =G1721 | AG85: =AF85/AF84-1 | AH85: =0.5*(ABS(L84-L83)+ABS(U84-U83)+ABS(AD84-AD83)+ABS(AE84-AE83)) | AI85: =L84*F85+U84*O85+AD84*X85+AE84*AG85 | AJ85: =AH85*$P$11 | AK85: =AI85-AJ85 | AL85: =AL84*(1+AK85) | AM85: =MAX($AL$40:AL85) | AN85: =AL85/AM85-1 | AO85: =AK85-AG85
C86: 41973 | D86: =D1740 | E86: =H1740 | F86: =D86/D85-1 | G86: =D86/D83-1 | H86: =D86/D80-1 | I86: =D86/D74-1 | J86: =STDEV.S(F75:F86)*SQRT(12) | K86: =IF(AND(G86>$P$6,H86>$P$7,I86>$P$8,D86>E86,J86<$P$10),1,0) | L86: =IF(SUM(K86,T86,AC86)=0,0,K86/SUM(K86,T86,AC86)) | M86: =E1740 | N86: =I1740 | O86: =M86/M85-1 | P86: =M86/M83-1 | Q86: =M86/M80-1 | R86: =M86/M74-1 | S86: =STDEV.S(O75:O86)*SQRT(12) | T86: =IF(AND(P86>$P$6,Q86>$P$7,R86>$P$8,M86>N86,S86<$P$10),1,0) | U86: =IF(SUM(K86,T86,AC86)=0,0,T86/SUM(K86,T86,AC86)) | V86: =F1740 | W86: =J1740 | X86: =V86/V85-1 | Y86: =V86/V83-1 | Z86: =V86/V80-1 | AA86: =V86/V74-1 | AB86: =STDEV.S(X75:X86)*SQRT(12) | AC86: =IF(AND(Y86>$P$6,Z86>$P$7,AA86>$P$8,V86>W86,AB86<$P$10),1,0) | AD86: =IF(SUM(K86,T86,AC86)=0,0,AC86/SUM(K86,T86,AC86)) | AE86: =IF(SUM(K86,T86,AC86)=0,1,0) | AF86: =G1740 | AG86: =AF86/AF85-1 | AH86: =0.5*(ABS(L85-L84)+ABS(U85-U84)+ABS(AD85-AD84)+ABS(AE85-AE84)) | AI86: =L85*F86+U85*O86+AD85*X86+AE85*AG86 | AJ86: =AH86*$P$11 | AK86: =AI86-AJ86 | AL86: =AL85*(1+AK86) | AM86: =MAX($AL$40:AL86) | AN86: =AL86/AM86-1 | AO86: =AK86-AG86
C87: 42004 | D87: =D1762 | E87: =H1762 | F87: =D87/D86-1 | G87: =D87/D84-1 | H87: =D87/D81-1 | I87: =D87/D75-1 | J87: =STDEV.S(F76:F87)*SQRT(12) | K87: =IF(AND(G87>$P$6,H87>$P$7,I87>$P$8,D87>E87,J87<$P$10),1,0) | L87: =IF(SUM(K87,T87,AC87)=0,0,K87/SUM(K87,T87,AC87)) | M87: =E1762 | N87: =I1762 | O87: =M87/M86-1 | P87: =M87/M84-1 | Q87: =M87/M81-1 | R87: =M87/M75-1 | S87: =STDEV.S(O76:O87)*SQRT(12) | T87: =IF(AND(P87>$P$6,Q87>$P$7,R87>$P$8,M87>N87,S87<$P$10),1,0) | U87: =IF(SUM(K87,T87,AC87)=0,0,T87/SUM(K87,T87,AC87)) | V87: =F1762 | W87: =J1762 | X87: =V87/V86-1 | Y87: =V87/V84-1 | Z87: =V87/V81-1 | AA87: =V87/V75-1 | AB87: =STDEV.S(X76:X87)*SQRT(12) | AC87: =IF(AND(Y87>$P$6,Z87>$P$7,AA87>$P$8,V87>W87,AB87<$P$10),1,0) | AD87: =IF(SUM(K87,T87,AC87)=0,0,AC87/SUM(K87,T87,AC87)) | AE87: =IF(SUM(K87,T87,AC87)=0,1,0) | AF87: =G1762 | AG87: =AF87/AF86-1 | AH87: =0.5*(ABS(L86-L85)+ABS(U86-U85)+ABS(AD86-AD85)+ABS(AE86-AE85)) | AI87: =L86*F87+U86*O87+AD86*X87+AE86*AG87 | AJ87: =AH87*$P$11 | AK87: =AI87-AJ87 | AL87: =AL86*(1+AK87) | AM87: =MAX($AL$40:AL87) | AN87: =AL87/AM87-1 | AO87: =AK87-AG87
C88: 42035 | D88: =D1782 | E88: =H1782 | F88: =D88/D87-1 | G88: =D88/D85-1 | H88: =D88/D82-1 | I88: =D88/D76-1 | J88: =STDEV.S(F77:F88)*SQRT(12) | K88: =IF(AND(G88>$P$6,H88>$P$7,I88>$P$8,D88>E88,J88<$P$10),1,0) | L88: =IF(SUM(K88,T88,AC88)=0,0,K88/SUM(K88,T88,AC88)) | M88: =E1782 | N88: =I1782 | O88: =M88/M87-1 | P88: =M88/M85-1 | Q88: =M88/M82-1 | R88: =M88/M76-1 | S88: =STDEV.S(O77:O88)*SQRT(12) | T88: =IF(AND(P88>$P$6,Q88>$P$7,R88>$P$8,M88>N88,S88<$P$10),1,0) | U88: =IF(SUM(K88,T88,AC88)=0,0,T88/SUM(K88,T88,AC88)) | V88: =F1782 | W88: =J1782 | X88: =V88/V87-1 | Y88: =V88/V85-1 | Z88: =V88/V82-1 | AA88: =V88/V76-1 | AB88: =STDEV.S(X77:X88)*SQRT(12) | AC88: =IF(AND(Y88>$P$6,Z88>$P$7,AA88>$P$8,V88>W88,AB88<$P$10),1,0) | AD88: =IF(SUM(K88,T88,AC88)=0,0,AC88/SUM(K88,T88,AC88)) | AE88: =IF(SUM(K88,T88,AC88)=0,1,0) | AF88: =G1782 | AG88: =AF88/AF87-1 | AH88: =0.5*(ABS(L87-L86)+ABS(U87-U86)+ABS(AD87-AD86)+ABS(AE87-AE86)) | AI88: =L87*F88+U87*O88+AD87*X88+AE87*AG88 | AJ88: =AH88*$P$11 | AK88: =AI88-AJ88 | AL88: =AL87*(1+AK88) | AM88: =MAX($AL$40:AL88) | AN88: =AL88/AM88-1 | AO88: =AK88-AG88
C89: 42063 | D89: =D1801 | E89: =H1801 | F89: =D89/D88-1 | G89: =D89/D86-1 | H89: =D89/D83-1 | I89: =D89/D77-1 | J89: =STDEV.S(F78:F89)*SQRT(12) | K89: =IF(AND(G89>$P$6,H89>$P$7,I89>$P$8,D89>E89,J89<$P$10),1,0) | L89: =IF(SUM(K89,T89,AC89)=0,0,K89/SUM(K89,T89,AC89)) | M89: =E1801 | N89: =I1801 | O89: =M89/M88-1 | P89: =M89/M86-1 | Q89: =M89/M83-1 | R89: =M89/M77-1 | S89: =STDEV.S(O78:O89)*SQRT(12) | T89: =IF(AND(P89>$P$6,Q89>$P$7,R89>$P$8,M89>N89,S89<$P$10),1,0) | U89: =IF(SUM(K89,T89,AC89)=0,0,T89/SUM(K89,T89,AC89)) | V89: =F1801 | W89: =J1801 | X89: =V89/V88-1 | Y89: =V89/V86-1 | Z89: =V89/V83-1 | AA89: =V89/V77-1 | AB89: =STDEV.S(X78:X89)*SQRT(12) | AC89: =IF(AND(Y89>$P$6,Z89>$P$7,AA89>$P$8,V89>W89,AB89<$P$10),1,0) | AD89: =IF(SUM(K89,T89,AC89)=0,0,AC89/SUM(K89,T89,AC89)) | AE89: =IF(SUM(K89,T89,AC89)=0,1,0) | AF89: =G1801 | AG89: =AF89/AF88-1 | AH89: =0.5*(ABS(L88-L87)+ABS(U88-U87)+ABS(AD88-AD87)+ABS(AE88-AE87)) | AI89: =L88*F89+U88*O89+AD88*X89+AE88*AG89 | AJ89: =AH89*$P$11 | AK89: =AI89-AJ89 | AL89: =AL88*(1+AK89) | AM89: =MAX($AL$40:AL89) | AN89: =AL89/AM89-1 | AO89: =AK89-AG89
C90: 42094 | D90: =D1823 | E90: =H1823 | F90: =D90/D89-1 | G90: =D90/D87-1 | H90: =D90/D84-1 | I90: =D90/D78-1 | J90: =STDEV.S(F79:F90)*SQRT(12) | K90: =IF(AND(G90>$P$6,H90>$P$7,I90>$P$8,D90>E90,J90<$P$10),1,0) | L90: =IF(SUM(K90,T90,AC90)=0,0,K90/SUM(K90,T90,AC90)) | M90: =E1823 | N90: =I1823 | O90: =M90/M89-1 | P90: =M90/M87-1 | Q90: =M90/M84-1 | R90: =M90/M78-1 | S90: =STDEV.S(O79:O90)*SQRT(12) | T90: =IF(AND(P90>$P$6,Q90>$P$7,R90>$P$8,M90>N90,S90<$P$10),1,0) | U90: =IF(SUM(K90,T90,AC90)=0,0,T90/SUM(K90,T90,AC90)) | V90: =F1823 | W90: =J1823 | X90: =V90/V89-1 | Y90: =V90/V87-1 | Z90: =V90/V84-1 | AA90: =V90/V78-1 | AB90: =STDEV.S(X79:X90)*SQRT(12) | AC90: =IF(AND(Y90>$P$6,Z90>$P$7,AA90>$P$8,V90>W90,AB90<$P$10),1,0) | AD90: =IF(SUM(K90,T90,AC90)=0,0,AC90/SUM(K90,T90,AC90)) | AE90: =IF(SUM(K90,T90,AC90)=0,1,0) | AF90: =G1823 | AG90: =AF90/AF89-1 | AH90: =0.5*(ABS(L89-L88)+ABS(U89-U88)+ABS(AD89-AD88)+ABS(AE89-AE88)) | AI90: =L89*F90+U89*O90+AD89*X90+AE89*AG90 | AJ90: =AH90*$P$11 | AK90: =AI90-AJ90 | AL90: =AL89*(1+AK90) | AM90: =MAX($AL$40:AL90) | AN90: =AL90/AM90-1 | AO90: =AK90-AG90
C91: 42124 | D91: =D1844 | E91: =H1844 | F91: =D91/D90-1 | G91: =D91/D88-1 | H91: =D91/D85-1 | I91: =D91/D79-1 | J91: =STDEV.S(F80:F91)*SQRT(12) | K91: =IF(AND(G91>$P$6,H91>$P$7,I91>$P$8,D91>E91,J91<$P$10),1,0) | L91: =IF(SUM(K91,T91,AC91)=0,0,K91/SUM(K91,T91,AC91)) | M91: =E1844 | N91: =I1844 | O91: =M91/M90-1 | P91: =M91/M88-1 | Q91: =M91/M85-1 | R91: =M91/M79-1 | S91: =STDEV.S(O80:O91)*SQRT(12) | T91: =IF(AND(P91>$P$6,Q91>$P$7,R91>$P$8,M91>N91,S91<$P$10),1,0) | U91: =IF(SUM(K91,T91,AC91)=0,0,T91/SUM(K91,T91,AC91)) | V91: =F1844 | W91: =J1844 | X91: =V91/V90-1 | Y91: =V91/V88-1 | Z91: =V91/V85-1 | AA91: =V91/V79-1 | AB91: =STDEV.S(X80:X91)*SQRT(12) | AC91: =IF(AND(Y91>$P$6,Z91>$P$7,AA91>$P$8,V91>W91,AB91<$P$10),1,0) | AD91: =IF(SUM(K91,T91,AC91)=0,0,AC91/SUM(K91,T91,AC91)) | AE91: =IF(SUM(K91,T91,AC91)=0,1,0) | AF91: =G1844 | AG91: =AF91/AF90-1 | AH91: =0.5*(ABS(L90-L89)+ABS(U90-U89)+ABS(AD90-AD89)+ABS(AE90-AE89)) | AI91: =L90*F91+U90*O91+AD90*X91+AE90*AG91 | AJ91: =AH91*$P$11 | AK91: =AI91-AJ91 | AL91: =AL90*(1+AK91) | AM91: =MAX($AL$40:AL91) | AN91: =AL91/AM91-1 | AO91: =AK91-AG91
C92: 42155 | D92: =D1864 | E92: =H1864 | F92: =D92/D91-1 | G92: =D92/D89-1 | H92: =D92/D86-1 | I92: =D92/D80-1 | J92: =STDEV.S(F81:F92)*SQRT(12) | K92: =IF(AND(G92>$P$6,H92>$P$7,I92>$P$8,D92>E92,J92<$P$10),1,0) | L92: =IF(SUM(K92,T92,AC92)=0,0,K92/SUM(K92,T92,AC92)) | M92: =E1864 | N92: =I1864 | O92: =M92/M91-1 | P92: =M92/M89-1 | Q92: =M92/M86-1 | R92: =M92/M80-1 | S92: =STDEV.S(O81:O92)*SQRT(12) | T92: =IF(AND(P92>$P$6,Q92>$P$7,R92>$P$8,M92>N92,S92<$P$10),1,0) | U92: =IF(SUM(K92,T92,AC92)=0,0,T92/SUM(K92,T92,AC92)) | V92: =F1864 | W92: =J1864 | X92: =V92/V91-1 | Y92: =V92/V89-1 | Z92: =V92/V86-1 | AA92: =V92/V80-1 | AB92: =STDEV.S(X81:X92)*SQRT(12) | AC92: =IF(AND(Y92>$P$6,Z92>$P$7,AA92>$P$8,V92>W92,AB92<$P$10),1,0) | AD92: =IF(SUM(K92,T92,AC92)=0,0,AC92/SUM(K92,T92,AC92)) | AE92: =IF(SUM(K92,T92,AC92)=0,1,0) | AF92: =G1864 | AG92: =AF92/AF91-1 | AH92: =0.5*(ABS(L91-L90)+ABS(U91-U90)+ABS(AD91-AD90)+ABS(AE91-AE90)) | AI92: =L91*F92+U91*O92+AD91*X92+AE91*AG92 | AJ92: =AH92*$P$11 | AK92: =AI92-AJ92 | AL92: =AL91*(1+AK92) | AM92: =MAX($AL$40:AL92) | AN92: =AL92/AM92-1 | AO92: =AK92-AG92
C93: 42185 | D93: =D1886 | E93: =H1886 | F93: =D93/D92-1 | G93: =D93/D90-1 | H93: =D93/D87-1 | I93: =D93/D81-1 | J93: =STDEV.S(F82:F93)*SQRT(12) | K93: =IF(AND(G93>$P$6,H93>$P$7,I93>$P$8,D93>E93,J93<$P$10),1,0) | L93: =IF(SUM(K93,T93,AC93)=0,0,K93/SUM(K93,T93,AC93)) | M93: =E1886 | N93: =I1886 | O93: =M93/M92-1 | P93: =M93/M90-1 | Q93: =M93/M87-1 | R93: =M93/M81-1 | S93: =STDEV.S(O82:O93)*SQRT(12) | T93: =IF(AND(P93>$P$6,Q93>$P$7,R93>$P$8,M93>N93,S93<$P$10),1,0) | U93: =IF(SUM(K93,T93,AC93)=0,0,T93/SUM(K93,T93,AC93)) | V93: =F1886 | W93: =J1886 | X93: =V93/V92-1 | Y93: =V93/V90-1 | Z93: =V93/V87-1 | AA93: =V93/V81-1 | AB93: =STDEV.S(X82:X93)*SQRT(12) | AC93: =IF(AND(Y93>$P$6,Z93>$P$7,AA93>$P$8,V93>W93,AB93<$P$10),1,0) | AD93: =IF(SUM(K93,T93,AC93)=0,0,AC93/SUM(K93,T93,AC93)) | AE93: =IF(SUM(K93,T93,AC93)=0,1,0) | AF93: =G1886 | AG93: =AF93/AF92-1 | AH93: =0.5*(ABS(L92-L91)+ABS(U92-U91)+ABS(AD92-AD91)+ABS(AE92-AE91)) | AI93: =L92*F93+U92*O93+AD92*X93+AE92*AG93 | AJ93: =AH93*$P$11 | AK93: =AI93-AJ93 | AL93: =AL92*(1+AK93) | AM93: =MAX($AL$40:AL93) | AN93: =AL93/AM93-1 | AO93: =AK93-AG93
C94: 42216 | D94: =D1908 | E94: =H1908 | F94: =D94/D93-1 | G94: =D94/D91-1 | H94: =D94/D88-1 | I94: =D94/D82-1 | J94: =STDEV.S(F83:F94)*SQRT(12) | K94: =IF(AND(G94>$P$6,H94>$P$7,I94>$P$8,D94>E94,J94<$P$10),1,0) | L94: =IF(SUM(K94,T94,AC94)=0,0,K94/SUM(K94,T94,AC94)) | M94: =E1908 | N94: =I1908 | O94: =M94/M93-1 | P94: =M94/M91-1 | Q94: =M94/M88-1 | R94: =M94/M82-1 | S94: =STDEV.S(O83:O94)*SQRT(12) | T94: =IF(AND(P94>$P$6,Q94>$P$7,R94>$P$8,M94>N94,S94<$P$10),1,0) | U94: =IF(SUM(K94,T94,AC94)=0,0,T94/SUM(K94,T94,AC94)) | V94: =F1908 | W94: =J1908 | X94: =V94/V93-1 | Y94: =V94/V91-1 | Z94: =V94/V88-1 | AA94: =V94/V82-1 | AB94: =STDEV.S(X83:X94)*SQRT(12) | AC94: =IF(AND(Y94>$P$6,Z94>$P$7,AA94>$P$8,V94>W94,AB94<$P$10),1,0) | AD94: =IF(SUM(K94,T94,AC94)=0,0,AC94/SUM(K94,T94,AC94)) | AE94: =IF(SUM(K94,T94,AC94)=0,1,0) | AF94: =G1908 | AG94: =AF94/AF93-1 | AH94: =0.5*(ABS(L93-L92)+ABS(U93-U92)+ABS(AD93-AD92)+ABS(AE93-AE92)) | AI94: =L93*F94+U93*O94+AD93*X94+AE93*AG94 | AJ94: =AH94*$P$11 | AK94: =AI94-AJ94 | AL94: =AL93*(1+AK94) | AM94: =MAX($AL$40:AL94) | AN94: =AL94/AM94-1 | AO94: =AK94-AG94
C95: 42247 | D95: =D1929 | E95: =H1929 | F95: =D95/D94-1 | G95: =D95/D92-1 | H95: =D95/D89-1 | I95: =D95/D83-1 | J95: =STDEV.S(F84:F95)*SQRT(12) | K95: =IF(AND(G95>$P$6,H95>$P$7,I95>$P$8,D95>E95,J95<$P$10),1,0) | L95: =IF(SUM(K95,T95,AC95)=0,0,K95/SUM(K95,T95,AC95)) | M95: =E1929 | N95: =I1929 | O95: =M95/M94-1 | P95: =M95/M92-1 | Q95: =M95/M89-1 | R95: =M95/M83-1 | S95: =STDEV.S(O84:O95)*SQRT(12) | T95: =IF(AND(P95>$P$6,Q95>$P$7,R95>$P$8,M95>N95,S95<$P$10),1,0) | U95: =IF(SUM(K95,T95,AC95)=0,0,T95/SUM(K95,T95,AC95)) | V95: =F1929 | W95: =J1929 | X95: =V95/V94-1 | Y95: =V95/V92-1 | Z95: =V95/V89-1 | AA95: =V95/V83-1 | AB95: =STDEV.S(X84:X95)*SQRT(12) | AC95: =IF(AND(Y95>$P$6,Z95>$P$7,AA95>$P$8,V95>W95,AB95<$P$10),1,0) | AD95: =IF(SUM(K95,T95,AC95)=0,0,AC95/SUM(K95,T95,AC95)) | AE95: =IF(SUM(K95,T95,AC95)=0,1,0) | AF95: =G1929 | AG95: =AF95/AF94-1 | AH95: =0.5*(ABS(L94-L93)+ABS(U94-U93)+ABS(AD94-AD93)+ABS(AE94-AE93)) | AI95: =L94*F95+U94*O95+AD94*X95+AE94*AG95 | AJ95: =AH95*$P$11 | AK95: =AI95-AJ95 | AL95: =AL94*(1+AK95) | AM95: =MAX($AL$40:AL95) | AN95: =AL95/AM95-1 | AO95: =AK95-AG95
C96: 42277 | D96: =D1950 | E96: =H1950 | F96: =D96/D95-1 | G96: =D96/D93-1 | H96: =D96/D90-1 | I96: =D96/D84-1 | J96: =STDEV.S(F85:F96)*SQRT(12) | K96: =IF(AND(G96>$P$6,H96>$P$7,I96>$P$8,D96>E96,J96<$P$10),1,0) | L96: =IF(SUM(K96,T96,AC96)=0,0,K96/SUM(K96,T96,AC96)) | M96: =E1950 | N96: =I1950 | O96: =M96/M95-1 | P96: =M96/M93-1 | Q96: =M96/M90-1 | R96: =M96/M84-1 | S96: =STDEV.S(O85:O96)*SQRT(12) | T96: =IF(AND(P96>$P$6,Q96>$P$7,R96>$P$8,M96>N96,S96<$P$10),1,0) | U96: =IF(SUM(K96,T96,AC96)=0,0,T96/SUM(K96,T96,AC96)) | V96: =F1950 | W96: =J1950 | X96: =V96/V95-1 | Y96: =V96/V93-1 | Z96: =V96/V90-1 | AA96: =V96/V84-1 | AB96: =STDEV.S(X85:X96)*SQRT(12) | AC96: =IF(AND(Y96>$P$6,Z96>$P$7,AA96>$P$8,V96>W96,AB96<$P$10),1,0) | AD96: =IF(SUM(K96,T96,AC96)=0,0,AC96/SUM(K96,T96,AC96)) | AE96: =IF(SUM(K96,T96,AC96)=0,1,0) | AF96: =G1950 | AG96: =AF96/AF95-1 | AH96: =0.5*(ABS(L95-L94)+ABS(U95-U94)+ABS(AD95-AD94)+ABS(AE95-AE94)) | AI96: =L95*F96+U95*O96+AD95*X96+AE95*AG96 | AJ96: =AH96*$P$11 | AK96: =AI96-AJ96 | AL96: =AL95*(1+AK96) | AM96: =MAX($AL$40:AL96) | AN96: =AL96/AM96-1 | AO96: =AK96-AG96
C97: 42308 | D97: =D1972 | E97: =H1972 | F97: =D97/D96-1 | G97: =D97/D94-1 | H97: =D97/D91-1 | I97: =D97/D85-1 | J97: =STDEV.S(F86:F97)*SQRT(12) | K97: =IF(AND(G97>$P$6,H97>$P$7,I97>$P$8,D97>E97,J97<$P$10),1,0) | L97: =IF(SUM(K97,T97,AC97)=0,0,K97/SUM(K97,T97,AC97)) | M97: =E1972 | N97: =I1972 | O97: =M97/M96-1 | P97: =M97/M94-1 | Q97: =M97/M91-1 | R97: =M97/M85-1 | S97: =STDEV.S(O86:O97)*SQRT(12) | T97: =IF(AND(P97>$P$6,Q97>$P$7,R97>$P$8,M97>N97,S97<$P$10),1,0) | U97: =IF(SUM(K97,T97,AC97)=0,0,T97/SUM(K97,T97,AC97)) | V97: =F1972 | W97: =J1972 | X97: =V97/V96-1 | Y97: =V97/V94-1 | Z97: =V97/V91-1 | AA97: =V97/V85-1 | AB97: =STDEV.S(X86:X97)*SQRT(12) | AC97: =IF(AND(Y97>$P$6,Z97>$P$7,AA97>$P$8,V97>W97,AB97<$P$10),1,0) | AD97: =IF(SUM(K97,T97,AC97)=0,0,AC97/SUM(K97,T97,AC97)) | AE97: =IF(SUM(K97,T97,AC97)=0,1,0) | AF97: =G1972 | AG97: =AF97/AF96-1 | AH97: =0.5*(ABS(L96-L95)+ABS(U96-U95)+ABS(AD96-AD95)+ABS(AE96-AE95)) | AI97: =L96*F97+U96*O97+AD96*X97+AE96*AG97 | AJ97: =AH97*$P$11 | AK97: =AI97-AJ97 | AL97: =AL96*(1+AK97) | AM97: =MAX($AL$40:AL97) | AN97: =AL97/AM97-1 | AO97: =AK97-AG97
C98: 42338 | D98: =D1992 | E98: =H1992 | F98: =D98/D97-1 | G98: =D98/D95-1 | H98: =D98/D92-1 | I98: =D98/D86-1 | J98: =STDEV.S(F87:F98)*SQRT(12) | K98: =IF(AND(G98>$P$6,H98>$P$7,I98>$P$8,D98>E98,J98<$P$10),1,0) | L98: =IF(SUM(K98,T98,AC98)=0,0,K98/SUM(K98,T98,AC98)) | M98: =E1992 | N98: =I1992 | O98: =M98/M97-1 | P98: =M98/M95-1 | Q98: =M98/M92-1 | R98: =M98/M86-1 | S98: =STDEV.S(O87:O98)*SQRT(12) | T98: =IF(AND(P98>$P$6,Q98>$P$7,R98>$P$8,M98>N98,S98<$P$10),1,0) | U98: =IF(SUM(K98,T98,AC98)=0,0,T98/SUM(K98,T98,AC98)) | V98: =F1992 | W98: =J1992 | X98: =V98/V97-1 | Y98: =V98/V95-1 | Z98: =V98/V92-1 | AA98: =V98/V86-1 | AB98: =STDEV.S(X87:X98)*SQRT(12) | AC98: =IF(AND(Y98>$P$6,Z98>$P$7,AA98>$P$8,V98>W98,AB98<$P$10),1,0) | AD98: =IF(SUM(K98,T98,AC98)=0,0,AC98/SUM(K98,T98,AC98)) | AE98: =IF(SUM(K98,T98,AC98)=0,1,0) | AF98: =G1992 | AG98: =AF98/AF97-1 | AH98: =0.5*(ABS(L97-L96)+ABS(U97-U96)+ABS(AD97-AD96)+ABS(AE97-AE96)) | AI98: =L97*F98+U97*O98+AD97*X98+AE97*AG98 | AJ98: =AH98*$P$11 | AK98: =AI98-AJ98 | AL98: =AL97*(1+AK98) | AM98: =MAX($AL$40:AL98) | AN98: =AL98/AM98-1 | AO98: =AK98-AG98
C99: 42369 | D99: =D2014 | E99: =H2014 | F99: =D99/D98-1 | G99: =D99/D96-1 | H99: =D99/D93-1 | I99: =D99/D87-1 | J99: =STDEV.S(F88:F99)*SQRT(12) | K99: =IF(AND(G99>$P$6,H99>$P$7,I99>$P$8,D99>E99,J99<$P$10),1,0) | L99: =IF(SUM(K99,T99,AC99)=0,0,K99/SUM(K99,T99,AC99)) | M99: =E2014 | N99: =I2014 | O99: =M99/M98-1 | P99: =M99/M96-1 | Q99: =M99/M93-1 | R99: =M99/M87-1 | S99: =STDEV.S(O88:O99)*SQRT(12) | T99: =IF(AND(P99>$P$6,Q99>$P$7,R99>$P$8,M99>N99,S99<$P$10),1,0) | U99: =IF(SUM(K99,T99,AC99)=0,0,T99/SUM(K99,T99,AC99)) | V99: =F2014 | W99: =J2014 | X99: =V99/V98-1 | Y99: =V99/V96-1 | Z99: =V99/V93-1 | AA99: =V99/V87-1 | AB99: =STDEV.S(X88:X99)*SQRT(12) | AC99: =IF(AND(Y99>$P$6,Z99>$P$7,AA99>$P$8,V99>W99,AB99<$P$10),1,0) | AD99: =IF(SUM(K99,T99,AC99)=0,0,AC99/SUM(K99,T99,AC99)) | AE99: =IF(SUM(K99,T99,AC99)=0,1,0) | AF99: =G2014 | AG99: =AF99/AF98-1 | AH99: =0.5*(ABS(L98-L97)+ABS(U98-U97)+ABS(AD98-AD97)+ABS(AE98-AE97)) | AI99: =L98*F99+U98*O99+AD98*X99+AE98*AG99 | AJ99: =AH99*$P$11 | AK99: =AI99-AJ99 | AL99: =AL98*(1+AK99) | AM99: =MAX($AL$40:AL99) | AN99: =AL99/AM99-1 | AO99: =AK99-AG99
C100: 42400 | D100: =D2033 | E100: =H2033 | F100: =D100/D99-1 | G100: =D100/D97-1 | H100: =D100/D94-1 | I100: =D100/D88-1 | J100: =STDEV.S(F89:F100)*SQRT(12) | K100: =IF(AND(G100>$P$6,H100>$P$7,I100>$P$8,D100>E100,J100<$P$10),1,0) | L100: =IF(SUM(K100,T100,AC100)=0,0,K100/SUM(K100,T100,AC100)) | M100: =E2033 | N100: =I2033 | O100: =M100/M99-1 | P100: =M100/M97-1 | Q100: =M100/M94-1 | R100: =M100/M88-1 | S100: =STDEV.S(O89:O100)*SQRT(12) | T100: =IF(AND(P100>$P$6,Q100>$P$7,R100>$P$8,M100>N100,S100<$P$10),1,0) | U100: =IF(SUM(K100,T100,AC100)=0,0,T100/SUM(K100,T100,AC100)) | V100: =F2033 | W100: =J2033 | X100: =V100/V99-1 | Y100: =V100/V97-1 | Z100: =V100/V94-1 | AA100: =V100/V88-1 | AB100: =STDEV.S(X89:X100)*SQRT(12) | AC100: =IF(AND(Y100>$P$6,Z100>$P$7,AA100>$P$8,V100>W100,AB100<$P$10),1,0) | AD100: =IF(SUM(K100,T100,AC100)=0,0,AC100/SUM(K100,T100,AC100)) | AE100: =IF(SUM(K100,T100,AC100)=0,1,0) | AF100: =G2033 | AG100: =AF100/AF99-1 | AH100: =0.5*(ABS(L99-L98)+ABS(U99-U98)+ABS(AD99-AD98)+ABS(AE99-AE98)) | AI100: =L99*F100+U99*O100+AD99*X100+AE99*AG100 | AJ100: =AH100*$P$11 | AK100: =AI100-AJ100 | AL100: =AL99*(1+AK100) | AM100: =MAX($AL$40:AL100) | AN100: =AL100/AM100-1 | AO100: =AK100-AG100
C101: 42429 | D101: =D2053 | E101: =H2053 | F101: =D101/D100-1 | G101: =D101/D98-1 | H101: =D101/D95-1 | I101: =D101/D89-1 | J101: =STDEV.S(F90:F101)*SQRT(12) | K101: =IF(AND(G101>$P$6,H101>$P$7,I101>$P$8,D101>E101,J101<$P$10),1,0) | L101: =IF(SUM(K101,T101,AC101)=0,0,K101/SUM(K101,T101,AC101)) | M101: =E2053 | N101: =I2053 | O101: =M101/M100-1 | P101: =M101/M98-1 | Q101: =M101/M95-1 | R101: =M101/M89-1 | S101: =STDEV.S(O90:O101)*SQRT(12) | T101: =IF(AND(P101>$P$6,Q101>$P$7,R101>$P$8,M101>N101,S101<$P$10),1,0) | U101: =IF(SUM(K101,T101,AC101)=0,0,T101/SUM(K101,T101,AC101)) | V101: =F2053 | W101: =J2053 | X101: =V101/V100-1 | Y101: =V101/V98-1 | Z101: =V101/V95-1 | AA101: =V101/V89-1 | AB101: =STDEV.S(X90:X101)*SQRT(12) | AC101: =IF(AND(Y101>$P$6,Z101>$P$7,AA101>$P$8,V101>W101,AB101<$P$10),1,0) | AD101: =IF(SUM(K101,T101,AC101)=0,0,AC101/SUM(K101,T101,AC101)) | AE101: =IF(SUM(K101,T101,AC101)=0,1,0) | AF101: =G2053 | AG101: =AF101/AF100-1 | AH101: =0.5*(ABS(L100-L99)+ABS(U100-U99)+ABS(AD100-AD99)+ABS(AE100-AE99)) | AI101: =L100*F101+U100*O101+AD100*X101+AE100*AG101 | AJ101: =AH101*$P$11 | AK101: =AI101-AJ101 | AL101: =AL100*(1+AK101) | AM101: =MAX($AL$40:AL101) | AN101: =AL101/AM101-1 | AO101: =AK101-AG101
C102: 42460 | D102: =D2075 | E102: =H2075 | F102: =D102/D101-1 | G102: =D102/D99-1 | H102: =D102/D96-1 | I102: =D102/D90-1 | J102: =STDEV.S(F91:F102)*SQRT(12) | K102: =IF(AND(G102>$P$6,H102>$P$7,I102>$P$8,D102>E102,J102<$P$10),1,0) | L102: =IF(SUM(K102,T102,AC102)=0,0,K102/SUM(K102,T102,AC102)) | M102: =E2075 | N102: =I2075 | O102: =M102/M101-1 | P102: =M102/M99-1 | Q102: =M102/M96-1 | R102: =M102/M90-1 | S102: =STDEV.S(O91:O102)*SQRT(12) | T102: =IF(AND(P102>$P$6,Q102>$P$7,R102>$P$8,M102>N102,S102<$P$10),1,0) | U102: =IF(SUM(K102,T102,AC102)=0,0,T102/SUM(K102,T102,AC102)) | V102: =F2075 | W102: =J2075 | X102: =V102/V101-1 | Y102: =V102/V99-1 | Z102: =V102/V96-1 | AA102: =V102/V90-1 | AB102: =STDEV.S(X91:X102)*SQRT(12) | AC102: =IF(AND(Y102>$P$6,Z102>$P$7,AA102>$P$8,V102>W102,AB102<$P$10),1,0) | AD102: =IF(SUM(K102,T102,AC102)=0,0,AC102/SUM(K102,T102,AC102)) | AE102: =IF(SUM(K102,T102,AC102)=0,1,0) | AF102: =G2075 | AG102: =AF102/AF101-1 | AH102: =0.5*(ABS(L101-L100)+ABS(U101-U100)+ABS(AD101-AD100)+ABS(AE101-AE100)) | AI102: =L101*F102+U101*O102+AD101*X102+AE101*AG102 | AJ102: =AH102*$P$11 | AK102: =AI102-AJ102 | AL102: =AL101*(1+AK102) | AM102: =MAX($AL$40:AL102) | AN102: =AL102/AM102-1 | AO102: =AK102-AG102
C103: 42490 | D103: =D2096 | E103: =H2096 | F103: =D103/D102-1 | G103: =D103/D100-1 | H103: =D103/D97-1 | I103: =D103/D91-1 | J103: =STDEV.S(F92:F103)*SQRT(12) | K103: =IF(AND(G103>$P$6,H103>$P$7,I103>$P$8,D103>E103,J103<$P$10),1,0) | L103: =IF(SUM(K103,T103,AC103)=0,0,K103/SUM(K103,T103,AC103)) | M103: =E2096 | N103: =I2096 | O103: =M103/M102-1 | P103: =M103/M100-1 | Q103: =M103/M97-1 | R103: =M103/M91-1 | S103: =STDEV.S(O92:O103)*SQRT(12) | T103: =IF(AND(P103>$P$6,Q103>$P$7,R103>$P$8,M103>N103,S103<$P$10),1,0) | U103: =IF(SUM(K103,T103,AC103)=0,0,T103/SUM(K103,T103,AC103)) | V103: =F2096 | W103: =J2096 | X103: =V103/V102-1 | Y103: =V103/V100-1 | Z103: =V103/V97-1 | AA103: =V103/V91-1 | AB103: =STDEV.S(X92:X103)*SQRT(12) | AC103: =IF(AND(Y103>$P$6,Z103>$P$7,AA103>$P$8,V103>W103,AB103<$P$10),1,0) | AD103: =IF(SUM(K103,T103,AC103)=0,0,AC103/SUM(K103,T103,AC103)) | AE103: =IF(SUM(K103,T103,AC103)=0,1,0) | AF103: =G2096 | AG103: =AF103/AF102-1 | AH103: =0.5*(ABS(L102-L101)+ABS(U102-U101)+ABS(AD102-AD101)+ABS(AE102-AE101)) | AI103: =L102*F103+U102*O103+AD102*X103+AE102*AG103 | AJ103: =AH103*$P$11 | AK103: =AI103-AJ103 | AL103: =AL102*(1+AK103) | AM103: =MAX($AL$40:AL103) | AN103: =AL103/AM103-1 | AO103: =AK103-AG103
...

Sheet 08_Proxies_Activas
C2: MODELO NEXUM - PROXIES PROVISIONALES DE MOMENTUM Y BAB
C3: Capa transitoria para estimación: SPMO y SPLV. No reemplaza los backtests point-in-time de selección individual.
C5: VENTANA COMÚN PROVISIONAL | H5: LECTURA CORRECTA
C6: Inicio niveles | D6: 42308 | E6: Mes | F6: Limitado por inicio de SPMO | H6: SPMO sigue el S&P 500 Momentum Index y constituye una proxy directa del factor, pero sus reglas no son idénticas al screening Nexum. SPLV selecciona baja volatilidad, no beta baja. Se utiliza porque conserva el universo S&P 500 y una implementación long-only; su beta realizada se calcula y se contrasta con el objetivo 0,70. Los resultados obtenidos con estas series son insumos provisionales de asignación, no evidencia del alpha de las reglas propias.
C7: Inicio retornos | D7: 42338 | E7: Mes | F7: Primer retorno comparable
C8: Fin | D8: 46265 | E8: Mes | F8: Último mes completo
C9: Niveles comunes | D9: 131 | E9: meses | F9: Oct-2015 a Ago-2026
C10: Retornos comunes | D10: 130 | E10: meses | F10: Nov-2015 a Ago-2026
C11: Estado | D11: PROVISIONAL | F11: Apto para Markowitz exploratorio
C14: 1. MÉTRICAS DE LAS PROXIES EN LA VENTANA COMÚN | P14: CONTROLES
C15: Serie | D15: Rol | E15: CAGR | F15: Vol. anual | G15: Beta vs SPY | H15: Correlación SPY | I15: Retorno anual aritm. | J15: Benchmark | K15: TE anual | L15: Retorno activo anual | M15: IR | N15: Estado | P15: Control | Q15: Resultado | R15: Objetivo | S15: Estado
C16: SPMO | D16: Proxy Momentum | E16: =('05_Datos_Historicos'!I214/'05_Datos_Historicos'!I84)^(12/130)-1 | F16: =STDEV.S('05_Datos_Historicos'!S85:S214)*SQRT(12) | G16: =COVARIANCE.S('05_Datos_Historicos'!S85:S214,'05_Datos_Historicos'!Q85:Q214)/VAR.S('05_Datos_Historicos'!Q85:Q214) | H16: =CORREL('05_Datos_Historicos'!S85:S214,'05_Datos_Historicos'!Q85:Q214) | I16: =AVERAGE('05_Datos_Historicos'!S85:S214)*12 | J16: SPY | K16: =STDEV.S(F23:F152)*SQRT(12) | L16: =AVERAGE(F23:F152)*12 | M16: =IF(K16=0,0,L16/K16) | N16: Provisional | P16: Retornos comunes | Q16: =COUNT(D23:D152) | R16: 130 | S16: =IF(ABS(Q16-R16)<0.00001,"OK","REVISAR")
C17: SPLV | D17: Proxy BAB long-only | E17: =('05_Datos_Historicos'!J214/'05_Datos_Historicos'!J84)^(12/130)-1 | F17: =STDEV.S('05_Datos_Historicos'!T85:T214)*SQRT(12) | G17: =COVARIANCE.S('05_Datos_Historicos'!T85:T214,'05_Datos_Historicos'!Q85:Q214)/VAR.S('05_Datos_Historicos'!Q85:Q214) | H17: =CORREL('05_Datos_Historicos'!T85:T214,'05_Datos_Historicos'!Q85:Q214) | I17: =AVERAGE('05_Datos_Historicos'!T85:T214)*12 | J17: β0,70×SPY + 0,30×BIL | K17: =STDEV.S(I23:I152)*SQRT(12) | L17: =AVERAGE(I23:I152)*12 | M17: =IF(K17=0,0,L17/K17) | N17: Provisional | P17: SPMO sin backfill | Q17: =COUNT('05_Datos_Historicos'!I27:I83) | R17: 0 | S17: =IF(ABS(Q17-R17)<0.00001,"OK","REVISAR")
C18: SPY | D18: Referencia mercado | E18: =('05_Datos_Historicos'!G214/'05_Datos_Historicos'!G84)^(12/130)-1 | F18: =STDEV.S('05_Datos_Historicos'!Q85:Q214)*SQRT(12) | G18: 1 | H18: 1 | I18: =AVERAGE('05_Datos_Historicos'!Q85:Q214)*12 | J18: — | N18: Referencia | P18: Beta SPLV en rango 0,50–0,90 | Q18: =IF(G17>0,1,0) | R18: 1 | S18: =IF(ABS(Q18-R18)<0.00001,"OK","REVISAR")
P19: Beta objetivo declarada | Q19: ='06_Parametros_Estrategias'!E43 | R19: 0.7 | S19: =IF(ABS(Q19-R19)<0.00001,"OK","REVISAR")
P20: Proxies identificadas | Q20: 1 | R20: 1 | S20: =IF(ABS(Q20-R20)<0.00001,"OK","REVISAR")
C21: 2. RETORNOS, BENCHMARKS Y DIFERENCIA ACTIVA | P21: Apto Markowitz preliminar | Q21: =IF(AND(Q16=R16,Q17=R17,Q18=R18,Q19=R19,Q20=R20),1,0) | R21: 1 | S21: =IF(ABS(Q21-R21)<0.00001,"OK","REVISAR")
C22: Fecha | D22: SPMO | E22: SPY | F22: Activo Momentum | G22: SPLV | H22: BAB beta-matched | I22: Activo BAB | J22: BIL | K22: Índice SPMO | L22: Índice SPLV
C23: ='05_Datos_Historicos'!M85 | D23: ='05_Datos_Historicos'!S85 | E23: ='05_Datos_Historicos'!Q85 | F23: =D23-E23 | G23: ='05_Datos_Historicos'!T85 | H23: ='06_Parametros_Estrategias'!E43*E23+(1-'06_Parametros_Estrategias'!E43)*J23 | I23: =G23-H23 | J23: ='05_Datos_Historicos'!R85 | K23: =100*(1+D23) | L23: =100*(1+G23)
C24: ='05_Datos_Historicos'!M86 | D24: ='05_Datos_Historicos'!S86 | E24: ='05_Datos_Historicos'!Q86 | F24: =D24-E24 | G24: ='05_Datos_Historicos'!T86 | H24: ='06_Parametros_Estrategias'!E43*E24+(1-'06_Parametros_Estrategias'!E43)*J24 | I24: =G24-H24 | J24: ='05_Datos_Historicos'!R86 | K24: =K23*(1+D24) | L24: =L23*(1+G24) | P24: LIMITACIÓN MATERIAL Esta hoja permite que el siguiente módulo calcule una frontera eficiente preliminar. Sin embargo: • SPMO no es el screening propio de Momentum. • SPLV usa baja volatilidad, no beta como criterio directo. • El alpha y Tracking Error observados pertenecen a las proxies. • La asignación obtenida deberá repetirse cuando se carguen los backtests point-in-time definitivos.
C25: ='05_Datos_Historicos'!M87 | D25: ='05_Datos_Historicos'!S87 | E25: ='05_Datos_Historicos'!Q87 | F25: =D25-E25 | G25: ='05_Datos_Historicos'!T87 | H25: ='06_Parametros_Estrategias'!E43*E25+(1-'06_Parametros_Estrategias'!E43)*J25 | I25: =G25-H25 | J25: ='05_Datos_Historicos'!R87 | K25: =K24*(1+D25) | L25: =L24*(1+G25)
C26: ='05_Datos_Historicos'!M88 | D26: ='05_Datos_Historicos'!S88 | E26: ='05_Datos_Historicos'!Q88 | F26: =D26-E26 | G26: ='05_Datos_Historicos'!T88 | H26: ='06_Parametros_Estrategias'!E43*E26+(1-'06_Parametros_Estrategias'!E43)*J26 | I26: =G26-H26 | J26: ='05_Datos_Historicos'!R88 | K26: =K25*(1+D26) | L26: =L25*(1+G26)
C27: ='05_Datos_Historicos'!M89 | D27: ='05_Datos_Historicos'!S89 | E27: ='05_Datos_Historicos'!Q89 | F27: =D27-E27 | G27: ='05_Datos_Historicos'!T89 | H27: ='06_Parametros_Estrategias'!E43*E27+(1-'06_Parametros_Estrategias'!E43)*J27 | I27: =G27-H27 | J27: ='05_Datos_Historicos'!R89 | K27: =K26*(1+D27) | L27: =L26*(1+G27)
C28: ='05_Datos_Historicos'!M90 | D28: ='05_Datos_Historicos'!S90 | E28: ='05_Datos_Historicos'!Q90 | F28: =D28-E28 | G28: ='05_Datos_Historicos'!T90 | H28: ='06_Parametros_Estrategias'!E43*E28+(1-'06_Parametros_Estrategias'!E43)*J28 | I28: =G28-H28 | J28: ='05_Datos_Historicos'!R90 | K28: =K27*(1+D28) | L28: =L27*(1+G28)
C29: ='05_Datos_Historicos'!M91 | D29: ='05_Datos_Historicos'!S91 | E29: ='05_Datos_Historicos'!Q91 | F29: =D29-E29 | G29: ='05_Datos_Historicos'!T91 | H29: ='06_Parametros_Estrategias'!E43*E29+(1-'06_Parametros_Estrategias'!E43)*J29 | I29: =G29-H29 | J29: ='05_Datos_Historicos'!R91 | K29: =K28*(1+D29) | L29: =L28*(1+G29)
C30: ='05_Datos_Historicos'!M92 | D30: ='05_Datos_Historicos'!S92 | E30: ='05_Datos_Historicos'!Q92 | F30: =D30-E30 | G30: ='05_Datos_Historicos'!T92 | H30: ='06_Parametros_Estrategias'!E43*E30+(1-'06_Parametros_Estrategias'!E43)*J30 | I30: =G30-H30 | J30: ='05_Datos_Historicos'!R92 | K30: =K29*(1+D30) | L30: =L29*(1+G30)
C31: ='05_Datos_Historicos'!M93 | D31: ='05_Datos_Historicos'!S93 | E31: ='05_Datos_Historicos'!Q93 | F31: =D31-E31 | G31: ='05_Datos_Historicos'!T93 | H31: ='06_Parametros_Estrategias'!E43*E31+(1-'06_Parametros_Estrategias'!E43)*J31 | I31: =G31-H31 | J31: ='05_Datos_Historicos'!R93 | K31: =K30*(1+D31) | L31: =L30*(1+G31)
C32: ='05_Datos_Historicos'!M94 | D32: ='05_Datos_Historicos'!S94 | E32: ='05_Datos_Historicos'!Q94 | F32: =D32-E32 | G32: ='05_Datos_Historicos'!T94 | H32: ='06_Parametros_Estrategias'!E43*E32+(1-'06_Parametros_Estrategias'!E43)*J32 | I32: =G32-H32 | J32: ='05_Datos_Historicos'!R94 | K32: =K31*(1+D32) | L32: =L31*(1+G32)
C33: ='05_Datos_Historicos'!M95 | D33: ='05_Datos_Historicos'!S95 | E33: ='05_Datos_Historicos'!Q95 | F33: =D33-E33 | G33: ='05_Datos_Historicos'!T95 | H33: ='06_Parametros_Estrategias'!E43*E33+(1-'06_Parametros_Estrategias'!E43)*J33 | I33: =G33-H33 | J33: ='05_Datos_Historicos'!R95 | K33: =K32*(1+D33) | L33: =L32*(1+G33)
C34: ='05_Datos_Historicos'!M96 | D34: ='05_Datos_Historicos'!S96 | E34: ='05_Datos_Historicos'!Q96 | F34: =D34-E34 | G34: ='05_Datos_Historicos'!T96 | H34: ='06_Parametros_Estrategias'!E43*E34+(1-'06_Parametros_Estrategias'!E43)*J34 | I34: =G34-H34 | J34: ='05_Datos_Historicos'!R96 | K34: =K33*(1+D34) | L34: =L33*(1+G34)
C35: ='05_Datos_Historicos'!M97 | D35: ='05_Datos_Historicos'!S97 | E35: ='05_Datos_Historicos'!Q97 | F35: =D35-E35 | G35: ='05_Datos_Historicos'!T97 | H35: ='06_Parametros_Estrategias'!E43*E35+(1-'06_Parametros_Estrategias'!E43)*J35 | I35: =G35-H35 | J35: ='05_Datos_Historicos'!R97 | K35: =K34*(1+D35) | L35: =L34*(1+G35)
C36: ='05_Datos_Historicos'!M98 | D36: ='05_Datos_Historicos'!S98 | E36: ='05_Datos_Historicos'!Q98 | F36: =D36-E36 | G36: ='05_Datos_Historicos'!T98 | H36: ='06_Parametros_Estrategias'!E43*E36+(1-'06_Parametros_Estrategias'!E43)*J36 | I36: =G36-H36 | J36: ='05_Datos_Historicos'!R98 | K36: =K35*(1+D36) | L36: =L35*(1+G36)
C37: ='05_Datos_Historicos'!M99 | D37: ='05_Datos_Historicos'!S99 | E37: ='05_Datos_Historicos'!Q99 | F37: =D37-E37 | G37: ='05_Datos_Historicos'!T99 | H37: ='06_Parametros_Estrategias'!E43*E37+(1-'06_Parametros_Estrategias'!E43)*J37 | I37: =G37-H37 | J37: ='05_Datos_Historicos'!R99 | K37: =K36*(1+D37) | L37: =L36*(1+G37)
C38: ='05_Datos_Historicos'!M100 | D38: ='05_Datos_Historicos'!S100 | E38: ='05_Datos_Historicos'!Q100 | F38: =D38-E38 | G38: ='05_Datos_Historicos'!T100 | H38: ='06_Parametros_Estrategias'!E43*E38+(1-'06_Parametros_Estrategias'!E43)*J38 | I38: =G38-H38 | J38: ='05_Datos_Historicos'!R100 | K38: =K37*(1+D38) | L38: =L37*(1+G38)
C39: ='05_Datos_Historicos'!M101 | D39: ='05_Datos_Historicos'!S101 | E39: ='05_Datos_Historicos'!Q101 | F39: =D39-E39 | G39: ='05_Datos_Historicos'!T101 | H39: ='06_Parametros_Estrategias'!E43*E39+(1-'06_Parametros_Estrategias'!E43)*J39 | I39: =G39-H39 | J39: ='05_Datos_Historicos'!R101 | K39: =K38*(1+D39) | L39: =L38*(1+G39)
C40: ='05_Datos_Historicos'!M102 | D40: ='05_Datos_Historicos'!S102 | E40: ='05_Datos_Historicos'!Q102 | F40: =D40-E40 | G40: ='05_Datos_Historicos'!T102 | H40: ='06_Parametros_Estrategias'!E43*E40+(1-'06_Parametros_Estrategias'!E43)*J40 | I40: =G40-H40 | J40: ='05_Datos_Historicos'!R102 | K40: =K39*(1+D40) | L40: =L39*(1+G40)
C41: ='05_Datos_Historicos'!M103 | D41: ='05_Datos_Historicos'!S103 | E41: ='05_Datos_Historicos'!Q103 | F41: =D41-E41 | G41: ='05_Datos_Historicos'!T103 | H41: ='06_Parametros_Estrategias'!E43*E41+(1-'06_Parametros_Estrategias'!E43)*J41 | I41: =G41-H41 | J41: ='05_Datos_Historicos'!R103 | K41: =K40*(1+D41) | L41: =L40*(1+G41)
C42: ='05_Datos_Historicos'!M104 | D42: ='05_Datos_Historicos'!S104 | E42: ='05_Datos_Historicos'!Q104 | F42: =D42-E42 | G42: ='05_Datos_Historicos'!T104 | H42: ='06_Parametros_Estrategias'!E43*E42+(1-'06_Parametros_Estrategias'!E43)*J42 | I42: =G42-H42 | J42: ='05_Datos_Historicos'!R104 | K42: =K41*(1+D42) | L42: =L41*(1+G42)
C43: ='05_Datos_Historicos'!M105 | D43: ='05_Datos_Historicos'!S105 | E43: ='05_Datos_Historicos'!Q105 | F43: =D43-E43 | G43: ='05_Datos_Historicos'!T105 | H43: ='06_Parametros_Estrategias'!E43*E43+(1-'06_Parametros_Estrategias'!E43)*J43 | I43: =G43-H43 | J43: ='05_Datos_Historicos'!R105 | K43: =K42*(1+D43) | L43: =L42*(1+G43)
C44: ='05_Datos_Historicos'!M106 | D44: ='05_Datos_Historicos'!S106 | E44: ='05_Datos_Historicos'!Q106 | F44: =D44-E44 | G44: ='05_Datos_Historicos'!T106 | H44: ='06_Parametros_Estrategias'!E43*E44+(1-'06_Parametros_Estrategias'!E43)*J44 | I44: =G44-H44 | J44: ='05_Datos_Historicos'!R106 | K44: =K43*(1+D44) | L44: =L43*(1+G44)
C45: ='05_Datos_Historicos'!M107 | D45: ='05_Datos_Historicos'!S107 | E45: ='05_Datos_Historicos'!Q107 | F45: =D45-E45 | G45: ='05_Datos_Historicos'!T107 | H45: ='06_Parametros_Estrategias'!E43*E45+(1-'06_Parametros_Estrategias'!E43)*J45 | I45: =G45-H45 | J45: ='05_Datos_Historicos'!R107 | K45: =K44*(1+D45) | L45: =L44*(1+G45)
C46: ='05_Datos_Historicos'!M108 | D46: ='05_Datos_Historicos'!S108 | E46: ='05_Datos_Historicos'!Q108 | F46: =D46-E46 | G46: ='05_Datos_Historicos'!T108 | H46: ='06_Parametros_Estrategias'!E43*E46+(1-'06_Parametros_Estrategias'!E43)*J46 | I46: =G46-H46 | J46: ='05_Datos_Historicos'!R108 | K46: =K45*(1+D46) | L46: =L45*(1+G46)
C47: ='05_Datos_Historicos'!M109 | D47: ='05_Datos_Historicos'!S109 | E47: ='05_Datos_Historicos'!Q109 | F47: =D47-E47 | G47: ='05_Datos_Historicos'!T109 | H47: ='06_Parametros_Estrategias'!E43*E47+(1-'06_Parametros_Estrategias'!E43)*J47 | I47: =G47-H47 | J47: ='05_Datos_Historicos'!R109 | K47: =K46*(1+D47) | L47: =L46*(1+G47)
C48: ='05_Datos_Historicos'!M110 | D48: ='05_Datos_Historicos'!S110 | E48: ='05_Datos_Historicos'!Q110 | F48: =D48-E48 | G48: ='05_Datos_Historicos'!T110 | H48: ='06_Parametros_Estrategias'!E43*E48+(1-'06_Parametros_Estrategias'!E43)*J48 | I48: =G48-H48 | J48: ='05_Datos_Historicos'!R110 | K48: =K47*(1+D48) | L48: =L47*(1+G48)
C49: ='05_Datos_Historicos'!M111 | D49: ='05_Datos_Historicos'!S111 | E49: ='05_Datos_Historicos'!Q111 | F49: =D49-E49 | G49: ='05_Datos_Historicos'!T111 | H49: ='06_Parametros_Estrategias'!E43*E49+(1-'06_Parametros_Estrategias'!E43)*J49 | I49: =G49-H49 | J49: ='05_Datos_Historicos'!R111 | K49: =K48*(1+D49) | L49: =L48*(1+G49)
C50: ='05_Datos_Historicos'!M112 | D50: ='05_Datos_Historicos'!S112 | E50: ='05_Datos_Historicos'!Q112 | F50: =D50-E50 | G50: ='05_Datos_Historicos'!T112 | H50: ='06_Parametros_Estrategias'!E43*E50+(1-'06_Parametros_Estrategias'!E43)*J50 | I50: =G50-H50 | J50: ='05_Datos_Historicos'!R112 | K50: =K49*(1+D50) | L50: =L49*(1+G50)
C51: ='05_Datos_Historicos'!M113 | D51: ='05_Datos_Historicos'!S113 | E51: ='05_Datos_Historicos'!Q113 | F51: =D51-E51 | G51: ='05_Datos_Historicos'!T113 | H51: ='06_Parametros_Estrategias'!E43*E51+(1-'06_Parametros_Estrategias'!E43)*J51 | I51: =G51-H51 | J51: ='05_Datos_Historicos'!R113 | K51: =K50*(1+D51) | L51: =L50*(1+G51)
C52: ='05_Datos_Historicos'!M114 | D52: ='05_Datos_Historicos'!S114 | E52: ='05_Datos_Historicos'!Q114 | F52: =D52-E52 | G52: ='05_Datos_Historicos'!T114 | H52: ='06_Parametros_Estrategias'!E43*E52+(1-'06_Parametros_Estrategias'!E43)*J52 | I52: =G52-H52 | J52: ='05_Datos_Historicos'!R114 | K52: =K51*(1+D52) | L52: =L51*(1+G52)
C53: ='05_Datos_Historicos'!M115 | D53: ='05_Datos_Historicos'!S115 | E53: ='05_Datos_Historicos'!Q115 | F53: =D53-E53 | G53: ='05_Datos_Historicos'!T115 | H53: ='06_Parametros_Estrategias'!E43*E53+(1-'06_Parametros_Estrategias'!E43)*J53 | I53: =G53-H53 | J53: ='05_Datos_Historicos'!R115 | K53: =K52*(1+D53) | L53: =L52*(1+G53)
C54: ='05_Datos_Historicos'!M116 | D54: ='05_Datos_Historicos'!S116 | E54: ='05_Datos_Historicos'!Q116 | F54: =D54-E54 | G54: ='05_Datos_Historicos'!T116 | H54: ='06_Parametros_Estrategias'!E43*E54+(1-'06_Parametros_Estrategias'!E43)*J54 | I54: =G54-H54 | J54: ='05_Datos_Historicos'!R116 | K54: =K53*(1+D54) | L54: =L53*(1+G54)
C55: ='05_Datos_Historicos'!M117 | D55: ='05_Datos_Historicos'!S117 | E55: ='05_Datos_Historicos'!Q117 | F55: =D55-E55 | G55: ='05_Datos_Historicos'!T117 | H55: ='06_Parametros_Estrategias'!E43*E55+(1-'06_Parametros_Estrategias'!E43)*J55 | I55: =G55-H55 | J55: ='05_Datos_Historicos'!R117 | K55: =K54*(1+D55) | L55: =L54*(1+G55)
C56: ='05_Datos_Historicos'!M118 | D56: ='05_Datos_Historicos'!S118 | E56: ='05_Datos_Historicos'!Q118 | F56: =D56-E56 | G56: ='05_Datos_Historicos'!T118 | H56: ='06_Parametros_Estrategias'!E43*E56+(1-'06_Parametros_Estrategias'!E43)*J56 | I56: =G56-H56 | J56: ='05_Datos_Historicos'!R118 | K56: =K55*(1+D56) | L56: =L55*(1+G56)
C57: ='05_Datos_Historicos'!M119 | D57: ='05_Datos_Historicos'!S119 | E57: ='05_Datos_Historicos'!Q119 | F57: =D57-E57 | G57: ='05_Datos_Historicos'!T119 | H57: ='06_Parametros_Estrategias'!E43*E57+(1-'06_Parametros_Estrategias'!E43)*J57 | I57: =G57-H57 | J57: ='05_Datos_Historicos'!R119 | K57: =K56*(1+D57) | L57: =L56*(1+G57)
C58: ='05_Datos_Historicos'!M120 | D58: ='05_Datos_Historicos'!S120 | E58: ='05_Datos_Historicos'!Q120 | F58: =D58-E58 | G58: ='05_Datos_Historicos'!T120 | H58: ='06_Parametros_Estrategias'!E43*E58+(1-'06_Parametros_Estrategias'!E43)*J58 | I58: =G58-H58 | J58: ='05_Datos_Historicos'!R120 | K58: =K57*(1+D58) | L58: =L57*(1+G58)
C59: ='05_Datos_Historicos'!M121 | D59: ='05_Datos_Historicos'!S121 | E59: ='05_Datos_Historicos'!Q121 | F59: =D59-E59 | G59: ='05_Datos_Historicos'!T121 | H59: ='06_Parametros_Estrategias'!E43*E59+(1-'06_Parametros_Estrategias'!E43)*J59 | I59: =G59-H59 | J59: ='05_Datos_Historicos'!R121 | K59: =K58*(1+D59) | L59: =L58*(1+G59)
C60: ='05_Datos_Historicos'!M122 | D60: ='05_Datos_Historicos'!S122 | E60: ='05_Datos_Historicos'!Q122 | F60: =D60-E60 | G60: ='05_Datos_Historicos'!T122 | H60: ='06_Parametros_Estrategias'!E43*E60+(1-'06_Parametros_Estrategias'!E43)*J60 | I60: =G60-H60 | J60: ='05_Datos_Historicos'!R122 | K60: =K59*(1+D60) | L60: =L59*(1+G60)
C61: ='05_Datos_Historicos'!M123 | D61: ='05_Datos_Historicos'!S123 | E61: ='05_Datos_Historicos'!Q123 | F61: =D61-E61 | G61: ='05_Datos_Historicos'!T123 | H61: ='06_Parametros_Estrategias'!E43*E61+(1-'06_Parametros_Estrategias'!E43)*J61 | I61: =G61-H61 | J61: ='05_Datos_Historicos'!R123 | K61: =K60*(1+D61) | L61: =L60*(1+G61)
C62: ='05_Datos_Historicos'!M124 | D62: ='05_Datos_Historicos'!S124 | E62: ='05_Datos_Historicos'!Q124 | F62: =D62-E62 | G62: ='05_Datos_Historicos'!T124 | H62: ='06_Parametros_Estrategias'!E43*E62+(1-'06_Parametros_Estrategias'!E43)*J62 | I62: =G62-H62 | J62: ='05_Datos_Historicos'!R124 | K62: =K61*(1+D62) | L62: =L61*(1+G62)
C63: ='05_Datos_Historicos'!M125 | D63: ='05_Datos_Historicos'!S125 | E63: ='05_Datos_Historicos'!Q125 | F63: =D63-E63 | G63: ='05_Datos_Historicos'!T125 | H63: ='06_Parametros_Estrategias'!E43*E63+(1-'06_Parametros_Estrategias'!E43)*J63 | I63: =G63-H63 | J63: ='05_Datos_Historicos'!R125 | K63: =K62*(1+D63) | L63: =L62*(1+G63)
C64: ='05_Datos_Historicos'!M126 | D64: ='05_Datos_Historicos'!S126 | E64: ='05_Datos_Historicos'!Q126 | F64: =D64-E64 | G64: ='05_Datos_Historicos'!T126 | H64: ='06_Parametros_Estrategias'!E43*E64+(1-'06_Parametros_Estrategias'!E43)*J64 | I64: =G64-H64 | J64: ='05_Datos_Historicos'!R126 | K64: =K63*(1+D64) | L64: =L63*(1+G64)
C65: ='05_Datos_Historicos'!M127 | D65: ='05_Datos_Historicos'!S127 | E65: ='05_Datos_Historicos'!Q127 | F65: =D65-E65 | G65: ='05_Datos_Historicos'!T127 | H65: ='06_Parametros_Estrategias'!E43*E65+(1-'06_Parametros_Estrategias'!E43)*J65 | I65: =G65-H65 | J65: ='05_Datos_Historicos'!R127 | K65: =K64*(1+D65) | L65: =L64*(1+G65)
C66: ='05_Datos_Historicos'!M128 | D66: ='05_Datos_Historicos'!S128 | E66: ='05_Datos_Historicos'!Q128 | F66: =D66-E66 | G66: ='05_Datos_Historicos'!T128 | H66: ='06_Parametros_Estrategias'!E43*E66+(1-'06_Parametros_Estrategias'!E43)*J66 | I66: =G66-H66 | J66: ='05_Datos_Historicos'!R128 | K66: =K65*(1+D66) | L66: =L65*(1+G66)
C67: ='05_Datos_Historicos'!M129 | D67: ='05_Datos_Historicos'!S129 | E67: ='05_Datos_Historicos'!Q129 | F67: =D67-E67 | G67: ='05_Datos_Historicos'!T129 | H67: ='06_Parametros_Estrategias'!E43*E67+(1-'06_Parametros_Estrategias'!E43)*J67 | I67: =G67-H67 | J67: ='05_Datos_Historicos'!R129 | K67: =K66*(1+D67) | L67: =L66*(1+G67)
C68: ='05_Datos_Historicos'!M130 | D68: ='05_Datos_Historicos'!S130 | E68: ='05_Datos_Historicos'!Q130 | F68: =D68-E68 | G68: ='05_Datos_Historicos'!T130 | H68: ='06_Parametros_Estrategias'!E43*E68+(1-'06_Parametros_Estrategias'!E43)*J68 | I68: =G68-H68 | J68: ='05_Datos_Historicos'!R130 | K68: =K67*(1+D68) | L68: =L67*(1+G68)
C69: ='05_Datos_Historicos'!M131 | D69: ='05_Datos_Historicos'!S131 | E69: ='05_Datos_Historicos'!Q131 | F69: =D69-E69 | G69: ='05_Datos_Historicos'!T131 | H69: ='06_Parametros_Estrategias'!E43*E69+(1-'06_Parametros_Estrategias'!E43)*J69 | I69: =G69-H69 | J69: ='05_Datos_Historicos'!R131 | K69: =K68*(1+D69) | L69: =L68*(1+G69)
C70: ='05_Datos_Historicos'!M132 | D70: ='05_Datos_Historicos'!S132 | E70: ='05_Datos_Historicos'!Q132 | F70: =D70-E70 | G70: ='05_Datos_Historicos'!T132 | H70: ='06_Parametros_Estrategias'!E43*E70+(1-'06_Parametros_Estrategias'!E43)*J70 | I70: =G70-H70 | J70: ='05_Datos_Historicos'!R132 | K70: =K69*(1+D70) | L70: =L69*(1+G70)
C71: ='05_Datos_Historicos'!M133 | D71: ='05_Datos_Historicos'!S133 | E71: ='05_Datos_Historicos'!Q133 | F71: =D71-E71 | G71: ='05_Datos_Historicos'!T133 | H71: ='06_Parametros_Estrategias'!E43*E71+(1-'06_Parametros_Estrategias'!E43)*J71 | I71: =G71-H71 | J71: ='05_Datos_Historicos'!R133 | K71: =K70*(1+D71) | L71: =L70*(1+G71)
C72: ='05_Datos_Historicos'!M134 | D72: ='05_Datos_Historicos'!S134 | E72: ='05_Datos_Historicos'!Q134 | F72: =D72-E72 | G72: ='05_Datos_Historicos'!T134 | H72: ='06_Parametros_Estrategias'!E43*E72+(1-'06_Parametros_Estrategias'!E43)*J72 | I72: =G72-H72 | J72: ='05_Datos_Historicos'!R134 | K72: =K71*(1+D72) | L72: =L71*(1+G72)
C73: ='05_Datos_Historicos'!M135 | D73: ='05_Datos_Historicos'!S135 | E73: ='05_Datos_Historicos'!Q135 | F73: =D73-E73 | G73: ='05_Datos_Historicos'!T135 | H73: ='06_Parametros_Estrategias'!E43*E73+(1-'06_Parametros_Estrategias'!E43)*J73 | I73: =G73-H73 | J73: ='05_Datos_Historicos'!R135 | K73: =K72*(1+D73) | L73: =L72*(1+G73)
C74: ='05_Datos_Historicos'!M136 | D74: ='05_Datos_Historicos'!S136 | E74: ='05_Datos_Historicos'!Q136 | F74: =D74-E74 | G74: ='05_Datos_Historicos'!T136 | H74: ='06_Parametros_Estrategias'!E43*E74+(1-'06_Parametros_Estrategias'!E43)*J74 | I74: =G74-H74 | J74: ='05_Datos_Historicos'!R136 | K74: =K73*(1+D74) | L74: =L73*(1+G74)
C75: ='05_Datos_Historicos'!M137 | D75: ='05_Datos_Historicos'!S137 | E75: ='05_Datos_Historicos'!Q137 | F75: =D75-E75 | G75: ='05_Datos_Historicos'!T137 | H75: ='06_Parametros_Estrategias'!E43*E75+(1-'06_Parametros_Estrategias'!E43)*J75 | I75: =G75-H75 | J75: ='05_Datos_Historicos'!R137 | K75: =K74*(1+D75) | L75: =L74*(1+G75)
C76: ='05_Datos_Historicos'!M138 | D76: ='05_Datos_Historicos'!S138 | E76: ='05_Datos_Historicos'!Q138 | F76: =D76-E76 | G76: ='05_Datos_Historicos'!T138 | H76: ='06_Parametros_Estrategias'!E43*E76+(1-'06_Parametros_Estrategias'!E43)*J76 | I76: =G76-H76 | J76: ='05_Datos_Historicos'!R138 | K76: =K75*(1+D76) | L76: =L75*(1+G76)
C77: ='05_Datos_Historicos'!M139 | D77: ='05_Datos_Historicos'!S139 | E77: ='05_Datos_Historicos'!Q139 | F77: =D77-E77 | G77: ='05_Datos_Historicos'!T139 | H77: ='06_Parametros_Estrategias'!E43*E77+(1-'06_Parametros_Estrategias'!E43)*J77 | I77: =G77-H77 | J77: ='05_Datos_Historicos'!R139 | K77: =K76*(1+D77) | L77: =L76*(1+G77)
C78: ='05_Datos_Historicos'!M140 | D78: ='05_Datos_Historicos'!S140 | E78: ='05_Datos_Historicos'!Q140 | F78: =D78-E78 | G78: ='05_Datos_Historicos'!T140 | H78: ='06_Parametros_Estrategias'!E43*E78+(1-'06_Parametros_Estrategias'!E43)*J78 | I78: =G78-H78 | J78: ='05_Datos_Historicos'!R140 | K78: =K77*(1+D78) | L78: =L77*(1+G78)
C79: ='05_Datos_Historicos'!M141 | D79: ='05_Datos_Historicos'!S141 | E79: ='05_Datos_Historicos'!Q141 | F79: =D79-E79 | G79: ='05_Datos_Historicos'!T141 | H79: ='06_Parametros_Estrategias'!E43*E79+(1-'06_Parametros_Estrategias'!E43)*J79 | I79: =G79-H79 | J79: ='05_Datos_Historicos'!R141 | K79: =K78*(1+D79) | L79: =L78*(1+G79)
C80: ='05_Datos_Historicos'!M142 | D80: ='05_Datos_Historicos'!S142 | E80: ='05_Datos_Historicos'!Q142 | F80: =D80-E80 | G80: ='05_Datos_Historicos'!T142 | H80: ='06_Parametros_Estrategias'!E43*E80+(1-'06_Parametros_Estrategias'!E43)*J80 | I80: =G80-H80 | J80: ='05_Datos_Historicos'!R142 | K80: =K79*(1+D80) | L80: =L79*(1+G80)
C81: ='05_Datos_Historicos'!M143 | D81: ='05_Datos_Historicos'!S143 | E81: ='05_Datos_Historicos'!Q143 | F81: =D81-E81 | G81: ='05_Datos_Historicos'!T143 | H81: ='06_Parametros_Estrategias'!E43*E81+(1-'06_Parametros_Estrategias'!E43)*J81 | I81: =G81-H81 | J81: ='05_Datos_Historicos'!R143 | K81: =K80*(1+D81) | L81: =L80*(1+G81)
C82: ='05_Datos_Historicos'!M144 | D82: ='05_Datos_Historicos'!S144 | E82: ='05_Datos_Historicos'!Q144 | F82: =D82-E82 | G82: ='05_Datos_Historicos'!T144 | H82: ='06_Parametros_Estrategias'!E43*E82+(1-'06_Parametros_Estrategias'!E43)*J82 | I82: =G82-H82 | J82: ='05_Datos_Historicos'!R144 | K82: =K81*(1+D82) | L82: =L81*(1+G82)
C83: ='05_Datos_Historicos'!M145 | D83: ='05_Datos_Historicos'!S145 | E83: ='05_Datos_Historicos'!Q145 | F83: =D83-E83 | G83: ='05_Datos_Historicos'!T145 | H83: ='06_Parametros_Estrategias'!E43*E83+(1-'06_Parametros_Estrategias'!E43)*J83 | I83: =G83-H83 | J83: ='05_Datos_Historicos'!R145 | K83: =K82*(1+D83) | L83: =L82*(1+G83)
C84: ='05_Datos_Historicos'!M146 | D84: ='05_Datos_Historicos'!S146 | E84: ='05_Datos_Historicos'!Q146 | F84: =D84-E84 | G84: ='05_Datos_Historicos'!T146 | H84: ='06_Parametros_Estrategias'!E43*E84+(1-'06_Parametros_Estrategias'!E43)*J84 | I84: =G84-H84 | J84: ='05_Datos_Historicos'!R146 | K84: =K83*(1+D84) | L84: =L83*(1+G84)
C85: ='05_Datos_Historicos'!M147 | D85: ='05_Datos_Historicos'!S147 | E85: ='05_Datos_Historicos'!Q147 | F85: =D85-E85 | G85: ='05_Datos_Historicos'!T147 | H85: ='06_Parametros_Estrategias'!E43*E85+(1-'06_Parametros_Estrategias'!E43)*J85 | I85: =G85-H85 | J85: ='05_Datos_Historicos'!R147 | K85: =K84*(1+D85) | L85: =L84*(1+G85)
C86: ='05_Datos_Historicos'!M148 | D86: ='05_Datos_Historicos'!S148 | E86: ='05_Datos_Historicos'!Q148 | F86: =D86-E86 | G86: ='05_Datos_Historicos'!T148 | H86: ='06_Parametros_Estrategias'!E43*E86+(1-'06_Parametros_Estrategias'!E43)*J86 | I86: =G86-H86 | J86: ='05_Datos_Historicos'!R148 | K86: =K85*(1+D86) | L86: =L85*(1+G86)
C87: ='05_Datos_Historicos'!M149 | D87: ='05_Datos_Historicos'!S149 | E87: ='05_Datos_Historicos'!Q149 | F87: =D87-E87 | G87: ='05_Datos_Historicos'!T149 | H87: ='06_Parametros_Estrategias'!E43*E87+(1-'06_Parametros_Estrategias'!E43)*J87 | I87: =G87-H87 | J87: ='05_Datos_Historicos'!R149 | K87: =K86*(1+D87) | L87: =L86*(1+G87)
C88: ='05_Datos_Historicos'!M150 | D88: ='05_Datos_Historicos'!S150 | E88: ='05_Datos_Historicos'!Q150 | F88: =D88-E88 | G88: ='05_Datos_Historicos'!T150 | H88: ='06_Parametros_Estrategias'!E43*E88+(1-'06_Parametros_Estrategias'!E43)*J88 | I88: =G88-H88 | J88: ='05_Datos_Historicos'!R150 | K88: =K87*(1+D88) | L88: =L87*(1+G88)
C89: ='05_Datos_Historicos'!M151 | D89: ='05_Datos_Historicos'!S151 | E89: ='05_Datos_Historicos'!Q151 | F89: =D89-E89 | G89: ='05_Datos_Historicos'!T151 | H89: ='06_Parametros_Estrategias'!E43*E89+(1-'06_Parametros_Estrategias'!E43)*J89 | I89: =G89-H89 | J89: ='05_Datos_Historicos'!R151 | K89: =K88*(1+D89) | L89: =L88*(1+G89)
C90: ='05_Datos_Historicos'!M152 | D90: ='05_Datos_Historicos'!S152 | E90: ='05_Datos_Historicos'!Q152 | F90: =D90-E90 | G90: ='05_Datos_Historicos'!T152 | H90: ='06_Parametros_Estrategias'!E43*E90+(1-'06_Parametros_Estrategias'!E43)*J90 | I90: =G90-H90 | J90: ='05_Datos_Historicos'!R152 | K90: =K89*(1+D90) | L90: =L89*(1+G90)
C91: ='05_Datos_Historicos'!M153 | D91: ='05_Datos_Historicos'!S153 | E91: ='05_Datos_Historicos'!Q153 | F91: =D91-E91 | G91: ='05_Datos_Historicos'!T153 | H91: ='06_Parametros_Estrategias'!E43*E91+(1-'06_Parametros_Estrategias'!E43)*J91 | I91: =G91-H91 | J91: ='05_Datos_Historicos'!R153 | K91: =K90*(1+D91) | L91: =L90*(1+G91)
C92: ='05_Datos_Historicos'!M154 | D92: ='05_Datos_Historicos'!S154 | E92: ='05_Datos_Historicos'!Q154 | F92: =D92-E92 | G92: ='05_Datos_Historicos'!T154 | H92: ='06_Parametros_Estrategias'!E43*E92+(1-'06_Parametros_Estrategias'!E43)*J92 | I92: =G92-H92 | J92: ='05_Datos_Historicos'!R154 | K92: =K91*(1+D92) | L92: =L91*(1+G92)
C93: ='05_Datos_Historicos'!M155 | D93: ='05_Datos_Historicos'!S155 | E93: ='05_Datos_Historicos'!Q155 | F93: =D93-E93 | G93: ='05_Datos_Historicos'!T155 | H93: ='06_Parametros_Estrategias'!E43*E93+(1-'06_Parametros_Estrategias'!E43)*J93 | I93: =G93-H93 | J93: ='05_Datos_Historicos'!R155 | K93: =K92*(1+D93) | L93: =L92*(1+G93)
C94: ='05_Datos_Historicos'!M156 | D94: ='05_Datos_Historicos'!S156 | E94: ='05_Datos_Historicos'!Q156 | F94: =D94-E94 | G94: ='05_Datos_Historicos'!T156 | H94: ='06_Parametros_Estrategias'!E43*E94+(1-'06_Parametros_Estrategias'!E43)*J94 | I94: =G94-H94 | J94: ='05_Datos_Historicos'!R156 | K94: =K93*(1+D94) | L94: =L93*(1+G94)
C95: ='05_Datos_Historicos'!M157 | D95: ='05_Datos_Historicos'!S157 | E95: ='05_Datos_Historicos'!Q157 | F95: =D95-E95 | G95: ='05_Datos_Historicos'!T157 | H95: ='06_Parametros_Estrategias'!E43*E95+(1-'06_Parametros_Estrategias'!E43)*J95 | I95: =G95-H95 | J95: ='05_Datos_Historicos'!R157 | K95: =K94*(1+D95) | L95: =L94*(1+G95)
C96: ='05_Datos_Historicos'!M158 | D96: ='05_Datos_Historicos'!S158 | E96: ='05_Datos_Historicos'!Q158 | F96: =D96-E96 | G96: ='05_Datos_Historicos'!T158 | H96: ='06_Parametros_Estrategias'!E43*E96+(1-'06_Parametros_Estrategias'!E43)*J96 | I96: =G96-H96 | J96: ='05_Datos_Historicos'!R158 | K96: =K95*(1+D96) | L96: =L95*(1+G96)
C97: ='05_Datos_Historicos'!M159 | D97: ='05_Datos_Historicos'!S159 | E97: ='05_Datos_Historicos'!Q159 | F97: =D97-E97 | G97: ='05_Datos_Historicos'!T159 | H97: ='06_Parametros_Estrategias'!E43*E97+(1-'06_Parametros_Estrategias'!E43)*J97 | I97: =G97-H97 | J97: ='05_Datos_Historicos'!R159 | K97: =K96*(1+D97) | L97: =L96*(1+G97)
C98: ='05_Datos_Historicos'!M160 | D98: ='05_Datos_Historicos'!S160 | E98: ='05_Datos_Historicos'!Q160 | F98: =D98-E98 | G98: ='05_Datos_Historicos'!T160 | H98: ='06_Parametros_Estrategias'!E43*E98+(1-'06_Parametros_Estrategias'!E43)*J98 | I98: =G98-H98 | J98: ='05_Datos_Historicos'!R160 | K98: =K97*(1+D98) | L98: =L97*(1+G98)
C99: ='05_Datos_Historicos'!M161 | D99: ='05_Datos_Historicos'!S161 | E99: ='05_Datos_Historicos'!Q161 | F99: =D99-E99 | G99: ='05_Datos_Historicos'!T161 | H99: ='06_Parametros_Estrategias'!E43*E99+(1-'06_Parametros_Estrategias'!E43)*J99 | I99: =G99-H99 | J99: ='05_Datos_Historicos'!R161 | K99: =K98*(1+D99) | L99: =L98*(1+G99)
C100: ='05_Datos_Historicos'!M162 | D100: ='05_Datos_Historicos'!S162 | E100: ='05_Datos_Historicos'!Q162 | F100: =D100-E100 | G100: ='05_Datos_Historicos'!T162 | H100: ='06_Parametros_Estrategias'!E43*E100+(1-'06_Parametros_Estrategias'!E43)*J100 | I100: =G100-H100 | J100: ='05_Datos_Historicos'!R162 | K100: =K99*(1+D100) | L100: =L99*(1+G100)
C101: ='05_Datos_Historicos'!M163 | D101: ='05_Datos_Historicos'!S163 | E101: ='05_Datos_Historicos'!Q163 | F101: =D101-E101 | G101: ='05_Datos_Historicos'!T163 | H101: ='06_Parametros_Estrategias'!E43*E101+(1-'06_Parametros_Estrategias'!E43)*J101 | I101: =G101-H101 | J101: ='05_Datos_Historicos'!R163 | K101: =K100*(1+D101) | L101: =L100*(1+G101)
C102: ='05_Datos_Historicos'!M164 | D102: ='05_Datos_Historicos'!S164 | E102: ='05_Datos_Historicos'!Q164 | F102: =D102-E102 | G102: ='05_Datos_Historicos'!T164 | H102: ='06_Parametros_Estrategias'!E43*E102+(1-'06_Parametros_Estrategias'!E43)*J102 | I102: =G102-H102 | J102: ='05_Datos_Historicos'!R164 | K102: =K101*(1+D102) | L102: =L101*(1+G102)
C103: ='05_Datos_Historicos'!M165 | D103: ='05_Datos_Historicos'!S165 | E103: ='05_Datos_Historicos'!Q165 | F103: =D103-E103 | G103: ='05_Datos_Historicos'!T165 | H103: ='06_Parametros_Estrategias'!E43*E103+(1-'06_Parametros_Estrategias'!E43)*J103 | I103: =G103-H103 | J103: ='05_Datos_Historicos'!R165 | K103: =K102*(1+D103) | L103: =L102*(1+G103)
C104: ='05_Datos_Historicos'!M166 | D104: ='05_Datos_Historicos'!S166 | E104: ='05_Datos_Historicos'!Q166 | F104: =D104-E104 | G104: ='05_Datos_Historicos'!T166 | H104: ='06_Parametros_Estrategias'!E43*E104+(1-'06_Parametros_Estrategias'!E43)*J104 | I104: =G104-H104 | J104: ='05_Datos_Historicos'!R166 | K104: =K103*(1+D104) | L104: =L103*(1+G104)
...

Sheet 09_Optimizador_Cartera
C2: MODELO NEXUM - OPTIMIZADOR DE CARTERA (v3: NUCLEO PASIVO / SATELITE ACTIVO)
